Workbook

Sheet Reporte de vacaciones 1
B1: REPORTE DE VACACIONES
B2: EMPLEADOS | C2: FECHA DE INGRESO A RUAG | D2: Fecha de ingreso a planilla | E2: Años correspondiente a vacaciones | F2: Días de vacaciones | G2: Derecho a días de vacaciones | H2: 44119 | I2: Gozados (2012) | J2: Enero - diciembre 2013 | V2: Gozadas (2013) | W2: Enero - diciembre 2014 | AI2: Gozadas (2014) | AJ2: Enero - diciembre 2015 | AV2: Gozadas (2015) | AW2: Enero - diciembre 2016 | BI2: Gozadas (2016) | BJ2: Enero - diciembre 2017 | BV2: Gozadas (2017) | BW2: Enero - diciembre 2018 | CI2: Gozadas (2018) | CJ2: Enero - diciembre 2019 | CV2: Gozadas (2019) | CW2: Enero - diciembre 2020 | DI2: Gozadas (2020 | DJ2: Total días gozados | DK2: PENDIENTE POR GOZAR
H3: Derecho a días de vacaciones
J4: ENE | K4: FEB | L4: MAR | M4: ABR | N4: MAY | O4: JUN | P4: JUL | Q4: AGO | R4: SEP | S4: OCT | T4: NOV | U4: DIC | W4: ENE | X4: FEB | Y4: MAR | Z4: ABR | AA4: MAY | AB4: JUN | AC4: JUL | AD4: AGO | AE4: SEP | AF4: OCT | AG4: NOV | AH4: DIC | AJ4: ENE | AK4: FEB | AL4: MAR | AM4: ABR | AN4: MAY | AO4: JUN | AP4: JUL | AQ4: AGO | AR4: SEP | AS4: OCT | AT4: NOV | AU4: DIC | AW4: ENE | AX4: FEB | AY4: MAR | AZ4: ABR | BA4: MAY | BB4: JUN | BC4: JUL | BD4: AGO | BE4: SEP | BF4: OCT | BG4: NOV | BH4: DIC | BJ4: ENE | BK4: FEB | BL4: MAR | BM4: ABR | BN4: MAY | BO4: JUN | BP4: JUL | BQ4: AGO | BR4: SEP | BS4: OCT | BT4: NOV | BU4: DIC | BW4: ENE | BX4: FEB | BY4: MAR | BZ4: ABR | CA4: MAY | CB4: JUN | CC4: JUL | CD4: AGO | CE4: SEP | CF4: OCT | CG4: NOV | CH4: DIC | CJ4: ENE | CK4: FEB | CL4: MAR | CM4: ABR | CN4: MAY | CO4: JUN | CP4: JUL | CQ4: AGO | CR4: SEP | CS4: OCT | CT4: NOV | CU4: DIC | CW4: ENE | CX4: FEB | CY4: MAR | CZ4: ABR | DA4: MAY | DB4: JUN | DC4: JUL | DD4: AGO | DE4: SEP | DF4: OCT | DG4: NOV | DH4: DIC
A5: 1 | B5: ALARCON PEREZ LUIS | C5: 42736 | D5: 01/01/2017 | E5: 01 ene 2017 al 31 dic 2017 | F5: 30 | G5: =+F5+F6+F8+F7 -> 90 | BO5: 1 | BS5: 1 | BU5: 6 | BV5: =BU5+BS5+BO5 -> 8 | BY5: 1 | CB5: 1 | CC5: 1 | CE5: 7 | CF5: =2+1 -> 3 | CI5: =SUM(BW5:CH8) -> 13 | CV5: =SUM(CJ5:CU8) -> 0 | CW5: 1 | DE5: 9 | DI5: =SUM(CW5:DH8) -> 10 | DJ5: =I5+V5+AI5+AV5+BI5+BV5+CI5+CV5+DI5 -> 31
E6: 01 ene 2018 al 31 dic 2018 | F6: 30 | H6: =ROUNDDOWN((H2-D5)/365,0)*30 -> 90 | DK6: =H6-DJ5 -> 59
E7: 01 ene 2019 al 31 dic 2019 | F7: 30
E8: 01 Ene 2020 al 31 Dic 2020
A9: 3 | B9: ALEJOS TORIBIO, SULELMA MELISA | C9: 01/09/2017 | D9: 01/09/2017 | E9: 01 set 2017 al 31 ago 2018 | F9: 30 | G9: =F9+F10+F11 -> 90 | BS9: 1 | BV9: =SUM(BJ10:BU10) -> 1 | BY9: 1 | BZ9: 2 | CA9: 2 | CB9: 2 | CI9: =SUM(BW9:CH11) -> 7 | CP9: 1 | CU9: 1 | CV9: =SUM(CJ9:CU11) -> 2 | DE9: 13 | DF9: 1 | DI9: =SUM(CW9:DH11) -> 14 | DJ9: =I9+V9+AI9+AV9+BI9+BV9+CI9+CV9+DI9 -> 24 | DK9: =H10-DJ9 -> 66
E10: 01 set 2018 al 31 ago 2019 | F10: 30 | H10: =ROUNDDOWN(($H$2-D9)/365,0)*30 -> 90 | BU10: 1
E11: 01 set 2019 al 31 ago 2020 | F11: 30
A12: 2 | B12: ALHUAY AYESTA, RAMIRO | D12: 01/09/2014 | E12: 01 Set 2014 al 30 Ago 2015 Gozado | F12: 30 | G12: =F12+F13+F17+F14+F15+F16 -> 180 | V12: =SUM(J12:U17) -> 0 | AF12: 5 | AH12: 10 | AI12: =SUM(W12:AH17) -> 15 | AK12: 1 | AM12: 3 | AO12: 6 | AP12: 2 | AQ12: 1 | AV12: =SUM(AJ12:AU17) -> 13 | BG12: 1 | BH12: 15 | BI12: =SUM(AW12:BH17) -> 16 | BM12: 2 | BU12: 6 | BV12: =SUM(BJ12:BU17) -> 8 | BX12: 2 | BZ12: 7 | CD12: 1 | CF12: 3 | CH12: 11 | CI12: =SUM(BW12:CH17) -> 24 | CO12: 15 | CP12: 7 | CR12: 14 | CU12: 12 | CV12: =SUM(CJ12:CU17) -> 48 | CX12: 4 | DF12: 31 | DI12: =SUM(CW12:DH17) -> 35 | DJ12: =I12+V12+AI12+AV12+BI12+BV12+CI12+CV12+DI12 -> 159 | DK12: =H14-DJ12 -> 21
E13: 01 Set 2015 al 30 Ago 2016 Gozado | F13: 30
E14: 01 Set 2016 al 30 Ago 2017 Gozado | F14: 30 | H14: =ROUNDDOWN(($H$2-D12)/365,0)*30 -> 180
E15: 01 Set 2017 al 30 Ago 2018 Gozado | F15: 30
E16: 01 Set 2018 al 30 Ago 2019 Gozados | F16: 30
E17: 01 Set 2019 al 30 Ago 2020 | F17: 30
A18: 4 | B18: ALTAMIRANO SULCA MANUEL | C18: 16/05/2012 BAJA | D18: 01/08/2018 | E18: 01 Ago 2018 al 31 Jul 2019 | F18: 30 | G18: =F18+F19+F20+F21 -> 60 | V18: =SUM(J18:U21) -> 0 | AI18: =SUM(W18:AH21) -> 0 | AV18: =SUM(AJ18:AU21) -> 0 | BG18: 1 | BH18: 7 | CJ18: 14 | CV18: =SUM(CJ18:CU21) -> 14 | DI18: =SUM(CW18:DH21) -> 0 | DJ18: =CV18 -> 14 | DK18: =H20-DJ18 -> 46
C19: 01/02/2019 BAJA | E19: 01 Ago 2019 al 31 Jul 2020 | F19: 30
H20: =ROUNDDOWN(($H$2-D18)/365,0)*30 -> 60
A22: 4 | B22: ARROYO FALLA, VANESSA ALICIA | C22: 16/05/2012 BAJA | D22: 01/04/2019 | E22: 01 abr 2019 al 31 mar 2020 | F22: 30 | G22: =F22+F23+F24+F25 -> 30 | V22: =SUM(J22:U25) -> 0 | AI22: =SUM(W22:AH25) -> 0 | AV22: =SUM(AJ22:AU25) -> 0 | BG22: 1 | BH22: 7 | CP22: 10 | CQ22: 7 | CV22: =SUM(CJ22:CU25) -> 17 | CX22: 10 | CY22: 11 | DI22: =SUM(CW22:DH25) -> 21 | DJ22: =CV22+DI22 -> 38 | DK22: =H24-DJ22 -> -8
C23: 01/02/2019 BAJA
H24: =ROUNDDOWN(($H$2-D22)/365,0)*30 -> 30
A26: 5 | B26: ASPILCUETA GUTIERREZ KAREN | C26: 01 abril 2013 | D26: 01/04/2013 | E26: 01 Abr 2013 al 30 Mar 2014 Gozado | F26: 30 | G26: =F26+F27+F28+F29+F30+F31 -> 180 | N26: 1 | V26: =SUM(J26:U31) -> 1 | AD26: 7 | AH26: 1 | AI26: =SUM(W26:AH31) -> 8 | AJ26: 1 | AK26: 4 | AL26: 2 | AN26: 1 | AP26: 1 | AS26: 1 | AU26: 3 | AV26: =SUM(AJ26:AU31) -> 13 | AW26: 2 | AX26: 1 | AZ26: 1 | BA26: 7 | BC26: 2 | BD26: 1 | BG26: 1 | BH26: 1 | BI26: =SUM(AW26:BH31) -> 16 | BJ26: 2 | BK26: 7 | BM26: 1 | BO26: 1 | BP26: 1 | BQ26: 1 | BS26: 2 | BT26: 1 | BU26: 8 | BV26: =SUM(BJ26:BU31) -> 24 | BW26: 13 | BX26: 1 | CA26: 1 | CC26: 8 | CE26: 1 | CH26: 2 | CI26: =SUM(BW26:CH31) -> 26 | CK26: 7 | CO26: 1 | CP26: 10 | CQ26: 1 | CU26: 1 | CV26: =SUM(CJ26:CU31) -> 20 | CX26: 7 | CY26: 8 | DE26: 15 | DI26: =SUM(CW26:DH31) -> 30 | DJ26: =V26+AI26+AV26+BI26+BV26+CI26+CV26+DI26 -> 138 | DK26: =H29-DJ26 -> 72
E27: 01 Abr 2014 al 30 Mar 2015 Gozado | F27: 30
E28: 01 Abr 2016 al 30 Mar 2017 Gozado | F28: 30
E29: 01 Abr 2017 al 30 Mar 2018 | F29: 30 | H29: =ROUNDDOWN(($H$2-D26)/365,0)*30 -> 210
E30: 01 Abr 2018 al 30 Mar 2019 | F30: 30
E31: 01 Abr 2019 al 30 Mar 2020 | F31: 30
A32: 6 | B32: BACA WIESSE JOSE ALBERTO | C32: 01 junio 2005 | D32: 01/01/2011 | E32: 01 Ene 2011 al 31 Dic 2011 Gozado | F32: 30 | G32: =F32+F33+F34+F35+F36+F37+F38+F39+F40 -> 270 | I32: 45 | K32: 1 | M32: 1 | O32: 4 | P32: 1 | Q32: 3 | U32: 1 | V32: =SUM(J32:U41) -> 11 | W32: 1 | X32: 1 | Z32: 1 | AA32: 4 | AE32: 1 | AF32: 1 | AH32: 3 | AI32: =SUM(W32:AH41) -> 12 | AK32: 4 | AM32: 1 | AO32: 4 | AP32: 2 | AR32: 1 | AS32: 4 | AT32: 1 | AU32: 3 | AV32: =SUM(AJ32:AU41) -> 20 | AX32: 14 | AY32: 2 | BF32: 1 | BG32: 3 | BH32: 3 | BI32: =SUM(AW32:BH41) -> 23 | BV32: =SUM(BJ32:BU41) -> 0 | BX32: 10 | CC32: 1 | CD32: 1 | CI32: =SUM(BW32:CH41) -> 12 | CK32: 11 | CU32: 14 | CV32: =SUM(CJ32:CU41) -> 25 | CX32: 12 | DE32: 15 | DF32: 15 | DI32: =SUM(CW32:DH41) -> 42 | DJ32: =I32+V32+AI32+AV32+BI32+BV32+CI32+CV32+DI32 -> 190 | DK32: =H37-DJ32 -> 80
E33: 01 Ene 2012 al 31 Dic 2012 Gozado | F33: 30
E34: 01 Ene 2013 al 31 Dic 2013 Gozado | F34: 30
E35: 01 Ene 2014 al 31 Dic 2014 Gozado | F35: 30
E36: 01 Ene 2015 al 31 Dic 2015 Gozado | F36: 30
E37: 01 Ene 2016 al 31 Dic 2016 | F37: 30 | H37: =ROUNDDOWN(($H$2-D32)/365,0)*30 -> 270
E38: 01 Ene 2017 al 31 Dic 2017 | F38: 30
E39: 01 Ene 2018 al 31 Dic 2018 | F39: 30
E40: 01 Ene 2019 al 31 Dic 2019 | F40: 30
E41: 01 Ene 2020 al 31 Dic 2020
A42: 7 | B42: BALLENA CASTILLO ITALA ADRIANA | C42: 01 febrero 2010 | D42: 01/03/2011 | E42: 01 Mar 2011 al 28 Feb 2012 gozado | F42: 30 | G42: =F42+F43+F44+F45+F46+F47+F48+F49+F50 -> 270 | I42: 15 | L42: 5 | O42: 5 | P42: 8 | V42: =SUM(J42:U50) -> 18 | AD42: 2 | AE42: 1 | AH42: 3 | AI42: =SUM(W42:AH50) -> 6 | AJ42: 1 | AK42: 15 | AP42: 4 | AQ42: 1 | AV42: =SUM(AJ42:AU50) -> 21 | BB42: 14 | BD42: 1 | BH42: 22 | BI42: =SUM(AW42:BH50) -> 37 | BQ42: 37 | BS42: 1 | BU42: 14 | BV42: =SUM(BJ42:BU50) -> 52 | BW42: 4 | CF42: 30 | CI42: =SUM(BW42:CH50) -> 34 | CM42: 3 | CR42: 8 | CU42: 15 | CV42: =SUM(CJ42:CU50) -> 26 | DI42: =SUM(CW42:DH50) -> 0 | DJ42: =I42+V42+AI42+AV42+BI42+BV42+CI42+CV42+DI42 -> 209 | DK42: =H46-DJ42 -> 61
E43: 01 Mar 2012 al 28 Feb 2013 gozado | F43: 30
E44: 01 Mar 2013 al 28 Feb 2014 gozado | F44: 30
E45: 01 Mar 2014 al 28 Feb 2015 gozado | F45: 30
E46: 01 Mar 2015 al 28 Feb 2016 gozado | F46: 30 | H46: =ROUNDDOWN(($H$2-D42)/365,0)*30 -> 270
E47: 01 Mar 2016 al 28 Feb 2017 pagada | F47: 30
E48: 01 Mar 2017 al 28 Feb 2018 Gozado | F48: 30
E49: 01 Mar 2018 al 31 Feb 2019 | F49: 30
E50: 01 Mar 2019 al 28 Feb 2020 | F50: 30
A51: 8 | B51: BAUTISTA AYESTA HEBER (INGRESO PLANILLA 01/07/2007) | C51: 01 agosto 2005 | D51: 01/07/2011 | E51: 01 Jul 2011 al 30 Jun 2012 Gozado | F51: 30 | G51: =F51+F52+F53+F54+F55+F56+F57+F59+F58 -> 270 | I51: 15 | V51: =SUM(J51:U59) -> 0 | AI51: =SUM(W51:AH51) -> 0 | AK51: 14 | AV51: =SUM(AJ51:AU51) -> 14 | AX51: 1 | AZ51: 1 | BB51: 5 | BI51: =SUM(AW51:BH51) -> 7 | BV51: =SUM(BJ51:BU51) -> 0 | BY51: 15 | CI51: =SUM(BW51:CH51) -> 15 | CP51: 14 | CV51: =SUM(CJ51:CU51) -> 14 | DI51: =SUM(CW51:DH51) -> 0 | DJ51: =I51+V51+AI51+AV51+BI51+BV51+CI51+CV51+DI51 -> 65 | DK51: =H55-DJ51 -> 205
E52: 01 Jul 2012 al 30 Jun 2013 Gozado | F52: 30
E53: 01 Jul 2013 al 30 Jun 2014 | F53: 30
E54: 01 Jul 2014 al 30 Jun 2015 | F54: 30
E55: 01 Jul 2015 al 30 Jun 2016 | F55: 30 | H55: =ROUNDDOWN(($H$2-D51)/365,0)*30 -> 270
E56: 01 Jul 2016 al 30 Jun 2017 | F56: 30
E57: 01 Jul 2017 al 30 Jun 2018 | F57: 30
E58: 01 Jul 2018 al 30 Jun 2019 | F58: 30
E59: 01 Jul 2019 al 30 Jun 2020 | F59: 30
A60: 9 | B60: BAUTISTA AYESTA WALTER (INGRESO A PLANILLA 01/05/2007) | C60: 01 agosto 2005 | D60: 01/05/2011 | E60: 01 May 2011 al 30 Abr 2012 | F60: 30 | G60: =F60+F61+F62+F63+F64+F65+F66+F68+F67 -> 270 | V60: =SUM(J60:U68) -> 0 | AI60: =SUM(W60:AH60) -> 0 | AO60: 6 | AV60: =SUM(AJ60:AU60) -> 6 | BI60: =SUM(AW60:BH60) -> 0 | BV60: =SUM(BJ60:BU60) -> 0 | CI60: =SUM(BW60:CH60) -> 0 | CV60: =SUM(CJ60:CU60) -> 0 | DI60: =SUM(CW60:DH60) -> 0 | DJ60: =SUM(AV60,BI60) -> 6 | DK60: =H63-DJ60 -> 264
E61: 01 May 2012 al 30 Abr 2013 | F61: 30
E62: 01 May 2013 al 30 Abr 2014 | F62: 30
E63: 01 May 2014 al 30 Abr 2015 | F63: 30 | H63: =ROUNDDOWN(($H$2-D60)/365,0)*30 -> 270
E64: 01 May 2015 al 30 Abr 2016 | F64: 30
E65: 01 May 2016 al 30 Abr 2017 | F65: 30
E66: 01 May 2017 al 30 Abr 2018 | F66: 30
E67: 01 May 2018 al 30 Abr 2019 | F67: 30
E68: 01 May 2019 al 30 Abr 2020 | F68: 30
A69: 10 | B69: BRIONES RIVERA, RICHARD | C69: 01 enero 2009 | D69: 01/02/2020 | G69: =F69+F70+F71+F72+F73+F74+F75+F76+F77 -> 0 | DJ69: =I69+V69+AI69+AV69+BI69+BV69+CI69+CV69 -> 0 | DK69: =H73-DJ69 -> 0
H73: =ROUNDDOWN(($H$2-D69)/365,0)*30 -> 0
A78: 12 | B78: COLETO PASTOR LUIS ENRIQUE (INGRESO A PLANILLA 01/10/2010) | D78: 01/10/2011 | E78: 01 Oct 2011 al 30 Set 2012 Gozado | F78: 30 | G78: =F78+F79+F80+F81+F82+F83+F84+F86+F85 -> 270 | V78: =SUM(J78:U80) -> 0 | W78: 10 | AD78: 16 | AE78: 30 | AF78: 30 | AI78: =SUM(W78:AH78) -> 86 | AQ78: 3 | AS78: 23 | AU78: 1 | AV78: =SUM(AJ78:AU78) -> 27 | AW78: 1 | BG78: 1 | BI78: =SUM(AW78:BH78) -> 2 | BL78: 7 | BU78: 4 | BV78: =SUM(BJ78:BU78) -> 11 | BW78: 54 | CI78: =SUM(BW78:CH78) -> 54 | CP78: 9 | CT78: 11 | CV78: =SUM(CJ78:CU78) -> 20 | DI78: =SUM(CW78:DH78) -> 0 | DJ78: =I78+V78+AI78+AV78+BI78+BV78+CI78+CV78 -> 200 | DK78: =H82-DJ78 -> 70
E79: 01 Oct 2012 al 30 Set 2013 Gozado | F79: 30
E80: 01 Oct 2013 al 30 Set 2014 Gozado | F80: 30
E81: 01 Oct 2014 al 30 Set 2015 Gozado | F81: 30
E82: 01 Oct 2015 al 30 Set 2016 Gozado | F82: 30 | H82: =ROUNDDOWN(($H$2-D78)/365,0)*30 -> 270
E83: 01 Oct 2016 al 30 Set 2017 Gozado | F83: 30
E84: 01 Oct 2017 al 30 Set 2018 | F84: 30
E85: 01 Oct 2018 al 30 Set 2019 | F85: 30
E86: 01 Oct 2019 al 30 Set 2020 | F86: 30
A87: 13 | B87: CORDOVA VELEZ, JULISSA | C87: 01 abril 2011 | D87: 01/02/2020 | G87: =F87+F88+F89+F90+F91+F92+F93+F95 -> 0 | P87: 15 | U87: 7 | DJ87: =V87+AI87+AV87+BI87+BV87+CI87+CV87+DI87 -> 0 | DK87: =H91-DJ87 -> 0
H91: =ROUNDDOWN(($H$2-D87)/365,0)*30 -> 0
A96: 16 | B96: DAMBROSIO RIVERO LIZETH STEFANNY | C96: 01 marzo 2007 | D96: 01/01/2019 | E96: 01 ene 2019 al 31 Dic 2019 | F96: 30 | G96: =F96+F97+F100+F98+F99 -> 30 | V96: =SUM(J96:U96) -> 0 | AC96: 1 | AV96: =SUM(AJ96:AU96) -> 0 | BI96: =SUM(AW96:BH96) -> 0 | BV96: =SUM(BJ96:BU100) -> 0 | CI96: =SUM(BW96:CH100) -> 0 | CN96: 3 | CU96: 4 | CV96: =SUM(CJ96:CU100) -> 7 | DD96: 31 | DE96: 2 | DI96: =SUM(CW96:DH100) -> 33 | DJ96: =I96+V96+AI96+AV96+BI96+BV96+CI96+CV96+DI96 -> 40 | DK96: =H98-DJ96 -> -10
E97: 1 ene 2020 al 31 Dic 2020
H98: =ROUNDDOWN(($H$2-D96)/365,0)*30 -> 30
A101: 16 | B101: FLORES GUARDIA CLAUDIA | C101: 01 marzo 2007 | D101: 01/11/2019 | E101: 01 nov 2019 al 31 oct 2020 | F101: 30 | G101: =F101+F102+F106+F103+F104+F105 -> 30 | DE101: 18 | DI101: =SUM(CW101:DH106) -> 18 | DJ101: =I101+V101+AI101+AV101+BI101+BV101+CI101+CV101+DI101 -> 18 | DK101: =H103-DJ101 -> -18
H103: =ROUNDDOWN(($H$2-D101)/365,0)*30 -> 0
A107: 16 | B107: FLORES MANTILLA MARIANA | C107: 01 marzo 2007 | D107: 01/07/2014 | E107: 01 Jul 2014 al 30 Jun 2015 Gozado | F107: 30 | G107: =F107+F108+F112+F109+F110+F111 -> 180 | V107: =SUM(J107:U107) -> 0 | AC107: 1 | AI107: =SUM(AC107:AH112) -> 1 | AK107: 30 | AL107: 30 | AP107: 1 | AV107: =SUM(AJ107:AU107) -> 61 | AX107: 7 | BC107: 3 | BG107: 1 | BI107: =SUM(AW107:BH107) -> 11 | BN107: 1 | BP107: 1 | BU107: 1 | BV107: =SUM(BJ107:BU112) -> 3 | BX107: 1 | BY107: 7 | CC107: 7 | CF107: 8 | CI107: =SUM(BW107:CH112) -> 23 | CL107: 1 | CO107: 7 | CP107: 2 | CV107: =SUM(CJ107:CU112) -> 10 | CX107: 6 | DF107: 2 | DI107: =SUM(CW107:DH112) -> 8 | DJ107: =I107+V107+AI107+AV107+BI107+BV107+CI107+CV107+DI107 -> 117 | DK107: =H109-DJ107 -> 63
E108: 01 Jul 2015 al 30 Jun 2016 Gozado | F108: 30
E109: 01 Jul 2016 al 30 Jun 2017 Gozado | F109: 30 | H109: =ROUNDDOWN(($H$2-D107)/365,0)*30 -> 180
E110: 01 Jul 2017 al 30 Jun 2018 | F110: 30
E111: 01 Jul 2018 al 30 Jun 2019 | F111: 30
E112: 01 Jul 2019 al 30 Jun 2020 | F112: 30
A113: 16 | B113: GOYAS ABRAMONTE JAVIER | C113: 01 marzo 2007 | D113: 01/04/2019 | E113: 01 Abr 2019 al 30 Mar 2020 | F113: 30 | G113: =F113+F114+F118+F115+F116+F117 -> 30 | DI113: =SUM(CW113:DH118) -> 0 | DJ113: =I113+V113+AI113+AV113+BI113+BV113+CI113+CV113+DI113 -> 0 | DK113: =H115-DJ113 -> 30
H115: =ROUNDDOWN(($H$2-D113)/365,0)*30 -> 30
A119: 17 | B119: GRANDE ALCANTARA GERMAN N. (INGRESO A PLANILLA 01/04/2007) | D119: 01/04/2011 | E119: 01 Abr 2011 al 30 Mar 2012 Gozado | F119: 30 | G119: =F119+F120+F121+F122+F123+F124+F125+F126+F127 -> 270 | V119: =SUM(J119:U127) -> 0 | AI119: =SUM(W119:AH127) -> 0 | AK119: 7 | AN119: 2 | AV119: =SUM(AJ119:AU127) -> 9 | AW119: 20 | BG119: 1 | BI119: =SUM(AW119:BH127) -> 21 | BN119: 7 | BP119: 20 | BV119: =SUM(BJ119:BU127) -> 27 | CI119: =SUM(BW119:CH127) -> 0 | CV119: =SUM(CJ119:CU127) -> 0 | CZ119: 30 | DE119: 3 | DI119: =SUM(CW119:DH127) -> 33 | DJ119: =SUM(V119,AI119,AV119,BI119,BV119,CI119:CI119,CV119,DI119) -> 90 | DK119: =H123-DJ119 -> 180
E120: 01 Abr 2012 al 30 Mar 2013 | F120: 30
E121: 01 Abr 2013 al 30 Mar 2014 | F121: 30
E122: 01 Abr 2014 al 30 Mar 2015 | F122: 30
E123: 01 Abr 2015 al 30 Mar 2016 | F123: 30 | H123: =ROUNDDOWN(($H$2-D119)/365,0)*30 -> 270
E124: 01 Abr 2016 al 30 Mar 2017 | F124: 30
E125: 01 Abr 2017 al 30 Mar 2018 | F125: 30
E126: 01 Abr 2018 al 30 Mar 2019 | F126: 30
...

Sheet control de vacaciones
D1: 44119
B2: VACACIONES EMPLEADOS | D2: PENDIENTE POR GOZAR DÍAS
A3: 24 | B3: 1 | C3: ALARCON PEREZ LUIS | D3: ='Reporte de vacaciones 1'!DK6 -> 59
A4: 32 | B4: 2 | C4: ALEJOS TORIBIO, SULELMA MELISA | D4: ='Reporte de vacaciones 1'!DK9 -> 66
A5: 34 | B5: 3 | C5: ALHUAY AYESTA, RAMIRO | D5: ='Reporte de vacaciones 1'!DK12 -> 21
A6: 31 | B6: 4 | C6: ALTAMIRANO SULCA MANUEL | D6: ='Reporte de vacaciones 1'!DK18 -> 46
A7: 16 | B7: 5 | C7: ARROYO FALLA, VANESSA ALICIA | D7: ='Reporte de vacaciones 1'!DK22 -> -8
A8: 7 | B8: 6 | C8: ASPILCUETA GUTIERREZ KAREN | D8: ='Reporte de vacaciones 1'!DK26 -> 72
A9: 13 | B9: 7 | C9: BACA WIESSE JOSE ALBERTO | D9: ='Reporte de vacaciones 1'!DK32 -> 80
A10: 33 | B10: 8 | C10: BALLENA CASTILLO ITALA ADRIANA | D10: ='Reporte de vacaciones 1'!DK42 -> 61
A11: 6 | B11: 9 | C11: BAUTISTA AYESTA HEBER | D11: ='Reporte de vacaciones 1'!DK51 -> 205
A12: 22 | B12: 10 | C12: BAUTISTA AYESTA WALTER | D12: ='Reporte de vacaciones 1'!DK60 -> 264
A13: 9 | B13: 11 | C13: BRIONES RIVERA, RICHARD | D13: ='Reporte de vacaciones 1'!DK69 -> 0
A14: 4 | B14: 12 | C14: COLETO PASTOR LUIS ENRIQUE | D14: ='Reporte de vacaciones 1'!DK78 -> 70
A15: 27 | B15: 13 | C15: CORDOVA VELEZ, JULISSA | D15: ='Reporte de vacaciones 1'!DK87 -> 0
A16: 5 | B16: 14 | C16: DAMBROSIO RIVERO LIZETH STEFANNY | D16: ='Reporte de vacaciones 1'!DK96 -> -10
A17: 4 | B17: 15 | C17: ESPEJO PACHECO, URSULA AMELIA
A18: 3 | B18: 16 | C18: FLORES GUARDIA CLAUDIA | D18: ='Reporte de vacaciones 1'!DK101 -> -18
A19: 10 | B19: 17 | C19: FLORES MANTILLA MARIANA | D19: ='Reporte de vacaciones 1'!DK107 -> 63
A20: 18 | B20: 18 | C20: GOYAS ABRAMONTE, JAVIER ENRRIQUE | D20: ='Reporte de vacaciones 1'!DK113 -> 30
A21: 17 | B21: 19 | C21: GRANDE ALCANTARA GERMAN N. | D21: ='Reporte de vacaciones 1'!DK119 -> 180
A22: 23 | B22: 20 | C22: GRANDE ALCANTARA MILAGROS M. | D22: ='Reporte de vacaciones 1'!DK128 -> 142
A23: 1 | B23: 21 | C23: GRANDE ALCANTARA PAUL | D23: ='Reporte de vacaciones 1'!DK133 -> 91
A24: 2 | B24: 22 | C24: GRANDE ALCANTRA, RAUL NEVADA
B25: 23 | C25: GRANDE PECEROS DAVID | D25: ='Reporte de vacaciones 1'!DK142 -> 13
A26: 8 | B26: 24 | C26: JUAN PEDRO CRUZ, GIOVANNA PAULA | D26: ='Reporte de vacaciones 1'!DK146 -> -9
A27: 19 | B27: 25 | C27: MENDOZA GARCÍA, ZINCIA | D27: ='Reporte de vacaciones 1'!DK155 -> -8
A28: 33 | B28: 26 | C28: OCHOA GUTIERREZ ERICKSON | D28: ='Reporte de vacaciones 1'!DK158 -> 30
A29: 29 | B29: 27 | C29: OROSCO BALAREZO SILVIA | D29: ='Reporte de vacaciones 1'!DK164 -> 0
A30: 12 | B30: 28 | C30: OSCCO GUILLEN EDWIN RAFAEL | D30: ='Reporte de vacaciones 1'!DK170 -> 0
A31: 221 | B31: 29 | C31: OSCCO GUILLEN ZORAIDA | D31: ='Reporte de vacaciones 1'!DK176 -> 56
A32: 24 | B32: 30 | C32: PEÑA HERNANDEZ, FERNANDO FAVIAN | D32: ='Reporte de vacaciones 1'!DK184 -> 74
B33: 31 | C33: RAMIREZ ROMAN MARCELO | D33: ='Reporte de vacaciones 1'!DK187 -> 152
B34: 32 | C34: REYNA COSTA CLARA | D34: ='Reporte de vacaciones 1'!DK196 -> -18
B35: 33 | C35: SALIRROSSA PONCE LILIANA | D35: ='Reporte de vacaciones 1'!DK199 -> 0
B36: 34 | C36: TERRONES BECERRA MARISSA | D36: ='Reporte de vacaciones 1'!DK202 -> 127
B37: 35 | C37: TOMAYLLA TERRONES KATHERINE | D37: ='Reporte de vacaciones 1'!DK211 -> 137
B38: 36 | C38: VENEGAS MARCHAND, FRANCISCO MARTIN | D38: ='Reporte de vacaciones 1'!DK217 -> 30
B39: 37 | C39: YNCIO JIMENEZ SILVIA | D39: ='Reporte de vacaciones 1'!DK223 -> -19
B40: 38 | C40: YON UTRILLA LUIS | D40: ='Reporte de vacaciones 1'!DK226 -> 6
B41: 39 | C41: ZURITA PEÑA JOANY | D41: ='Reporte de vacaciones 1'!DK229 -> 83

Sheet Reporte de vacaciones  (2)
B1: REPORTE DE VACACIONES | I1: 2019 | K1: 2020 | N1: 2021
B2: EMPLEADOS | C2: FECHA DE INGRESO A RUAG | D2: Fecha de ingreso a planilla | E2: Años correspondiente a vacaciones | F2: Días de vacaciones | G2: Derecho a días de vacaciones | H2: Fecha de ingreso a planilla (covid-19) | K2: NO AFECTO A COVID | L2: AFECTO A COVID | P2: 44132 | Q2: Gozados (2012) | R2: Enero - diciembre 2013 | AD2: Gozadas (2013) | AE2: Enero - diciembre 2014 | AQ2: Gozadas (2014) | AR2: Enero - diciembre 2015 | BD2: Gozadas (2015) | BE2: Enero - diciembre 2016 | BQ2: Gozadas (2016) | BR2: Enero - diciembre 2017 | CD2: Gozadas (2017) | CE2: Enero - diciembre 2018 | CQ2: Gozadas (2018) | CR2: Enero - diciembre 2019 | DD2: Gozadas (2019) | DE2: Enero - diciembre 2020 | DQ2: Gozadas (2020 | DS2: Dias no trabajados X COVID | DT2: Fecha de ingreso a planilla (covid-19) | DU2: 2021 | DW2: 44130 | DX2: Total días gozados | DY2: PENDIENTE POR GOZAR | DZ2: PROYECTADO | EN2: Total días gozados
P3: Derecho a días de vacaciones | DW3: Derecho a días de vacaciones | DZ3: 2020 | EB3: 2021
R4: ENE | S4: FEB | T4: MAR | U4: ABR | V4: MAY | W4: JUN | X4: JUL | Y4: AGO | Z4: SEP | AA4: OCT | AB4: NOV | AC4: DIC | AE4: ENE | AF4: FEB | AG4: MAR | AH4: ABR | AI4: MAY | AJ4: JUN | AK4: JUL | AL4: AGO | AM4: SEP | AN4: OCT | AO4: NOV | AP4: DIC | AR4: ENE | AS4: FEB | AT4: MAR | AU4: ABR | AV4: MAY | AW4: JUN | AX4: JUL | AY4: AGO | AZ4: SEP | BA4: OCT | BB4: NOV | BC4: DIC | BE4: ENE | BF4: FEB | BG4: MAR | BH4: ABR | BI4: MAY | BJ4: JUN | BK4: JUL | BL4: AGO | BM4: SEP | BN4: OCT | BO4: NOV | BP4: DIC | BR4: ENE | BS4: FEB | BT4: MAR | BU4: ABR | BV4: MAY | BW4: JUN | BX4: JUL | BY4: AGO | BZ4: SEP | CA4: OCT | CB4: NOV | CC4: DIC | CE4: ENE | CF4: FEB | CG4: MAR | CH4: ABR | CI4: MAY | CJ4: JUN | CK4: JUL | CL4: AGO | CM4: SEP | CN4: OCT | CO4: NOV | CP4: DIC | CR4: ENE | CS4: FEB | CT4: MAR | CU4: ABR | CV4: MAY | CW4: JUN | CX4: JUL | CY4: AGO | CZ4: SEP | DA4: OCT | DB4: NOV | DC4: DIC | DE4: ENE | DF4: FEB | DG4: MAR | DH4: ABR | DI4: MAY | DJ4: JUN | DK4: JUL | DL4: AGO | DM4: SEP | DN4: OCT | DO4: NOV | DP4: DIC | DZ4: NOV | EA4: DIC | EB4: ENE | EC4: FEB | ED4: MAR | EE4: ABR | EF4: MAY | EG4: JUN | EH4: JUL | EI4: AGO | EJ4: SET | EK4: OCT | EL4: NOV | EM4: DIC
A5: 1 | B5: ALARCON PEREZ LUIS | C5: 42736 | D5: 01/01/2017 | E5: 01 ene 2017 al 31 dic 2017 | F5: 30 | G5: =+F5+F6+#REF!+#REF! -> #REF! | H5: 42792 | I5: =+D5+3*360 -> 43816 | J5: 90 | K5: =+I5+360 -> 44176 | L5: =K5+DS5 -> 44232 | M5: 0 | N5: 44232 | P5: =ROUNDDOWN((P2-D5)/365,0)*30 -> 90 | BW5: 1 | CA5: 1 | CC5: 6 | CD5: =CC5+CA5+BW5 -> 8 | CG5: 1 | CJ5: 1 | CK5: 1 | CM5: 7 | CN5: =2+1 -> 3 | CQ5: =SUM(CE5:CP6) -> 13 | DD5: =SUM(CR5:DC6) -> 0 | DE5: 1 | DM5: 9 | DQ5: =SUM(DE5:DP6) -> 10 | DS5: ='Determ días de vacaciones'!S10 -> 56 | DT5: =K5+DS5 -> 44232 | DW5: =ROUNDDOWN(($DW$2-H5)/365,0)*30 -> 90 | DX5: =Q5+AD5+AQ5+BD5+BQ5+CD5+CQ5+DD5+DQ5 -> 31 | DY5: =P5-DX5 -> 59 | DZ5: 15 | EA5: 15 | EB5: 15 | EC5: 14 | EN5: =SUM(DZ5:EM6) -> 59
E6: 01 ene 2018 al 31 dic 2018 | F6: 30
A7: 2 | B7: ALEJOS TORIBIO, SULELMA MELISA | C7: 01/09/2017 | D7: 01/09/2017 | E7: 01 set 2017 al 31 ago 2018 | F7: 30 | G7: =F7+F8+#REF! -> #REF! | H7: 43071 | I7: =+D7+2*360 -> 43699 | J7: 60 | K7: =I7+360 -> 44059 | L7: =K7+DS7 -> 44151 | M7: 0 | N7: =+L7+360 -> 44511 | P7: =ROUNDDOWN(($P$2-D7)/365,0)*30 -> 90 | CA7: 1 | CD7: =SUM(BR8:CC8) -> 1 | CG7: 1 | CH7: 2 | CI7: 2 | CJ7: 2 | CQ7: =SUM(CE7:CP8) -> 7 | CX7: 1 | DC7: 1 | DD7: =SUM(CR7:DC8) -> 2 | DM7: 13 | DN7: 1 | DQ7: =SUM(DE7:DP8) -> 14 | DS7: ='Determ días de vacaciones'!S11 -> 92 | DW7: =ROUNDDOWN(($DW$2-H7)/365,0)*30 -> 60 | DX7: =Q7+AD7+AQ7+BD7+BQ7+CD7+CQ7+DD7+DQ7 -> 24 | DY7: =P7-DX7 -> 66 | DZ7: 15 | EA7: 15 | EB7: 15 | EC7: 15 | ED7: 6 | EN7: =SUM(DZ7:EM8) -> 66
E8: 01 set 2018 al 31 ago 2019 | F8: 30 | CC8: 1
A9: 3 | B9: ALHUAY AYESTA, RAMIRO | D9: 01/09/2014 | E9: 01 Set 2014 al 30 Ago 2015 Gozado | F9: 30 | G9: =F9+F10+#REF!+#REF!+#REF!+#REF! -> #REF! | H9: 41975 | I9: =+D9+5*360 -> 43683 | J9: 150 | K9: =I9+360 -> 44043 | L9: =K9+DS9 -> 44135 | M9: 0 | N9: =+L9+360 -> 44495 | P9: =ROUNDDOWN(($P$2-D9)/365,0)*30 -> 180 | AD9: =SUM(R9:AC10) -> 0 | AN9: 5 | AP9: 10 | AQ9: =SUM(AE9:AP10) -> 15 | AS9: 1 | AU9: 3 | AW9: 6 | AX9: 2 | AY9: 1 | BD9: =SUM(AR9:BC10) -> 13 | BO9: 1 | BP9: 15 | BQ9: =SUM(BE9:BP10) -> 16 | BU9: 2 | CC9: 6 | CD9: =SUM(BR9:CC10) -> 8 | CF9: 2 | CH9: 7 | CL9: 1 | CN9: 3 | CP9: 11 | CQ9: =SUM(CE9:CP10) -> 24 | CW9: 15 | CX9: 7 | CZ9: 14 | DC9: 12 | DD9: =SUM(CR9:DC10) -> 48 | DF9: 4 | DN9: 31 | DQ9: =SUM(DE9:DP10) -> 35 | DS9: ='Determ días de vacaciones'!S12 -> 92 | DW9: =ROUNDDOWN(($DW$2-H9)/365,0)*30 -> 150 | DX9: =Q9+AD9+AQ9+BD9+BQ9+CD9+CQ9+DD9+DQ9 -> 159 | DY9: =P9-DX9 -> 21 | DZ9: 21 | EN9: =SUM(DZ9:EM10) -> 21
E10: 01 Set 2015 al 30 Ago 2016 Gozado | F10: 30
A11: 4 | B11: ALTAMIRANO SULCA MANUEL | C11: 16/05/2012 BAJA | D11: 01/08/2018 | E11: 01 Ago 2018 al 31 Jul 2019 | F11: 30 | G11: =F11+F12+#REF!+#REF! -> #REF! | H11: 43375 | I11: =+D11+360 -> 43673 | J11: 30 | K11: =I11+360 -> 44033 | L11: =K11+DS11 -> 44095 | M11: 30 | N11: =+L11+360 -> 44455 | P11: =ROUNDDOWN(($P$2-D11)/365,0)*30 -> 60 | AD11: =SUM(R11:AC12) -> 0 | AQ11: =SUM(AE11:AP12) -> 0 | BD11: =SUM(AR11:BC12) -> 0 | BO11: 1 | BP11: 7 | CR11: 14 | DD11: =SUM(CR11:DC12) -> 14 | DQ11: =SUM(DE11:DP12) -> 0 | DS11: ='Determ días de vacaciones'!S13 -> 62 | DW11: =ROUNDDOWN(($DW$2-H11)/365,0)*30 -> 60 | DX11: =DD11 -> 14 | DY11: =P11-DX11 -> 46 | DZ11: 30 | EA11: 16 | EN11: =SUM(DZ11:EM12) -> 46
C12: 01/02/2019 BAJA | E12: 01 Ago 2019 al 31 Jul 2020 | F12: 30
A13: 5 | B13: ARROYO FALLA, VANESSA ALICIA | C13: 16/05/2012 BAJA | D13: 01/04/2019 | E13: 01 abr 2019 al 31 mar 2020 | F13: 30 | G13: =F13+F14+#REF!+#REF! -> #REF! | H13: 43986 | K13: =+D13+360 -> 43916 | L13: =K13+DS13 -> 43980 | M13: 30 | N13: =+L13+360 -> 44340 | P13: =ROUNDDOWN(($P$2-D13)/365,0)*30 -> 30 | AD13: =SUM(R13:AC14) -> 0 | AQ13: =SUM(AE13:AP14) -> 0 | BD13: =SUM(AR13:BC14) -> 0 | BO13: 1 | BP13: 7 | CX13: 10 | CY13: 7 | DD13: =SUM(CR13:DC14) -> 17 | DF13: 10 | DG13: 11 | DQ13: =SUM(DE13:DP14) -> 21 | DS13: 64 | DW13: =ROUNDDOWN(($DW$2-H13)/365,0)*30 -> 0 | DX13: =DD13+DQ13 -> 38 | DY13: =P13-DX13 -> -8 | EN13: =SUM(DZ13:EM14) -> 0
C14: 01/02/2019 BAJA
A15: 6 | B15: ASPILCUETA GUTIERREZ KAREN | C15: 01 abril 2013 | D15: 01/04/2013 | E15: 01 Abr 2013 al 30 Mar 2014 Gozado | F15: 30 | G15: =F15+F16+#REF!+#REF!+#REF!+#REF! -> #REF! | H15: 41406 | I15: =+D15+6*360 -> 43525 | J15: 180 | K15: =I15+360 -> 43885 | M15: 30 | N15: =+K15+DS15+360 -> 44286 | P15: =ROUNDDOWN(($P$2-D15)/365,0)*30 -> 210 | V15: 1 | AD15: =SUM(R15:AC16) -> 1 | AL15: 7 | AP15: 1 | AQ15: =SUM(AE15:AP16) -> 8 | AR15: 1 | AS15: 4 | AT15: 2 | AV15: 1 | AX15: 1 | BA15: 1 | BC15: 3 | BD15: =SUM(AR15:BC16) -> 13 | BE15: 2 | BF15: 1 | BH15: 1 | BI15: 7 | BK15: 2 | BL15: 1 | BO15: 1 | BP15: 1 | BQ15: =SUM(BE15:BP16) -> 16 | BR15: 2 | BS15: 7 | BU15: 1 | BW15: 1 | BX15: 1 | BY15: 1 | CA15: 2 | CB15: 1 | CC15: 8 | CD15: =SUM(BR15:CC16) -> 24 | CE15: 13 | CF15: 1 | CI15: 1 | CK15: 8 | CM15: 1 | CP15: 2 | CQ15: =SUM(CE15:CP16) -> 26 | CS15: 7 | CW15: 1 | CX15: 10 | CY15: 1 | DC15: 1 | DD15: =SUM(CR15:DC16) -> 20 | DF15: 7 | DG15: 8 | DM15: 15 | DQ15: =SUM(DE15:DP16) -> 30 | DS15: ='Determ días de vacaciones'!S15 -> 41 | DW15: =ROUNDDOWN(($DW$2-H15)/365,0)*30 -> 210 | DX15: =AD15+AQ15+BD15+BQ15+CD15+CQ15+DD15+DQ15 -> 138 | DY15: =P15-DX15 -> 72 | DZ15: 15 | EA15: 15 | EB15: 15 | EC15: 15 | ED15: 12 | EN15: =SUM(DZ15:EM16) -> 72
E16: 01 Abr 2014 al 30 Mar 2015 Gozado | F16: 30
A17: 7 | B17: BACA WIESSE JOSE ALBERTO | C17: 01 junio 2005 | D17: 01/01/2011 | E17: 01 Ene 2011 al 31 Dic 2011 Gozado | F17: 30 | G17: =F17+F18+#REF!+#REF!+#REF!+#REF!+#REF!+#REF!+#REF! -> #REF! | H17: 40605 | I17: =+D17+9*360 -> 43784 | J17: 270 | K17: =I17+360 -> 44144 | L17: =K17+DS17 -> 44206 | M17: 0 | N17: 44206 | P17: =ROUNDDOWN(($P$2-D17)/365,0)*30 -> 270 | Q17: 45 | S17: 1 | U17: 1 | W17: 4 | X17: 1 | Y17: 3 | AC17: 1 | AD17: =SUM(R17:AC18) -> 11 | AE17: 1 | AF17: 1 | AH17: 1 | AI17: 4 | AM17: 1 | AN17: 1 | AP17: 3 | AQ17: =SUM(AE17:AP18) -> 12 | AS17: 4 | AU17: 1 | AW17: 4 | AX17: 2 | AZ17: 1 | BA17: 4 | BB17: 1 | BC17: 3 | BD17: =SUM(AR17:BC18) -> 20 | BF17: 14 | BG17: 2 | BN17: 1 | BO17: 3 | BP17: 3 | BQ17: =SUM(BE17:BP18) -> 23 | CD17: =SUM(BR17:CC18) -> 0 | CF17: 10 | CK17: 1 | CL17: 1 | CQ17: =SUM(CE17:CP18) -> 12 | CS17: 11 | DC17: 14 | DD17: =SUM(CR17:DC18) -> 25 | DF17: 12 | DM17: 15 | DN17: 15 | DQ17: =SUM(DE17:DP18) -> 42 | DS17: ='Determ días de vacaciones'!S16 -> 62 | DT17: =K17+DS17 -> 44206 | DW17: =ROUNDDOWN(($DW$2-H17)/365,0)*30 -> 270 | DX17: =Q17+AD17+AQ17+BD17+BQ17+CD17+CQ17+DD17+DQ17 -> 190 | DY17: =P17-DX17 -> 80 | DZ17: 15 | EA17: 15 | EB17: 15 | EC17: 15 | ED17: 15 | EE17: 5 | EN17: =SUM(DZ17:EM18) -> 80
E18: 01 Ene 2012 al 31 Dic 2012 Gozado | F18: 30
A19: 8 | B19: BALLENA CASTILLO ITALA ADRIANA | C19: 01 febrero 2010 | D19: 01/03/2011 | E19: 01 Mar 2011 al 28 Feb 2012 gozado | F19: 30 | G19: =F19+F20+#REF!+#REF!+#REF!+#REF!+#REF!+#REF!+#REF! -> #REF! | H19: 40647 | I19: =+D19+8*360 -> 43483 | J19: 240 | K19: =I19+360 -> 43843 | M19: 30 | N19: =+K19+DS19+360 -> 44247 | P19: =ROUNDDOWN(($P$2-D19)/365,0)*30 -> 270 | Q19: 15 | T19: 5 | W19: 5 | X19: 8 | AD19: =SUM(R19:AC20) -> 18 | AL19: 2 | AM19: 1 | AP19: 3 | AQ19: =SUM(AE19:AP20) -> 6 | AR19: 1 | AS19: 15 | AX19: 4 | AY19: 1 | BD19: =SUM(AR19:BC20) -> 21 | BJ19: 14 | BL19: 1 | BP19: 22 | BQ19: =SUM(BE19:BP20) -> 37 | BY19: 37 | CA19: 1 | CC19: 14 | CD19: =SUM(BR19:CC20) -> 52 | CE19: 4 | CN19: 30 | CQ19: =SUM(CE19:CP20) -> 34 | CU19: 3 | CZ19: 8 | DC19: 15 | DD19: =SUM(CR19:DC20) -> 26 | DQ19: =SUM(DE19:DP20) -> 0 | DS19: ='Determ días de vacaciones'!S17 -> 44 | DT19: =K19+DS19 -> 43887 | DW19: =ROUNDDOWN(($DW$2-H19)/365,0)*30 -> 270 | DX19: =Q19+AD19+AQ19+BD19+BQ19+CD19+CQ19+DD19+DQ19 -> 209 | DY19: =P19-DX19 -> 61 | DZ19: 30 | EA19: 31 | EN19: =SUM(DZ19:EM20) -> 61
E20: 01 Mar 2012 al 28 Feb 2013 gozado | F20: 30
A21: 9 | B21: BAUTISTA AYESTA HEBER (INGRESO PLANILLA 01/07/2007) | C21: 01 agosto 2005 | D21: 01/07/2011 | E21: 01 Jul 2011 al 30 Jun 2012 Gozado | F21: 30 | G21: =F21+F22+#REF!+#REF!+#REF!+#REF!+#REF!+#REF!+#REF! -> #REF! | H21: 40787 | I21: =+D21+8*360 -> 43605 | J21: 240 | K21: =I21+360 -> 43965 | L21: =K21+DS21 -> 44027 | M21: 30 | N21: =+L21+360 -> 44387 | P21: =ROUNDDOWN(($P$2-D21)/365,0)*30 -> 270 | Q21: 15 | AD21: =SUM(R21:AC22) -> 0 | AQ21: =SUM(AE21:AP21) -> 0 | AS21: 14 | BD21: =SUM(AR21:BC21) -> 14 | BF21: 1 | BH21: 1 | BJ21: 5 | BQ21: =SUM(BE21:BP21) -> 7 | CD21: =SUM(BR21:CC21) -> 0 | CG21: 15 | CQ21: =SUM(CE21:CP21) -> 15 | CX21: 14 | DD21: =SUM(CR21:DC21) -> 14 | DQ21: =SUM(DE21:DP21) -> 0 | DS21: ='Determ días de vacaciones'!S18 -> 62 | DW21: =ROUNDDOWN(($DW$2-H21)/365,0)*30 -> 270 | DX21: =Q21+AD21+AQ21+BD21+BQ21+CD21+CQ21+DD21+DQ21 -> 65 | DY21: =P21-DX21 -> 205 | DZ21: 30 | EA21: 31 | EB21: 31 | EC21: 28 | ED21: 31 | EE21: 30 | EF21: 24 | EN21: =SUM(DZ21:EM22) -> 205
E22: 01 Jul 2012 al 30 Jun 2013 Gozado | F22: 30
A23: 10 | B23: BAUTISTA AYESTA WALTER (INGRESO A PLANILLA 01/05/2007) | C23: 01 agosto 2005 | D23: 01/05/2011 | E23: 01 May 2011 al 30 Abr 2012 | F23: 30 | G23: =F23+F24+#REF!+#REF!+#REF!+#REF!+#REF!+#REF!+#REF! -> #REF! | H23: 40756 | I23: =+D23+8*360 -> 43544 | J23: 240 | K23: =I23+360 -> 43904 | M23: 30 | N23: =K23+DS23+360 -> 44356 | P23: =ROUNDDOWN(($P$2-D23)/365,0)*30 -> 270 | AD23: =SUM(R23:AC24) -> 0 | AQ23: =SUM(AE23:AP23) -> 0 | AW23: 6 | BD23: =SUM(AR23:BC23) -> 6 | BQ23: =SUM(BE23:BP23) -> 0 | CD23: =SUM(BR23:CC23) -> 0 | CQ23: =SUM(CE23:CP23) -> 0 | DD23: =SUM(CR23:DC23) -> 0 | DQ23: =SUM(DE23:DP23) -> 0 | DS23: ='Determ días de vacaciones'!S19 -> 92 | DW23: =ROUNDDOWN(($DW$2-H23)/365,0)*30 -> 270 | DX23: =SUM(BD23,BQ23) -> 6 | DY23: =P23-DX23 -> 264 | DZ23: 30 | EA23: 31 | EB23: 31 | EC23: 28 | ED23: 31 | EE23: 30 | EF23: 31 | EG23: 30 | EH23: 22 | EN23: =SUM(DZ23:EM24) -> 264
E24: 01 May 2012 al 30 Abr 2013 | F24: 30
A25: 11 | B25: BRIONES RIVERA, RICHARD | C25: 01 enero 2009 | D25: 01/02/2020 | G25: =F25+F26+#REF!+#REF!+#REF!+#REF!+#REF!+#REF!+#REF! -> #REF! | K25: 01/02/2020 | M25: 0 | N25: =+K25+DS25+360 -> 44359 | P25: =ROUNDDOWN(($P$2-D25)/365,0)*30 -> 0 | DS25: ='Determ días de vacaciones'!S20 -> 137 | DX25: =Q25+AD25+AQ25+BD25+BQ25+CD25+CQ25+DD25 -> 0 | DY25: =P25-DX25 -> 0 | EN25: =SUM(DZ25:EM26) -> 0
A27: 12 | B27: COLETO PASTOR LUIS ENRIQUE (INGRESO A PLANILLA 01/10/2010) | D27: 01/10/2011 | E27: 01 Oct 2011 al 30 Set 2012 Gozado | F27: 30 | G27: =F27+F28+#REF!+#REF!+#REF!+#REF!+#REF!+#REF!+#REF! -> #REF! | H27: 40544 | I27: =+D27+8*360 -> 43697 | J27: 240 | K27: =I27+360 -> 44057 | L27: =K27+DS27 -> 44149 | M27: 0 | N27: =+L27+360 -> 44509 | P27: =ROUNDDOWN(($P$2-D27)/365,0)*30 -> 270 | AD27: =SUM(R27:AC28) -> 0 | AE27: 10 | AL27: 16 | AM27: 30 | AN27: 30 | AQ27: =SUM(AE27:AP27) -> 86 | AY27: 3 | BA27: 23 | BC27: 1 | BD27: =SUM(AR27:BC27) -> 27 | BE27: 1 | BO27: 1 | BQ27: =SUM(BE27:BP27) -> 2 | BT27: 7 | CC27: 4 | CD27: =SUM(BR27:CC27) -> 11 | CE27: 54 | CQ27: =SUM(CE27:CP27) -> 54 | CX27: 9 | DB27: 11 | DD27: =SUM(CR27:DC27) -> 20 | DQ27: =SUM(DE27:DP27) -> 0 | DS27: ='Determ días de vacaciones'!S21 -> 92 | DW27: =ROUNDDOWN(($DW$2-H27)/365,0)*30 -> 270 | DX27: =Q27+AD27+AQ27+BD27+BQ27+CD27+CQ27+DD27 -> 200 | DY27: =P27-DX27 -> 70 | DZ27: 30 | EA27: 31 | EB27: 9 | EN27: =SUM(DZ27:EM28) -> 70
E28: 01 Oct 2012 al 30 Set 2013 Gozado | F28: 30
A29: 13 | B29: CORDOVA VELEZ, JULISSA | C29: 01 abril 2011 | D29: 01/02/2020 | G29: =F29+F30+#REF!+#REF!+#REF!+#REF!+#REF!+#REF! -> #REF! | K29: 01/02/2020 | M29: 0 | N29: =+K29+DS29+360 -> 44359 | P29: =ROUNDDOWN(($P$2-D29)/365,0)*30 -> 0 | X29: 15 | AC29: 7 | DS29: ='Determ días de vacaciones'!S22 -> 137 | DX29: =AD29+AQ29+BD29+BQ29+CD29+CQ29+DD29+DQ29 -> 0 | DY29: =P29-DX29 -> 0 | EN29: =SUM(DZ29:EM30) -> 0
A31: 14 | B31: DAMBROSIO RIVERO LIZETH STEFANNY | C31: 01 marzo 2007 | D31: 01/01/2019 | E31: 01 ene 2019 al 31 Dic 2019 | F31: 30 | G31: =F31+F32+#REF!+#REF!+#REF! -> #REF! | H31: 43561 | I31: =+D31+360 -> 43826 | J31: 30 | K31: 43831 | M31: 30 | N31: =K31+DS31+360 -> 44287 | P31: =ROUNDDOWN(($P$2-D31)/365,0)*30 -> 30 | AD31: =SUM(R31:AC31) -> 0 | AK31: 1 | BD31: =SUM(AR31:BC31) -> 0 | BQ31: =SUM(BE31:BP31) -> 0 | CD31: =SUM(BR31:CC32) -> 0 | CQ31: =SUM(CE31:CP32) -> 0 | CV31: 3 | DC31: 4 | DD31: =SUM(CR31:DC32) -> 7 | DL31: 31 | DM31: 2 | DQ31: =SUM(DE31:DP32) -> 33 | DS31: 96 | DT31: =K31+DS31 -> 43927 | DW31: =ROUNDDOWN(($DW$2-H31)/365,0)*30 -> 30 | DX31: =Q31+AD31+AQ31+BD31+BQ31+CD31+CQ31+DD31+DQ31 -> 40 | DY31: =P31-DX31 -> -10 | EN31: =SUM(DZ31:EM32) -> 0
E32: 1 ene 2020 al 31 Dic 2020
A33: 15 | B33: FLORES GUARDIA CLAUDIA | C33: 01 marzo 2007 | D33: 01/11/2019 | E33: 01 nov 2019 al 31 oct 2020 | F33: 30 | G33: =F33+F34+#REF!+#REF!+#REF!+#REF! -> #REF! | K33: 44136 | L33: =+K33+DS33 -> 44206 | M33: 0 | N33: 44206 | P33: =ROUNDDOWN(($P$2-D33)/365,0)*30 -> 0 | DM33: 18 | DQ33: =SUM(DE33:DP34) -> 18 | DS33: 70 | DT33: =K33+DS33 -> 44206 | DX33: =Q33+AD33+AQ33+BD33+BQ33+CD33+CQ33+DD33+DQ33 -> 18 | DY33: =P33-DX33 -> -18 | EN33: =SUM(DZ33:EM34) -> 0
A35: 16 | B35: FLORES MANTILLA MARIANA | C35: 01 marzo 2007 | D35: 01/07/2014 | E35: 01 Jul 2014 al 30 Jun 2015 Gozado | F35: 30 | G35: =F35+F36+#REF!+#REF!+#REF!+#REF! -> #REF! | H35: 41898 | I35: =+D35+5*360 -> 43621 | J35: 150 | K35: =I35+360 -> 43981 | L35: =K35+DS35 -> 44058 | M35: 30 | N35: =+L35+360 -> 44418 | P35: =ROUNDDOWN(($P$2-D35)/365,0)*30 -> 180 | AD35: =SUM(R35:AC35) -> 0 | AK35: 1 | AQ35: =SUM(AK35:AP36) -> 1 | AS35: 30 | AT35: 30 | AX35: 1 | BD35: =SUM(AR35:BC35) -> 61 | BF35: 7 | BK35: 3 | BO35: 1 | BQ35: =SUM(BE35:BP35) -> 11 | BV35: 1 | BX35: 1 | CC35: 1 | CD35: =SUM(BR35:CC36) -> 3 | CF35: 1 | CG35: 7 | CK35: 7 | CN35: 8 | CQ35: =SUM(CE35:CP36) -> 23 | CT35: 1 | CW35: 7 | CX35: 2 | DD35: =SUM(CR35:DC36) -> 10 | DF35: 6 | DN35: 2 | DQ35: =SUM(DE35:DP36) -> 8 | DS35: ='Determ días de vacaciones'!S26 -> 77 | DW35: =ROUNDDOWN(($DW$2-H35)/365,0)*30 -> 180 | DX35: =Q35+AD35+AQ35+BD35+BQ35+CD35+CQ35+DD35+DQ35 -> 117 | DY35: =P35-DX35 -> 63 | DZ35: 30 | EA35: 31 | EB35: 2 | EN35: =SUM(DZ35:EM36) -> 63
E36: 01 Jul 2015 al 30 Jun 2016 Gozado | F36: 30
A37: 17 | B37: GOYAS ABRAMONTE JAVIER | C37: 01 marzo 2007 | D37: 01/04/2019 | E37: 01 Abr 2019 al 30 Mar 2020 | F37: 30 | G37: =F37+F38+#REF!+#REF!+#REF!+#REF! -> #REF! | H37: 43600 | K37: 43922 | L37: =K37+DS37 -> 43966 | M37: 30 | N37: =+L37+360 -> 44326 | P37: =ROUNDDOWN(($P$2-D37)/365,0)*30 -> 30 | DQ37: =SUM(DE37:DP38) -> 0 | DS37: ='Determ días de vacaciones'!S27 -> 44 | DW37: =ROUNDDOWN(($DW$2-H37)/365,0)*30 -> 30 | DX37: =Q37+AD37+AQ37+BD37+BQ37+CD37+CQ37+DD37+DQ37 -> 0 | DY37: =P37-DX37 -> 30 | DZ37: 30 | EN37: =SUM(DZ37:EM38) -> 30
A39: 18 | B39: GRANDE ALCANTARA GERMAN N. (INGRESO A PLANILLA 01/04/2007) | D39: 01/04/2011 | E39: 01 Abr 2011 al 30 Mar 2012 Gozado | F39: 30 | G39: =F39+F40+#REF!+#REF!+#REF!+#REF!+#REF!+#REF!+#REF! -> #REF! | H39: 40675 | I39: =+D39+8*360 -> 43514 | J39: 240 | K39: =I39+360 -> 43874 | M39: 30 | N39: =K39+DS39+360 -> 44275 | P39: =ROUNDDOWN(($P$2-D39)/365,0)*30 -> 270 | AD39: =SUM(R39:AC40) -> 0 | AQ39: =SUM(AE39:AP40) -> 0 | AS39: 7 | AV39: 2 | BD39: =SUM(AR39:BC40) -> 9 | BE39: 20 | BO39: 1 | BQ39: =SUM(BE39:BP40) -> 21 | BV39: 7 | BX39: 20 | CD39: =SUM(BR39:CC40) -> 27 | CQ39: =SUM(CE39:CP40) -> 0 | DD39: =SUM(CR39:DC40) -> 0 | DH39: 30 | DM39: 3 | DQ39: =SUM(DE39:DP40) -> 33 | DS39: ='Determ días de vacaciones'!S28 -> 41 | DW39: =ROUNDDOWN(($DW$2-H39)/365,0)*30 -> 270 | DX39: =SUM(AD39,AQ39,BD39,BQ39,CD39,CQ39:CQ39,DD39,DQ39) -> 90 | DY39: =P39-DX39 -> 180 | DZ39: 15 | EA39: 15 | EB39: 15 | EC39: 15 | ED39: 15 | EE39: 15 | EF39: 15 | EG39: 15 | EH39: 15 | EI39: 15 | EJ39: 15 | EK39: 15 | EN39: =SUM(DZ39:EM40) -> 180
E40: 01 Abr 2012 al 30 Mar 2013 | F40: 30
A41: 19 | B41: GRANDE ALCANTARA MILAGROS M. (INGRESO PLANILLA 01/07/2008) | D41: 01/07/2011 | E41: 01 Jul 2011 al 30 Jun 2012 Gozado | F41: 30 | G41: =F41+F42+#REF!+#REF!+#REF!+#REF!+#REF!+#REF!+#REF! -> #REF! | H41: 40781 | I41: =+D41+8*360 -> 43605 | J41: 240 | K41: =I41+360 -> 43965 | L41: =K41+DS41 -> 44021 | M41: 30 | N41: =+L41+360 -> 44381 | P41: =ROUNDDOWN(($P$2-D41)/365,0)*30 -> 270 | Q41: 15 | AD41: =SUM(R41:AC42) -> 0 | AQ41: =SUM(AE41:AP42) -> 0 | AS41: 8 | AX41: 8 | BD41: =SUM(AR41:BC42) -> 16 | BO41: 1 | BQ41: =SUM(BE41:BP42) -> 1 | BX41: 10 | CD41: =SUM(BR41:CC42) -> 10 | CF41: 5 | CQ41: =SUM(CE41:CP42) -> 5 | CR41: 30 | DD41: =SUM(CR41:DC42) -> 30 | DE41: 31 | DN41: 20 | DQ41: =SUM(DE41:DP42) -> 51 | DS41: ='Determ días de vacaciones'!S29 -> 56 | DW41: =ROUNDDOWN(($DW$2-H41)/365,0)*30 -> 270 | DX41: =Q41+AD41+AQ41+BD41+BQ41+CD41+CQ41+DD41+DQ41 -> 128 | DY41: =P41-DX41 -> 142 | DZ41: 30 | EA41: 31 | EB41: 31 | EC41: 28 | ED41: 22 | EN41: =SUM(DZ41:EM42) -> 142
E42: 01 Jul 2012 al 30 Jun 2013 Gozado | F42: 30
A43: 20 | B43: GRANDE ALCANTARA PAUL | D43: 01/01/2012 | E43: 01 Ene 2012 al 30 Dic 2012 Gozado | F43: 30 | G43: =F43+F44+#REF!+#REF!+#REF!+#REF!+#REF!+#REF!+F45 -> #REF! | H43: 40956 | I43: =+D43+8*360 -> 43789 | J43: 240 | K43: =I43+360 -> 44149 | L43: =+K43+DS43 -> 44196 | M43: 0 | N43: =+L43+360 -> 44556 | P43: =ROUNDDOWN(($P$2-D43)/365,0)*30 -> 240 | Q43: 15 | AD43: =SUM(R43:AC44) -> 0 | AE43: 4 | AI43: 3 | AQ43: =SUM(AE43:AP44) -> 7 | AS43: 7 | AW43: 7 | BB43: 2 | BC43: 3 | BD43: =SUM(AR43:BC44) -> 19 | BE43: 10 | BF43: 2 | BK43: 7 | BQ43: =SUM(BE43:BP44) -> 19 | BS43: 2 | CD43: =SUM(BS43:CC44) -> 2 | CG43: 6 | CH43: 8 | CQ43: =SUM(CG43:CP44) -> 14 | CY43: 12 | DD43: =SUM(CT43:DC44) -> 12 | DM43: 30 | DN43: 31 | DQ43: =SUM(DG43:DP44) -> 61 | DS43: ='Determ días de vacaciones'!S30 -> 47 | DT43: =K43+DS43 -> 44196 | DW43: =ROUNDDOWN(($DW$2-H43)/365,0)*30 -> 240 | DX43: =Q43+AD43+AQ43+BD43+BQ43+CD43+CQ43+DD43+DQ43 -> 149 | DY43: =P43-DX43 -> 91 | DZ43: 30 | EA43: 31 | EB43: 30 | EN43: =SUM(DZ43:EM44) -> 91
E44: 01 Ene 2013 al 30 Dic 2013 Gozado | F44: 30
A45: 21 | B45: GRANDE PECEROS DAVID | D45: 01/10/2018 | E45: 01 Oct 2018 al 31 Jul 2019 | F45: 30 | G45: =SUM(F45+F46+#REF!+#REF!) -> #REF! | H45: 43421 | I45: =+D45+360 -> 43734 | J45: 30 | K45: =I45+360 -> 44094 | L45: =K45+DS45 -> 44141 | M45: 0 | N45: =+L45+360 -> 44501 | P45: =ROUNDDOWN(($P$2-D45)/365,0)*30 -> 60 | CP45: 4 | CQ45: =SUM(CE45:CP46) -> 4 | CS45: 7 | CX45: 1 | CZ45: 8 | DD45: =SUM(CR45:DC46) -> 16 | DF45: 15 | DM45: 12 | DQ45: =SUM(DE45:DP46) -> 27 | DS45: ='Determ días de vacaciones'!S32 -> 47 | DW45: =ROUNDDOWN(($DW$2-H45)/365,0)*30 -> 30 | DX45: =CQ45+DD45+DQ45 -> 47 | DY45: =P45-DX45 -> 13 | DZ45: 13 | EN45: =SUM(DZ45:EM46) -> 13
E46: 01 Oct 2019 al 31 Jul 2020 | F46: 30
A47: 22 | B47: JUAN PEDRO CRUZ, GIOVANNA PAULA | C47: 01 agosto 2008 | D47: 01/03/2012 | G47: =F47+F48+#REF!+#REF!+#REF!+#REF!+#REF!+#REF!+#REF! -> #REF! | H47: 41025 | I47: =D47+7*360 -> 43489 | J47: 210 | K47: =I47+360 -> 43849 | M47: 30 | N47: =K47+DS47+360 -> 44265 | P47: =ROUNDDOWN(($P$2-D47)/365,0)*30 -> 240 | S47: 1 | W47: 1 | Y47: 2 | AD47: =SUM(R47:AC48) -> 4 | AF47: 2 | AG47: 1 | AI47: 1 | AQ47: =SUM(AE47:AP48) -> 4 | AR47: 1 | AT47: 2 | AU47: 5 | AW47: 1 | AX47: 2 | AY47: 5 | BB47: 1 | BD47: =SUM(AR47:BC48) -> 17 | BE47: 1 | BF47: 1 | BH47: 2 | BO47: 1 | BQ47: =SUM(BE47:BP48) -> 5 | BR47: 2 | BS47: 2 | BT47: 1 | BU47: 2 | BV47: 3 | CB47: 4 | CC47: 6 | CD47: =SUM(BR47:CC48) -> 20 | CE47: 1 | CF47: 5 | CI47: 5 | CJ47: 2 | CK47: 3 | CM47: 2 | CQ47: =SUM(CE47:CP48) -> 18 | CR47: 60 | CT47: 2 | CV47: 60 | CZ47: 30 | DD47: =SUM(CR47:DC48) -> 152 | DF47: 7 | DM47: 15 | DN47: 3 | DQ47: =SUM(DE47:DP48) -> 25 | DS47: ='Determ días de vacaciones'!S33 -> 56 | DT47: =K47+DS47 -> 43905 | DW47: =ROUNDDOWN(($DW$2-H47)/365,0)*30 -> 240 | DX47: =BQ47+AD47+AQ47+BD47+BQ47+CD47+CQ47+DD47+DQ47 -> 250 | DY47: =P47-DX47 -> -10 | EN47: =SUM(DZ47:EM48) -> 0
E48: 01 Mar 2012 al 28 Feb 2013 gozado | F48: 30
A49: 23 | B49: MENDOZA GARCÍA, ZINCIA | D49: 01/01/2019 | E49: 01 Ene 2019 al 31 Dic 2019 | F49: 30 | G49: =F49+F50+#REF! -> #REF! | H49: 43587 | K49: 43831 | M49: 30 | N49: =K49+DS49+360 -> 44313 | P49: =ROUNDDOWN(($P$2-D49)/365,0)*30 -> 30 | CQ49: =SUM(CE49:CP50) -> 0 | CY49: 5 | DD49: =SUM(CR49:DC50) -> 5 | DL49: 31 | DM49: 2 | DQ49: =SUM(DE49:DP50) -> 33 | DS49: ='Determ días de vacaciones'!S34 -> 122 | DW49: =ROUNDDOWN(($DW$2-H49)/365,0)*30 -> 30 | DX49: =Q49+AD49+AQ49+BD49+BQ49+CD49+CQ49+DD49+DQ49 -> 38 | DY49: =P49-DX49 -> -8 | EN49: =SUM(DZ49:EM50) -> 0
E50: 1 Ene 2020 al 31 Dic 2020
A51: 25 | B51: MURGA SALCEDO ANTHONY EDGAR | C51: 01 marzo 2007 | D51: 15/10/2020 | G51: =F51+F52+#REF!+#REF!+#REF!+#REF! -> #REF! | K51: 44119 | M51: 0 | N51: =+D51+DS51+360 -> 44479 | P51: =ROUNDDOWN(($P$2-D51)/365,0)*30 -> 0 | DQ51: =SUM(DE51:DP52) -> 0 | DX51: =Q51+AD51+AQ51+BD51+BQ51+CD51+CQ51+DD51+DQ51 -> 0 | DY51: =P51-DX51 -> 0 | EN51: =SUM(DZ51:EM52) -> 0
A53: 24 | B53: OCHOA GUTIERREZ ERICKSON | C53: 01 marzo 2007 | D53: 01/08/2019 | E53: 01 ago 2019 al 30 set 2020 | F53: 30 | G53: =F53+F54+#REF!+#REF!+#REF!+#REF! -> #REF! | H53: 43722 | K53: 44044 | L53: =K53+DS53 -> 44088 | M53: 30 | N53: =+L53+360 -> 44448 | P53: =ROUNDDOWN(($P$2-D53)/365,0)*30 -> 30 | DQ53: =SUM(DE53:DP54) -> 0 | DS53: ='Determ días de vacaciones'!S35 -> 44 | DW53: =ROUNDDOWN(($DW$2-H53)/365,0)*30 -> 30 | DX53: =Q53+AD53+AQ53+BD53+BQ53+CD53+CQ53+DD53+DQ53 -> 0 | DY53: =P53-DX53 -> 30 | DZ53: 30 | EN53: =SUM(DZ53:EM54) -> 30
A55: 25 | B55: OROZCO BALAREZO SILVIA | C55: 01 marzo 2007 | D55: 01/08/2020 | G55: =F55+F56+#REF!+#REF!+#REF!+#REF! -> #REF! | K55: 44044 | M55: 0 | N55: =+D55+DS55+360 -> 44404 | P55: =ROUNDDOWN(($P$2-D55)/365,0)*30 -> 0 | DQ55: =SUM(DE55:DP56) -> 0 | DX55: =Q55+AD55+AQ55+BD55+BQ55+CD55+CQ55+DD55+DQ55 -> 0 | DY55: =P55-DX55 -> 0 | EN55: =SUM(DZ55:EM56) -> 0
A57: 26 | B57: OSCCO GUILLEN EDWIN | C57: 01 marzo 2007 | D57: 01/11/2018 | E57: 01 nov 2018 al 31 oct 2019 | F57: 30 | G57: =F57+F58+#REF!+#REF!+#REF!+#REF! -> #REF! | H57: 43444 | I57: =D57+360 -> 43765 | J57: 30 | K57: =I57+360 -> 44125 | L57: =K57+DS57 -> 44164.5 | M57: 0 | N57: =+L57+360 -> 44524.5 | P57: =ROUNDDOWN(($P$2-D57)/365,0)*30 -> 30 | DE57: 7 | DM57: 5 | DN57: 21 | DQ57: =SUM(DE57:DP58) -> 33 | DS57: ='Determ días de vacaciones'!S36 -> 39.5 | DW57: =ROUNDDOWN(($DW$2-H57)/365,0)*30 -> 30 | DX57: =Q57+AD57+AQ57+BD57+BQ57+CD57+CQ57+DD57+DQ57 -> 33 | DY57: =P57-DX57 -> -3 | EN57: =SUM(DZ57:EM58) -> 0
E58: 01 nov 2019 al 31 oct 2020 | F58: 30
A59: 27 | B59: OSCCO GUILLEN ZORAIDA | C59: 01 agosto 2008 | D59: 09/01/2013 | E59: 01 Ene 2013 al 30 Dic 2013 Gozado | F59: 30 | G59: =F59+F60+#REF!+#REF!+#REF!+#REF!+#REF! -> #REF! | H59: 41285 | I59: =D59+7*360 -> 43803 | J59: 210 | K59: =I59+360 -> 44163 | L59: =K59+DS59 -> 44165 | M59: 0 | N59: =+L59+360 -> 44525 | P59: =ROUNDDOWN(($P$2-D59)/365,0)*30 -> 210 | W59: 2 | AC59: 24 | AD59: =SUM(R59:AC60) -> 26 | AQ59: =SUM(AE59:AP60) -> 0 | AT59: 1 | AV59: 1 | AW59: 5 | AX59: 1 | AY59: 1 | BA59: 1 | BB59: 1 | BC59: 29 | BD59: =SUM(AR59:BC60) -> 40 | BO59: 1 | BQ59: =SUM(BE59:BP60) -> 1 | CA59: 1 | CB59: 3 | CC59: 5 | CD59: =SUM(BR59:CC60) -> 9 | CE59: 8 | CF59: 3 | CI59: 1 | CP59: 2 | CQ59: =SUM(CE59:CP60) -> 14 | CV59: 2 | CY59: 1 | CZ59: 1 | DB59: 1 | DC59: 30 | DD59: =SUM(CR59:DC60) -> 35 | DM59: 14 | DN59: 9 | DQ59: =SUM(DE59:DP60) -> 23 | DS59: ='Determ días de vacaciones'!S37 -> 2 | DT59: =K59+DS59 -> 44165 | DW59: =ROUNDDOWN(($DW$2-H59)/365,0)*30 -> 210 | DX59: =Q59+AD59+AQ59+BD59+BQ59+CD59+CQ59+DD59+DQ59 -> 148 | DY59: =P59-DX59 -> 62 | DZ59: 30 | EA59: 26 | EN59: =SUM(DZ59:EM60) -> 56
E60: 01 Ene 2014 al 30 Dic 2014 Gozado | F60: 30
A61: 28 | B61: PEÑA HERNANDEZ, FERNANDO FAVIAN | D61: 01/05/2017 | E61: 01/05/2017 AL 30/04/2018 | F61: 30 | G61: =F61+F62+#REF! -> #REF! | H61: 42948 | I61: =D61+2*360 -> 43576 | J61: 60 | K61: =I61+360 -> 43936 | L61: =K61+DS61 -> 44028 | M61: 30 | N61: =+L61+360 -> 44388 | P61: =ROUNDDOWN(($P$2-D61)/365,0)*30 -> 90 | CI61: 5 | CN61: 7 | CQ61: =SUM(CE61:CP62) -> 12 | CU61: 1 | CY61: 3 | DD61: =SUM(CR61:DC62) -> 4 | DQ61: =SUM(DE61:DP62) -> 0 | DS61: ='Determ días de vacaciones'!S38 -> 92 | DW61: =ROUNDDOWN(($DW$2-H61)/365,0)*30 -> 90 | DX61: =Q61+AD61+AQ61+BD61+BQ61+CD61+CQ61+DD61 -> 16 | DY61: =P61-DX61 -> 74 | DZ61: 30 | EA61: 31 | EB61: 13 | EN61: =SUM(DZ61:EM62) -> 74
E62: 01 May 2018 al 30 Abr 2019 | F62: 30
A63: 29 | B63: RAMIREZ ROMAN MARCELO (INGRESO A PLANILLA 01/07/2008) | C63: 01 agosto 2007 | D63: 01/07/2011 | E63: 01 Jul 2011 al 30 Jun 2012 Gozado | F63: 30 | G63: =F63+F64+#REF!+#REF!+#REF!+#REF!+#REF!+#REF! -> #REF! | H63: 40784 | I63: =D63+8*360 -> 43605 | J63: 240 | K63: =I63+360 -> 43965 | L63: =K63+DS63 -> 44024 | M63: 30 | N63: =+L63+360 -> 44384 | P63: =ROUNDDOWN(($P$2-D63)/365,0)*30 -> 270 | Q63: 30 | V63: 1 | Z63: 3 | AC63: 15 | AD63: =SUM(R63:AC64) -> 19 | AG63: 5 | AH63: 8 | AI63: 1 | AM63: 3 | AP63: 9 | AQ63: =SUM(AE63:AP64) -> 26 | AU63: 1 | AV63: 7 | AX63: 1 | AY63: 4 | AZ63: 1 | BD63: =SUM(AR63:BC64) -> 14 | BG63: 1 | BO63: 1 | BQ63: =SUM(BE63:BP64) -> 2 | BX63: 15 | CD63: =SUM(BR63:CC64) -> 15 | CQ63: =SUM(CE63:CP64) -> 0 | CV63: 7 | DD63: =SUM(CR63:DC64) -> 7 | DF63: 5 | DQ63: =SUM(DE63:DP64) -> 5 | DS63: ='Determ días de vacaciones'!S39 -> 59 | DW63: =ROUNDDOWN(($DW$2-H63)/365,0)*30 -> 270 | DX63: =Q63+AD63+AQ63+BD63+BQ63+CD63+CQ63+DD63+DQ63 -> 118 | DY63: =P63-DX63 -> 152 | DZ63: 15 | EA63: 15 | EB63: 15 | EC63: 15 | ED63: 15 | EE63: 15 | EF63: 15 | EG63: 15 | EH63: 15 | EI63: 15 | EJ63: 2 | EN63: =SUM(DZ63:EM64) -> 152
E64: 01 Jul 2012 al 30 Jun 2013 Gozado | F64: 30
A65: 30 | B65: REYNA COSTA CLARA | D65: 01/12/2017 | E65: 01 Dic 2017 al 30 Nov 2018 | F65: 30 | G65: =F65+F66+#REF! -> #REF! | H65: 42757 | I65: =D65+2*360 -> 43790 | J65: 60 | K65: =I65+360 -> 44150 | L65: =+K65+DS65 -> 44202 | M65: 0 | N65: 44202 | P65: =ROUNDDOWN(($P$2-D65)/365,0)*30 -> 60 | AD65: =SUM(R65:AC66) -> 0 | AJ65: 1 | AN65: 1 | AU65: 2 | AW65: 1 | AX65: 1 | AZ65: 1 | BA65: 1 | BB65: 1 | BC65: 1 | BE65: 2 | BF65: 1 | BH65: 1 | BK65: 1 | BO65: 1 | CD65: =SUM(BR65:CC66) -> 0 | CH65: 22 | CQ65: =SUM(CE65:CP66) -> 22 | CV65: 4 | DD65: =SUM(CR65:DC66) -> 4 | DL65: 8 | DM65: 30 | DN65: 14 | DQ65: =SUM(DE65:DP66) -> 52 | DS65: 52 | DT65: =K65+DS65 -> 44202 | DW65: =ROUNDDOWN(($DW$2-H65)/365,0)*30 -> 90 | DX65: =Q65+AD65+AQ65+BD65+BQ65+CD65+CQ65+DD65+DQ65 -> 78 | DY65: =P65-DX65 -> -18 | EN65: =SUM(DZ65:EM66) -> 0
E66: 01 Dic 2018 al 30 Nov 2019 | F66: 30
A67: 31 | B67: SALIRROSAS PONCE LILIANA | C67: 01 marzo 2007 | D67: 01/09/2020 | G67: =F67+F68+#REF!+#REF!+#REF!+#REF! -> #REF! | K67: 01/09/2020 | M67: 0 | N67: =K67+DS67+360 -> 44435 | P67: =ROUNDDOWN(($P$2-D67)/365,0)*30 -> 0 | DQ67: =SUM(DE67:DP68) -> 0 | DX67: =Q67+AD67+AQ67+BD67+BQ67+CD67+CQ67+DD67+DQ67 -> 0 | DY67: =P67-DX67 -> 0 | EN67: =SUM(DZ67:EM68) -> 0
A69: 32 | B69: TERRONES BECERRA MARISSA (INGRESO PLANILLA 01/07/2008) | D69: 01/07/2011 | E69: 01 Jul 2011 al 30 Jun 2012 Gozada | F69: 30 | G69: =F69+F70+#REF!+#REF!+#REF!+#REF!+#REF!+#REF!+#REF! -> #REF! | H69: 40766 | I69: =D69+8*360 -> 43605 | J69: 240 | K69: =I69+360 -> 43965 | L69: =K69+DS69 -> 44006 | M69: 30 | N69: =+L69+360 -> 44366 | P69: =ROUNDDOWN(($P$2-D69)/365,0)*30 -> 270 | T69: 1 | V69: 1 | X69: 2 | AA69: 1 | AD69: =SUM(R69:AC70) -> 5 | AE69: 7 | AJ69: 1 | AK69: 1 | AQ69: =SUM(AE69:AP70) -> 9 | AT69: 4 | AU69: 1 | AX69: 6 | AY69: 1 | AZ69: 1 | BA69: 1 | BB69: 3 | BD69: =SUM(AR69:BC70) -> 17 | BH69: 2 | BI69: 10 | BK69: 1 | BM69: 2 | BN69: 1 | BO69: 3 | BP69: 1 | BQ69: =SUM(BE69:BP70) -> 20 | BR69: 1 | BS69: 8 | BU69: 2 | BV69: 2 | BX69: 3 | BY69: 7 | CA69: 2 | CC69: 6 | CD69: =SUM(BR69:CC70) -> 31 | CE69: 2 | CF69: 2 | CG69: 6 | CI69: 4 | CL69: 5 | CN69: =3+1 -> 4 | CP69: 1 | CQ69: =SUM(CE69:CP70) -> 24 | CR69: 1 | CS69: 1 | CT69: 5 | CV69: 3 | CX69: 8 | CZ69: =1+1 -> 2 | DA69: =1+1+1 -> 3 | DB69: =1+2 -> 3 | DC69: =1+1 -> 2 | DD69: =SUM(CR69:DC70) -> 28 | DE69: 3 | DF69: 6 | DQ69: =SUM(DE69:DP70) -> 9 | DS69: ='Determ días de vacaciones'!S41 -> 41 | DW69: =ROUNDDOWN(($DW$2-H69)/365,0)*30 -> 270 | DX69: =Q69+AD69+AQ69+BD69+BQ69+CD69+CQ69+DD69+DQ69 -> 143 | DY69: =P69-DX69 -> 127 | DZ69: 2 | EA69: 15 | EB69: 15 | EC69: 15 | ED69: 15 | EE69: 15 | EF69: 15 | EG69: 15 | EH69: 15 | EI69: 5 | EN69: =SUM(DZ69:EM70) -> 127
E70: 01 Jul 2012 al 30 Jun 2013 Gozada | F70: 30
A71: 33 | B71: TOMAYLLA TERRONES KATHERINE | D71: 01/02/2014 | E71: 01 Feb 2014 al 30 Ene 2015 Gozado | F71: 30 | G71: =F71+F72+#REF!+#REF!+#REF!+#REF! -> #REF! | H71: 41732 | I71: =D71+5*360 -> 43471 | J71: 150 | K71: =I71+360 -> 43831 | M71: 30 | N71: =K71+DS71+360 -> 44253 | P71: =ROUNDDOWN(($P$2-D71)/365,0)*30 -> 180 | AD71: =SUM(R71:AC72) -> 0 | AJ71: 1 | AN71: 1 | AQ71: =SUM(AE71:AP72) -> 2 | AU71: 2 | AW71: 1 | AX71: 1 | AZ71: 1 | BA71: 1 | BB71: 1 | BC71: 1 | BD71: =SUM(AR71:BC72) -> 8 | BE71: 2 | BF71: 1 | BH71: 1 | BK71: 1 | BO71: 1 | BQ71: =SUM(BE71:BP72) -> 6 | CC71: 6 | CD71: =SUM(BR71:CC72) -> 6 | CF71: 1 | CQ71: =SUM(CE71:CP72) -> 1 | CT71: 1 | CW71: 1 | CX71: 1 | CY71: 1 | CZ71: 1 | DA71: 2 | DD71: =SUM(CR71:DC72) -> 7 | DF71: 1 | DM71: 12 | DQ71: =SUM(DE71:DP72) -> 13 | DS71: ='Determ días de vacaciones'!S42 -> 62 | DT71: =K71+DS71 -> 43893 | DW71: =ROUNDDOWN(($DW$2-H71)/365,0)*30 -> 180 | DX71: =Q71+AD71+AQ71+BD71+BQ71+CD71+CQ71+DD71+DQ71 -> 43 | DY71: =P71-DX71 -> 137 | DZ71: 15 | EA71: 15 | EB71: 15 | EC71: 15 | ED71: 15 | EE71: 15 | EF71: 15 | EG71: 15 | EH71: 15 | EI71: 2 | EN71: =SUM(DZ71:EM72) -> 137
E72: 01 Feb 2015 al 30 Ene 2016 | F72: 30
A73: 34 | B73: VENEGAS MARCHAND FRANCISCO | C73: 01 marzo 2007 | D73: 01/01/2019 | E73: 01 ene 2019 al 31 dic 2019 | F73: 30 | G73: =F73+F74+#REF!+#REF!+#REF!+#REF! -> #REF! | H73: 43527 | K73: 43831 | M73: 30 | N73: =K73+DS73+360 -> 44253 | P73: =ROUNDDOWN(($P$2-D73)/365,0)*30 -> 30 | DQ73: =SUM(DE73:DP74) -> 0 | DS73: ='Determ días de vacaciones'!S43 -> 62 | DT73: =K73+DS73 -> 43893 | DW73: =ROUNDDOWN(($DW$2-H73)/365,0)*30 -> 30 | DX73: =Q73+AD73+AQ73+BD73+BQ73+CD73+CQ73+DD73+DQ73 -> 0 | DY73: =P73-DX73 -> 30 | EN73: =SUM(DZ73:EM74) -> 0
E74: 01 Ene 2020 al 31 Dic 2020
A75: 35 | B75: YNCIO JIMENEZ SILVIA | D75: 01/01/2018 | E75: 01 Ene 2018 al 31 Dic 2018 Gozada | F75: 30 | G75: =F75+F76+#REF! -> #REF! | H75: 43148 | I75: =D75+2*360 -> 43821 | J75: 60 | K75: =I75+360 -> 44181 | L75: =K75+DS75 -> 44228 | M75: 0 | N75: 44228 | P75: =ROUNDDOWN(($P$2-D75)/365,0)*30 -> 60 | AD75: =SUM(R75:AC76) -> 0 | AJ75: 1 | AN75: 1 | AU75: 2 | AW75: 1 | AX75: 1 | AZ75: 1 | BA75: 1 | BB75: 1 | BC75: 1 | BE75: 2 | BF75: 1 | BH75: 1 | BK75: 1 | BO75: 1 | CD75: =SUM(BR75:CC76) -> 0 | CG75: 6 | CI75: 1 | CK75: 2 | CM75: 7 | CP75: 14 | CQ75: =SUM(CE75:CP76) -> 30 | CW75: 17 | CX75: 3 | DC75: 13 | DD75: =SUM(CR75:DC76) -> 33 | DM75: 15 | DN75: 1 | DQ75: =SUM(DE75:DP76) -> 16 | DS75: ='Determ días de vacaciones'!S44 -> 47 | DT75: =K75+DS75 -> 44228 | DW75: =ROUNDDOWN(($DW$2-H75)/365,0)*30 -> 60 | DX75: =Q75+AD75+AQ75+BD75+BQ75+CD75+CQ75+DD75+DQ75 -> 79 | DY75: =P75-DX75 -> -19 | EN75: =SUM(DZ75:EM76) -> 0
E76: 01 Ene 2019 al 31 Dic 2019 Gozada | F76: 30
A77: 36 | B77: YON UTRILLA LUIS | D77: 01/08/2018 | E77: 01 Ago 2018 al 31 Jul 2019 | F77: 30 | G77: =F77+F78+#REF! -> #REF! | H77: 43390 | I77: =D77+360 -> 43673 | J77: 30 | K77: =I77+360 -> 44033 | L77: =K77+DS77 -> 44110 | M77: 30 | N77: =+L77+360 -> 44470 | P77: =ROUNDDOWN(($P$2-D77)/365,0)*30 -> 60 | AD77: =SUM(R77:AC78) -> 0 | AJ77: 1 | AN77: 1 | AU77: 2 | AW77: 1 | AX77: 1 | AZ77: 1 | BA77: 1 | BB77: 1 | BC77: 1 | BE77: 2 | BF77: 1 | BH77: 1 | BK77: 1 | BO77: 1 | CD77: =SUM(BR77:CC78) -> 0 | CM77: 1 | CQ77: =SUM(CF77:CP78) -> 1 | CS77: 14 | DD77: =SUM(CR77:DC78) -> 14 | DG77: 7 | DL77: 30 | DM77: 2 | DQ77: =SUM(DE77:DP78) -> 39 | DS77: ='Determ días de vacaciones'!S45 -> 77 | DW77: =ROUNDDOWN(($DW$2-H77)/365,0)*30 -> 60 | DX77: =Q77+AD77+AQ77+BD77+BQ77+CD77+CQ77+DD77+DQ77 -> 54 | DY77: =P77-DX77 -> 6 | DZ77: 6 | EN77: =SUM(DZ77:EM78) -> 6
E78: 01 Ago 2019 al 31 Jul 2020 | F78: 30
A79: 37 | B79: ZURITA PEÑA JOANY | D79: 01/10/2014 | E79: 01 Oct 2014 al 30 Set 2015 Gozada | F79: 30 | G79: =F79+F80+#REF!+#REF!+#REF!+#REF! -> #REF! | H79: 41915 | I79: =D79+5*360 -> 43713 | J79: 150 | K79: =I79+360 -> 44073 | L79: =K79+DS79 -> 44075 | M79: 30 | N79: =+L79+360 -> 44435 | P79: =ROUNDDOWN(($P$2-D79)/365,0)*30 -> 180 | AD79: =SUM(R79:AC80) -> 0 | AN79: 1 | AP79: 4 | AQ79: =SUM(AE79:AP80) -> 5 | AT79: 2 | AV79: 2 | AX79: 1 | BC79: 15 | BD79: =SUM(AR79:BC80) -> 20 | BF79: 3 | BH79: 2 | BN79: 7 | BO79: 2 | BP79: 11 | BQ79: =SUM(BE79:BP80) -> 25 | BV79: 1 | BX79: 7 | CA79: 2 | CC79: 15 | CD79: =SUM(BR79:CC80) -> 25 | CG79: 7 | CI79: 1 | CL79: 3 | CP79: 2 | CQ79: =SUM(CE79:CP80) -> 13 | CT79: 2 | CZ79: 7 | DD79: =SUM(CR79:DC80) -> 9 | DQ79: =SUM(DE79:DP80) -> 0 | DS79: ='Determ días de vacaciones'!S46 -> 2 | DW79: =ROUNDDOWN(($DW$2-H79)/365,0)*30 -> 180 | DX79: =AQ79+BD79+BQ79+CD79+CQ79+DD79 -> 97 | DY79: =P79-DX79 -> 83 | DZ79: 15 | EA79: 15 | EB79: 15 | EC79: 15 | ED79: 15 | EE79: 8 | EN79: =SUM(DZ79:EM80) -> 83
E80: 01 Oct 2015 al 30 Set 2016 Gozada | F80: 30

Sheet vacaciones 2026
B1: REPORTE DE VACACIONES
B2: EMPLEADOS | D2: SALDOS DE DIAS POR GOZAR 2025 | E2: ENE | F2: FEB | G2: MAR | H2: ABR | I2: MAY | J2: JUN | K2: JUL | L2: AGO | M2: SET | N2: OCT | O2: NOV | P2: DIC | Q2: Total días gozados | R2: PENDIENTES POR GOZAR 2025 | S2: FECHAS DE VENCIMIENTO 2026 | T2: VACACIONES POR VENCER 2026 | U2: Vacaciones Pendientes por gozar 2026
B3: AREA DE GERENCIA
A4: 2 | B4: ASPILCUETA GUTIERREZ KAREN | C4: ASISTENTE GERENCIAL | D4: 120 | F4: 1 | G4: 1 | Q4: =SUM(E4:P4) -> 2 | R4: =+D4-Q4 -> 118 | S4: 46113 | T4: 30 | U4: =+R4+T4 -> 148
A5: 3 | B5: GRANDE PECEROS DAVID | C5: ADMINISTRADOR | D5: 44 | G5: 2 | Q5: =SUM(E5:P5) -> 2 | R5: =+D5-Q5 -> 42 | S5: 46296 | U5: =+R5+T5 -> 42
A6: 1 | B6: GRANDE ALCANTRA, RAUL NEVADA | C6: GERENTE GENERAL | D6: ='vacaciones 2023 '!U6 -> 0 | Q6: =SUM(E6:P6) -> 0 | R6: =+D6-Q6 -> 0 | U6: =+R6+T6 -> 0
B7: AREA DE PRESUPUESTO
A8: 7 | B8: YON UTRILLA LUIS | C8: ARQUITECTO | D8: 143 | Q8: =SUM(E8:P8) -> 0 | R8: =+D8-Q8 -> 143 | S8: 46311 | U8: =+R8+T8 -> 143
B9: VENEGAS MARCHAND FRANCISCO | C9: ING. CIVIL | D9: 9 | G9: 7 | Q9: =SUM(E9:P9) -> 7 | R9: =+D9-Q9 -> 2 | S9: 46235 | U9: =+R9+T9 -> 2
B10: ROMERO ARROYO, VALERIE FERNANDA | C10: ARQUITECTO | S10: 46388
B11: OCHOA GUTIERREZ ERICKSON | C11: ING. CIVIL | D11: -5 | Q11: =SUM(E11:P11) -> 0 | R11: =+D11-Q11 -> -5 | S11: 46102 | T11: 30 | U11: =+R11+T11 -> 25
B12: AREA DE OPERACIONES
A13: 11 | B13: ARROYO FALLA, VANESSA ALICIA | C13: ARQUITECTA | D13: 21 | Q13: =SUM(E13:P13) -> 0 | R13: =+D13-Q13 -> 21 | S13: 46113 | U13: =+R13+T13 -> 21 | W13: =W12-#REF!+1 -> #REF!
A14: 12 | B14: BAUTISTA MOLINA LUIS FERNANDO | C14: ING. CIVIL | D14: 148 | Q14: =SUM(E14:P14) -> 0 | R14: =+D14-Q14 -> 148 | S14: 46327 | U14: =+R14+T14 -> 148
B15: BRAVO GARCIA CESAR OMAR | C15: ARQUITECTO | D15: 0 | E15: 5 | Q15: =SUM(E15:P15) -> 5 | R15: =+D15-Q15 -> -5 | S15: 46054 | T15: 30 | U15: =+R15+T15 -> 25
A16: 13 | B16: BRIONES RIVERA, RICHARD | C16: ARQUITECTO | D16: 9 | Q16: =SUM(E16:P16) -> 0 | R16: =+D16-Q16 -> 9 | S16: 46054 | T16: 30 | U16: =+R16+T16 -> 39 | W16: 45996
B17: CARRANZA HOYOS GUILLERMO | C17: ING. CIVIL | D17: 30 | Q17: =SUM(E17:P17) -> 0 | R17: =+D17-Q17 -> 30 | S17: 46267 | U17: =+R17+T17 -> 30
B18: CASTRO VALERIO HASSANAL | C18: ARQUITECTO | D18: 0 | Q18: =SUM(E18:P18) -> 0 | R18: =+D18-Q18 -> 0 | S18: 46489 | U18: =+R18+T18 -> 0
B19: CHUMBIAUCA URIBE, JOSE CARLOS | C19: ING. CIVIL | D19: 0 | Q19: =SUM(E19:P19) -> 0 | R19: =+D19-Q19 -> 0 | S19: 46450 | U19: =+R19+T19 -> 0
A20: 14 | B20: COLETO PASTOR LUIS ENRIQUE | C20: ING. CIVIL | D20: 0 | Q20: =SUM(E20:P20) -> 0 | R20: =+D20-Q20 -> 0 | S20: 46023 | T20: 30 | U20: =+R20+T20 -> 30 | W20: 45983
B21: CUEVA RIVAS, JORGE ARMANDO | C21: ING. CIVIL | D21: 0 | Q21: =SUM(E21:P21) -> 0 | R21: =+D21-Q21 -> 0 | S21: 46442 | U21: =+R21+T21 -> 0
A22: 16 | B22: DAMBROSIO RIVERO LIZETH STEFANNY | C22: ARQUITECTA | D22: 22 | F22: 6 | Q22: =SUM(E22:P22) -> 6 | R22: =+D22-Q22 -> 16 | S22: 46023 | T22: 30 | U22: =+R22+T22 -> 46
B23: DEPAZ HUERTAS, JOSE DANIEL | C23: BIM | D23: 0 | Q23: =SUM(E23:P23) -> 0 | R23: =+D23-Q23 -> 0 | S23: 46331 | U23: =+R23+T23 -> 0
A24: 19 | B24: FLORES MANTILLA MARIANA | C24: ARQUITECTA | D24: 66 | E24: 15 | Q24: =SUM(E24:P24) -> 15 | R24: =+D24-Q24 -> 51 | S24: 46235 | U24: =+R24+T24 -> 51
A25: 4 | B25: GOYAS ABRAMONTE, JAVIER ENRRIQUE | C25: ING. CIVIL | D25: 135 | Q25: =SUM(E25:P25) -> 0 | R25: =+D25-Q25 -> 135 | S25: 46113 | T25: 30 | U25: =+R25+T25 -> 165
A26: 20 | B26: GRANDE ALCANTARA MILAGROS M. | C26: ARQUITECTA | D26: -16 | Q26: =SUM(E26:P26) -> 0 | R26: =+D26-Q26 -> -16 | S26: 46204 | U26: =+R26+T26 -> -16
B27: HABICH ACUÑA, JACQUELINE | C27: ARQUITECTO | D27: 0 | Q27: =SUM(E27:P27) -> 0 | R27: =+D27-Q27 -> 0 | S27: 46301 | U27: =+R27+T27 -> 0
B28: HERMITAÑO ASPILCUETA DIEGO ALFONSO | C28: ING. CIVIL - ASIST | D28: 60 | Q28: =SUM(E28:P28) -> 0 | R28: =+D28-Q28 -> 60 | S28: 46060 | U28: =+R28+T28 -> 60
B29: LEON TORRES JHOSSELYN | C29: ARQUITECTO | D29: 30 | H29: 18 | Q29: =SUM(E29:P29) -> 18 | R29: =+D29-Q29 -> 12 | S29: 46235 | U29: =+R29+T29 -> 12
B30: MEDINA POLO, OMAR | C30: ING. CIVIL | D30: 0 | Q30: =SUM(E30:P30) -> 0 | R30: =+D30-Q30 -> 0 | S30: 46447 | U30: =+R30+T30 -> 0
B31: MIRANDA HUAMAN, MILAGROS VIRGINIA ADALETE | C31: ARQUITECTO | D31: 30 | H31: 18 | I31: 12 | Q31: =SUM(E31:P31) -> 30 | R31: =+D31-Q31 -> 0 | S31: 46163 | U31: =+R31+T31 -> 0 | X31: 259 | Y31: =X31*Y29/X29 -> #DIV/0!
B32: NEYRA CUMPA JORGAN CESAR | C32: SOFTWARE | D32: 0 | F32: 1 | G32: 3 | Q32: =SUM(E32:P32) -> 4 | R32: =+D32-Q32 -> -4 | S32: 46419 | U32: =+R32+T32 -> -4
A33: 24 | B33: OSCCO GUILLEN EDWIN RAFAEL | C33: ING. CIVIL | D33: 84 | F33: 8 | Q33: =SUM(E33:P33) -> 8 | R33: =+D33-Q33 -> 76 | S33: 46327 | U33: =+R33+T33 -> 76
B34: PESEROS MOREYRA, ALEXANDER HEINZ | C34: ARQUITECTO | D34: 0 | Q34: =SUM(E34:P34) -> 0 | R34: =+D34-Q34 -> 0 | S34: 46097 | T34: 30 | U34: =+R34+T34 -> 30
A35: 5 | B35: RAMIREZ ROMAN MARCELO | C35: ING. CIVIL | D35: 236 | Q35: =SUM(E35:O35) -> 0 | R35: =+D35-Q35 -> 236 | S35: 46204 | U35: =+R35+T35 -> 236 | AL35: =C35*40% -> #VALUE!
B36: RAMOS RAMOS, LENIN ANTHONY | C36: ING. CIVIL | D36: 0 | Q36: =SUM(E36:P36) -> 0 | R36: =+D36-Q36 -> 0 | S36: 46420 | U36: =+R36+T36 -> 0
B37: ROBLES ARIAS HARIF ALDAIR | C37: ING. CIVIL | D37: 0 | Q37: =SUM(E37:P37) -> 0 | R37: =+D37-Q37 -> 0 | S37: 46357 | U37: =+R37+T37 -> 0
A38: ruiz | B38: RUIZ LOPEZ GEYSIN | C38: ING. CIVIL | D38: 30 | F38: 7 | Q38: =SUM(E38:P38) -> 7 | R38: =+D38-Q38 -> 23 | S38: 46211 | U38: =+R38+T38 -> 23
B39: VALDEZ RODRIGUEZ, KENYI JORGE | C39: ING. CIVIL | D39: 0 | Q39: =SUM(E39:P39) -> 0 | R39: =+D39-Q39 -> 0 | S39: 46255 | U39: =+R39+T39 -> 0
B40: VILLALOBOS ZUÑIGA, DIEGO ALONSO | C40: ING. CIVIL | D40: 0 | Q40: =SUM(E40:P40) -> 0 | R40: =+D40-Q40 -> 0 | S40: 46095 | U40: =+R40+T40 -> 0
B41: AREA CONTABLE
A42: 27 | B42: BACA WIESSE JOSE ALBERTO | C42: CONTADOR GENERAL | D42: 54 | E42: 6 | Q42: =SUM(E42:P42) -> 6 | R42: =+D42-Q42 -> 48 | S42: 46023 | T42: 30 | U42: =+R42+T42 -> 78
A43: 29 | B43: GUZMAN MANTARI INGRID | C43: ASISTENTE CONTABLE | D43: 40 | F43: 1 | H43: 14 | Q43: =SUM(E43:P43) -> 15 | R43: =+D43-Q43 -> 25 | S43: 46327 | U43: =+R43+T43 -> 25
B44: VILCHEZ VIDAL ANDREA ELENA | C44: ASISTENTE CONTABLE | D44: 38 | E44: 7 | Q44: =SUM(E44:P44) -> 7 | R44: =+D44-Q44 -> 31 | S44: 46174 | U44: =+R44+T44 -> 31
B45: AREA DE FINANZAS
A46: 30 | B46: GRANDE ALCANTARA GERMAN N. | C46: GERENTE DE FINANZAS | D46: 269 | Q46: =SUM(E46:P46) -> 0 | R46: =+D46-Q46 -> 269 | S46: 46113 | T46: 30 | U46: =+R46+T46 -> 299
A47: 31 | B47: JUAN PEDRO CRUZ, GIOVANNA PAULA | C47: ASISTENTE ADMINISTRATIVO | D47: 57 | E47: 1 | G47: =1+2 -> 3 | Q47: =SUM(E47:P47) -> 4 | R47: =+D47-Q47 -> 53 | S47: 46082 | T47: 30 | U47: =+R47+T47 -> 83
A48: 17 | B48: ESPEJO PACHECO, URSULA AMELIA | C48: ASISTENTE ADMINISTRATIVO | D48: ='vacaciones 2023 '!U42 -> 0 | Q48: =SUM(E48:P48) -> 0 | R48: =+D48-Q48 -> 0 | U48: =+R48+T48 -> 0 | X48: 45964
B49: AREA DE LOGISTICA | X49: 45991
A50: 34 | B50: BAUTISTA AYESTA WALTER | C50: ADMIN. DE OBRA | D50: 198 | Q50: =SUM(E50:P50) -> 0 | R50: =+D50-Q50 -> 198 | S50: 46143 | U50: =+R50+T50 -> 198 | X50: =X49-X48+1 -> 28
A51: 33 | B51: BAUTISTA AYESTA HEBER | C51: ADMIN. DE OBRA | D51: 178 | Q51: =SUM(E51:P51) -> 0 | R51: =+D51-Q51 -> 178 | S51: 46204 | U51: =+R51+T51 -> 178 | W51: 2023 | X51: 2024 | Y51: 2022
A52: 36 | B52: GRANDE ALCANTARA PAUL | C52: LOGISTICA | D52: 77 | Q52: =SUM(E52:P52) -> 0 | R52: =+D52-Q52 -> 77 | S52: 46023 | T52: 30 | U52: =+R52+T52 -> 107
B53: ANAYA ESPINOZA KEVIN RONALD | C53: LOGISTICA | D53: 60 | H53: 1 | Q53: =SUM(E53:P53) -> 1 | R53: =+D53-Q53 -> 59 | S53: 46327 | U53: =+R53+T53 -> 59
A54: 35 | B54: ALHUAY AYESTA, RAMIRO | C54: LOGISTICA | D54: 30 | F54: =1+1 -> 2 | H54: 14 | Q54: =SUM(E54:P54) -> 16 | R54: =+D54-Q54 -> 14 | S54: 46266 | U54: =+R54+T54 -> 14 | W54: 30 | X54: 30 | Y54: 15
B55: AREA DE REGURSOS HUMANOS
A56: 37 | B56: TOMAYLLA TERRONES KATHERINE | C56: RECURSOS HUMANOS | D56: 75 | E56: 1 | G56: 1 | Q56: =SUM(E56:P56) -> 2 | R56: =+D56-Q56 -> 73 | S56: 46074 | T56: 30 | U56: =+R56+T56 -> 103
A57: 37 | B57: ARROYO MUNIVE IVETTE | C57: RECURSOS HUMANOS | D57: 76 | E57: 1 | Q57: =SUM(E57:P57) -> 1 | R57: =+D57-Q57 -> 75 | S57: 46179 | U57: =+R57+T57 -> 75
B58: AREA DE SEGURIDAD | W58: 18 | X58: 2021
A59: 40 | B59: ZURITA PEÑA JOANY | C59: PREVENCION (OBRA) | D59: 87 | E59: 8 | Q59: =SUM(E59:P59) -> 8 | R59: =+D59-Q59 -> 79 | S59: 46296 | U59: =+R59+T59 -> 79 | W59: 60 | X59: 2022-2023 | AC59: 46118
A60: 38 | B60: OSCCO GUILLEN ZORAIDA | C60: JEFA DE SEGURIDAD | D60: 38 | E60: 11 | F60: 6 | G60: 1 | Q60: =SUM(E60:P60) -> 18 | R60: =+D60-Q60 -> 20 | S60: 46031 | T60: 30 | U60: =+R60+T60 -> 50 | W60: 5 | X60: 2022 | AC60: 46131
B61: QUISPE FAJARDO LIZ KAREN | C61: PREVENCION | D61: 16 | E61: 7 | G61: 7 | Q61: =SUM(E61:P61) -> 14 | R61: =+D61-Q61 -> 2 | S61: 46266 | U61: =+R61+T61 -> 2 | W61: 30 | X61: 2023 | AC61: =AC60-AC59+1 -> 14
B62: FALLA UMBO, MILTON RAUL | C62: JEFA DE SEGURIDAD (OBRA) | D62: 0 | Q62: =SUM(E62:P62) -> 0 | R62: =+D62-Q62 -> 0 | S62: 46098 | T62: 30 | U62: =+R62+T62 -> 30
B63: AREA COMERCIAL
A64: 41 | B64: PEÑA HERNANDEZ, FERNANDO FAVIAN | C64: GERENTE DE VENTAS | D64: 64 | Q64: =SUM(E64:P64) -> 0 | R64: =+D64-Q64 -> 64 | S64: 46143 | U64: =+R64+T64 -> 64

Sheet vacaciones 2025
B1: REPORTE DE VACACIONES
B2: EMPLEADOS | D2: SALDOS DE DIAS POR GOZAR 2024 | E2: ENE | F2: FEB | G2: MAR | H2: ABR | I2: MAY | J2: JUN | K2: JUL | L2: AGO | M2: SET | N2: OCT | O2: NOV | P2: DIC | Q2: Total días gozados | R2: PENDIENTES POR GOZAR 2024 | S2: FECHAS DE VENCIMIENTO 2025 | T2: VACACIONES POR VENCER 2025 | U2: Vacaciones Pendientes por gozar 2025
B3: AREA DE GERENCIA
A4: 2 | B4: ASPILCUETA GUTIERREZ KAREN | C4: ASISTENTE GERENCIAL | D4: ='vacaciones 2024'!U4 -> 96 | G4: 1 | I4: =1+2 -> 3 | J4: 1 | K4: 1 | Q4: =SUM(E4:P4) -> 6 | R4: =+D4-Q4 -> 90 | S4: 45735 | T4: 30 | U4: =+R4+T4 -> 120
A5: 3 | B5: GRANDE PECEROS DAVID | C5: ADMINISTRADOR | D5: ='vacaciones 2024'!U5 -> 37 | E5: 11 | F5: 4 | I5: 1 | K5: 7 | Q5: =SUM(E5:P5) -> 23 | R5: =+D5-Q5 -> 14 | S5: 45950 | T5: 30 | U5: =+R5+T5 -> 44
A6: 1 | B6: GRANDE ALCANTRA, RAUL NEVADA | C6: GERENTE GENERAL | D6: ='vacaciones 2023 '!U6 -> 0 | Q6: =SUM(E6:P6) -> 0 | R6: =+D6-Q6 -> 0 | U6: =+R6+T6 -> 0
B7: AREA DE PRESUPUESTO
A8: 7 | B8: YON UTRILLA LUIS | C8: ARQUITECTO | D8: ='vacaciones 2024'!U8 -> 113 | Q8: =SUM(E8:P8) -> 0 | R8: =+D8-Q8 -> 113 | S8: 45581 | T8: 30 | U8: =+R8+T8 -> 143
B9: VENEGAS MARCHAND FRANCISCO | C9: ING. CIVIL | K9: 21 | Q9: =SUM(E9:P9) -> 21 | R9: =+D9-Q9 -> -21 | S9: 45870 | T9: 30 | U9: =+R9+T9 -> 9
B10: OCHOA GUTIERREZ ERICKSON | C10: ING. CIVIL | D10: ='vacaciones 2024'!U9 -> -5 | F10: 25 | J10: 4 | N10: 1 | Q10: =SUM(E10:P10) -> 30 | R10: =+D10-Q10 -> -35 | S10: 45737 | T10: 30 | U10: =+R10+T10 -> -5
B11: AREA DE OPERACIONES
A12: 5 | B12: RAMIREZ ROMAN MARCELO | C12: ING. CIVIL | D12: ='vacaciones 2024'!U11 -> 240 | E12: 15 | F12: 16 | J12: 3 | Q12: =SUM(E12:O12) -> 34 | R12: =+D12-Q12 -> 206 | S12: 45840 | T12: 30 | U12: =+R12+T12 -> 236 | AL12: =C12*40% -> #VALUE!
A13: 12 | B13: BAUTISTA MOLINA LUIS FERNANDO | C13: ING. CIVIL | D13: ='vacaciones 2024'!U16 -> 118 | Q13: =SUM(E13:P13) -> 0 | R13: =+D13-Q13 -> 118 | S13: 45953 | T13: 30 | U13: =+R13+T13 -> 148
A14: 4 | B14: GOYAS ABRAMONTE, JAVIER ENRRIQUE | C14: ING. CIVIL | D14: ='vacaciones 2024'!U12 -> 115 | F14: =4+6 -> 10 | Q14: =SUM(E14:P14) -> 10 | R14: =+D14-Q14 -> 105 | S14: 45776 | T14: 30 | U14: =+R14+T14 -> 135
A15: 24 | B15: OSCCO GUILLEN EDWIN RAFAEL | C15: ING. CIVIL | D15: ='vacaciones 2024'!U14 -> 83 | E15: 7 | F15: 15 | G15: 7 | Q15: =SUM(E15:P15) -> 29 | R15: =+D15-Q15 -> 54 | S15: 45980 | T15: 30 | U15: =+R15+T15 -> 84
A16: 19 | B16: FLORES MANTILLA MARIANA | C16: ARQUITECTA | D16: ='vacaciones 2024'!U13 -> 70 | F16: 21 | K16: 5 | O16: 8 | Q16: =SUM(E16:P16) -> 34 | R16: =+D16-Q16 -> 36 | S16: 45874 | T16: 30 | U16: =+R16+T16 -> 66
B17: HERMITAÑO ASPILCUETA DIEGO ALFONSO | C17: ING. CIVIL - ASIST | D17: ='vacaciones 2024'!U40 -> 30 | Q17: =SUM(E17:P17) -> 0 | R17: =+D17-Q17 -> 30 | S17: 45890 | T17: 30 | U17: =+R17+T17 -> 60
B18: MIRANDA HUAMAN, MILAGROS VIRGINIA ADALETE | C18: ARQUITECTO | Q18: =SUM(E18:P18) -> 0 | R18: =+D18-Q18 -> 0 | S18: 45802 | T18: 30 | U18: =+R18+T18 -> 30 | X18: 259 | Y18: =X18*Y16/X16 -> #DIV/0!
B19: LEON TORRES JHOSSELYN | C19: ARQUITECTO | Q19: =SUM(E19:P19) -> 0 | R19: =+D19-Q19 -> 0 | S19: 45870 | T19: 30 | U19: =+R19+T19 -> 30
A20: ruiz | B20: RUIZ LOPEZ GEYSIN | C20: ING. CIVIL | Q20: =SUM(E20:P20) -> 0 | R20: =+D20-Q20 -> 0 | S20: 45846 | T20: 30 | U20: =+R20+T20 -> 30
B21: CARRANZA HOYOS GUILLERMO | C21: ING. CIVIL | Q21: =SUM(E21:P21) -> 0 | R21: =+D21-Q21 -> 0 | S21: 45902 | T21: 30 | U21: =+R21+T21 -> 30
B22: YUEN VENTURO CESIA SHARON | C22: ING. CIVIL | D22: ='vacaciones 2024'!U22 -> 30 | I22: 29 | N22: 7 | P22: 7 | Q22: =SUM(E22:P22) -> 43 | R22: =+D22-Q22 -> -13 | S22: 45897 | T22: 30 | U22: =+R22+T22 -> 17 | X22: 365 | Y22: 30
A23: 16 | B23: DAMBROSIO RIVERO LIZETH STEFANNY | C23: ARQUITECTA | D23: ='vacaciones 2024'!U17 -> 45 | E23: 31 | F23: 13 | I23: 2 | N23: 7 | Q23: =SUM(E23:P23) -> 53 | R23: =+D23-Q23 -> -8 | S23: 45826 | T23: 30 | U23: =+R23+T23 -> 22
A24: 11 | B24: ARROYO FALLA, VANESSA ALICIA | C24: ARQUITECTA | D24: ='vacaciones 2024'!U20 -> -9 | Q24: =SUM(E24:P24) -> 0 | R24: =+D24-Q24 -> -9 | S24: 45826 | T24: 30 | U24: =+R24+T24 -> 21 | W24: =W23-W22+1 -> 1
A25: 13 | B25: BRIONES RIVERA, RICHARD | C25: ARQUITECTO | D25: ='vacaciones 2024'!U19 -> 40 | E25: 22 | F25: 25 | P25: 14 | Q25: =SUM(E25:P25) -> 61 | R25: =+D25-Q25 -> -21 | S25: 43862 | T25: 30 | U25: =+R25+T25 -> 9 | W25: 45996
A26: 14 | B26: COLETO PASTOR LUIS ENRIQUE | C26: ING. CIVIL | D26: ='vacaciones 2024'!U18 -> 0 | E26: 12 | F26: =10+8 -> 18 | Q26: =SUM(E26:P26) -> 30 | R26: =+D26-Q26 -> -30 | S26: 45658 | T26: 30 | U26: =+R26+T26 -> 0 | W26: 45983
B27: RODRIGUEZ ZAMBRANO, ELISEO HUGO | N27: 7 | Q27: =SUM(E27:P27) -> 7 | R27: =+D27-Q27 -> -7 | S27: 46121 | U27: =+R27+T27 -> -7
A28: 20 | B28: GRANDE ALCANTARA MILAGROS M. | C28: ARQUITECTA | D28: ='vacaciones 2024'!U15 -> 59 | F28: 28 | G28: 16 | N28: 26 | O28: 30 | P28: 5 | Q28: =SUM(E28:P28) -> 105 | R28: =+D28-Q28 -> -46 | S28: 45837 | T28: 30 | U28: =+R28+T28 -> -16
B29: DE LAS CASAS DE LOS SANTOS, FABRIZIO IBRAIM | C29: ING. CIVIL | Q29: =SUM(E29:P29) -> 0 | R29: =+D29-Q29 -> 0 | S29: 46318 | U29: =+R29+T29 -> 0
B30: DEPAZ HUERTAS, JOSE DANIEL | C30: BIM | Q30: =SUM(E30:P30) -> 0 | R30: =+D30-Q30 -> 0 | S30: 46331 | U30: =+R30+T30 -> 0
B31: HABICH ACUÑA, JACQUELINE | C31: ARQUITECTO | Q31: =SUM(E31:P31) -> 0 | R31: =+D31-Q31 -> 0 | S31: 0610/2026 | U31: =+R31+T31 -> 0
B32: PESEROS MOREYRA, ALEXANDER HEINZ | C32: ARQUITECTO | Q32: =SUM(E32:P32) -> 0 | R32: =+D32-Q32 -> 0 | S32: 46097 | U32: =+R32+T32 -> 0
B33: VALDEZ RODRIGUEZ, KENYI JORGE | C33: ING. CIVIL | Q33: =SUM(E33:P33) -> 0 | R33: =+D33-Q33 -> 0 | S33: 46255 | U33: =+R33+T33 -> 0
B34: VEGA MORENO, BRYAN GERARDO | C34: ING. CIVIL | Q34: =SUM(E34:P34) -> 0 | R34: =+D34-Q34 -> 0 | S34: 46350 | U34: =+R34+T34 -> 0
B35: ZULUETA CALDERON, ROBERT ALEXANDER | C35: ING. CIVIL | Q35: =SUM(E35:P35) -> 0 | R35: =+D35-Q35 -> 0 | S35: 46255 | U35: =+R35+T35 -> 0
B36: BRAVO GARCIA CESAR OMAR | C36: ARQUITECTO | Q36: =SUM(E36:P36) -> 0 | R36: =+D36-Q36 -> 0 | S36: 46023 | U36: =+R36+T36 -> 0
B37: ROBLES ARIAS HARIF ALDAIR | C37: ING. CIVIL | S37: 46357
B38: AREA CONTABLE
A39: 27 | B39: BACA WIESSE JOSE ALBERTO | C39: CONTADOR GENERAL | D39: ='vacaciones 2024'!U27 -> 67 | E39: 1 | F39: 12 | G39: 6 | I39: 14 | P39: 10 | Q39: =SUM(E39:P39) -> 43 | R39: =+D39-Q39 -> 24 | S39: 45662 | T39: 30 | U39: =+R39+T39 -> 54 | AA39: 46013
A40: 29 | B40: GUZMAN MANTARI INGRID | C40: ASISTENTE CONTABLE | D40: ='vacaciones 2024'!U30 -> 29 | E40: 1 | F40: =1+1 -> 2 | G40: 1 | I40: 1 | K40: =5+2 -> 7 | P40: 7 | Q40: =SUM(E40:P40) -> 19 | R40: =+D40-Q40 -> 10 | S40: 45953 | T40: 30 | U40: =+R40+T40 -> 40 | AA40: 46022
B41: VILCHEZ VIDAL ANDREA ELENA | C41: ASISTENTE CONTABLE | D41: ='vacaciones 2024'!U29 -> 9 | H41: 1 | Q41: =SUM(E41:P41) -> 1 | R41: =+D41-Q41 -> 8 | S41: 45809 | T41: 30 | U41: =+R41+T41 -> 38 | AA41: =AA40-AA39+1 -> 10
B42: AREA DE FINANZAS
A43: 30 | B43: GRANDE ALCANTARA GERMAN N. | C43: GERENTE DE FINANZAS | D43: ='vacaciones 2024'!U32 -> 239 | Q43: =SUM(E43:P43) -> 0 | R43: =+D43-Q43 -> 239 | S43: 45731 | T43: 30 | U43: =+R43+T43 -> 269
A44: 31 | B44: JUAN PEDRO CRUZ, GIOVANNA PAULA | C44: ASISTENTE ADMINISTRATIVO | D44: ='vacaciones 2024'!U33 -> 42 | E44: 2 | F44: =5+1 -> 6 | H44: =1+1 -> 2 | K44: =1+1 -> 2 | L44: 1 | O44: 2 | Q44: =SUM(E44:P44) -> 15 | R44: =+D44-Q44 -> 27 | S44: 45721 | T44: 30 | U44: =+R44+T44 -> 57
A45: 17 | B45: ESPEJO PACHECO, URSULA AMELIA | C45: ASISTENTE ADMINISTRATIVO | D45: ='vacaciones 2023 '!U42 -> 0 | Q45: =SUM(E45:P45) -> 0 | R45: =+D45-Q45 -> 0 | U45: =+R45+T45 -> 0 | X45: 45964
B46: AREA DE LOGISTICA | X46: 45991
A47: 34 | B47: BAUTISTA AYESTA WALTER | C47: ADMIN. DE OBRA | D47: ='vacaciones 2024'!U36 -> 210 | E47: 7 | O47: 28 | P47: 7 | Q47: =SUM(E47:P47) -> 42 | R47: =+D47-Q47 -> 168 | S47: 45812 | T47: 30 | U47: =+R47+T47 -> 198 | X47: =X46-X45+1 -> 28
A48: 33 | B48: BAUTISTA AYESTA HEBER | C48: ADMIN. DE OBRA | D48: ='vacaciones 2024'!U37 -> 185 | E48: 4 | F48: 17 | P48: 16 | Q48: =SUM(E48:P48) -> 37 | R48: =+D48-Q48 -> 148 | S48: 45843 | T48: 30 | U48: =+R48+T48 -> 178 | W48: 2023 | X48: 2024 | Y48: 2022
A49: 36 | B49: GRANDE ALCANTARA PAUL | C49: LOGISTICA | D49: ='vacaciones 2024'!U39 -> 65 | F49: 5 | G49: 13 | Q49: =SUM(E49:P49) -> 18 | R49: =+D49-Q49 -> 47 | S49: 46012 | T49: 30 | U49: =+R49+T49 -> 77
B50: ANAYA ESPINOZA KEVIN RONALD | C50: LOGISTICA | D50: ='vacaciones 2024'!U41 -> 30 | Q50: =SUM(E50:P50) -> 0 | R50: =+D50-Q50 -> 30 | S50: 45963 | T50: 30 | U50: =+R50+T50 -> 60
A51: 35 | B51: ALHUAY AYESTA, RAMIRO | C51: LOGISTICA | D51: ='vacaciones 2024'!U38 -> 35 | F51: 20 | G51: 7 | H51: 1 | O51: 7 | Q51: =SUM(E51:P51) -> 35 | R51: =+D51-Q51 -> 0 | S51: 45951 | T51: 30 | U51: =+R51+T51 -> 30 | W51: 30 | X51: 30 | Y51: 15
B52: AREA DE REGURSOS HUMANOS
A53: 37 | B53: TOMAYLLA TERRONES KATHERINE | C53: RECURSOS HUMANOS | D53: ='vacaciones 2024'!U43 -> 66 | J53: =3+3 -> 6 | O53: 15 | Q53: =SUM(E53:P53) -> 21 | R53: =+D53-Q53 -> 45 | S53: 45709 | T53: 30 | U53: =+R53+T53 -> 75
A54: 37 | B54: ARROYO MUNIVE IVETTE | C54: RECURSOS HUMANOS | D54: ='vacaciones 2024'!U44 -> 55 | F54: 8 | N54: 1 | Q54: =SUM(E54:P54) -> 9 | R54: =+D54-Q54 -> 46 | S54: 45814 | T54: 30 | U54: =+R54+T54 -> 76
B55: AREA DE SEGURIDAD | W55: 18 | X55: 2021
A56: 40 | B56: ZURITA PEÑA JOANY | C56: PREVENCION (OBRA) | D56: ='vacaciones 2024'!U46 -> 78 | F56: 21 | Q56: =SUM(E56:P56) -> 21 | R56: =+D56-Q56 -> 57 | S56: 45891 | T56: 30 | U56: =+R56+T56 -> 87 | W56: 60 | X56: 2022-2023
A57: 38 | B57: OSCCO GUILLEN ZORAIDA | C57: JEFA DE SEGURIDAD | D57: ='vacaciones 2024'!U47 -> 39 | E57: 4 | F57: 21 | I57: =1+1 -> 2 | N57: 1 | P57: 3 | Q57: =SUM(E57:P57) -> 31 | R57: =+D57-Q57 -> 8 | S57: 45981 | T57: 30 | U57: =+R57+T57 -> 38 | W57: 5 | X57: 2022 | AD57: 46020
B58: QUISPE FAJARDO LIZ KAREN | C58: PREVENCION | D58: ='vacaciones 2024'!U48 -> 26 | E58: 14 | F58: 21 | K58: 5 | Q58: =SUM(E58:P58) -> 40 | R58: =+D58-Q58 -> -14 | S58: 45901 | T58: 30 | U58: =+R58+T58 -> 16 | W58: 30 | X58: 2023 | AD58: 46022
B59: MENDIETA GRANDE, MATEO | C59: PREVENCION | Q59: =SUM(E59:P59) -> 0 | R59: =+D59-Q59 -> 0 | S59: 46122 | U59: =+R59+T59 -> 0 | AD59: =AD58-AD57+1 -> 3
B60: FALLA UMBO, MILTON RAUL | C60: JEFA DE SEGURIDAD (OBRA) | Q60: =SUM(E60:P60) -> 0 | R60: =+D60-Q60 -> 0 | S60: 46098 | U60: =+R60+T60 -> 0
A61: 39 | B61: OSCCO GUILLEN MARIBEL | C61: PREVENCION | D61: ='vacaciones 2024'!U50 -> 59 | G61: 11 | H61: 30 | I61: 31 | J61: 17 | Q61: =SUM(E61:P61) -> 89 | R61: =+D61-Q61 -> -30 | S61: 45658 | T61: 30 | U61: =+R61+T61 -> 0 | W61: 12 | X61: 2023
B62: AREA COMERCIAL
A63: 41 | B63: PEÑA HERNANDEZ, FERNANDO FAVIAN | C63: GERENTE DE VENTAS | D63: ='vacaciones 2024'!U52 -> 60 | E63: 8 | F63: 7 | L63: 11 | Q63: =SUM(E63:P63) -> 26 | R63: =+D63-Q63 -> 34 | S63: 45844 | T63: 30 | U63: =+R63+T63 -> 64

Sheet vacaciones 2024
B1: REPORTE DE VACACIONES
B2: EMPLEADOS | D2: SALDOS DE DIAS POR GOZAR 2023 | E2: ENE | F2: FEB | G2: MAR | H2: ABR | I2: MAY | J2: JUN | K2: JUL | L2: AGO | M2: SET | N2: OCT | O2: NOV | P2: DIC | Q2: Total días gozados | R2: PENDIENTES POR GOZAR 2023 | S2: FECHAS DE VENCIMIENTO 2024 | T2: VACACIONES POR VENCER 2024 | U2: Vacaciones Pendientes por gozar 2024
B3: AREA DE GERENCIA
A4: 2 | B4: ASPILCUETA GUTIERREZ KAREN | C4: ASISTENTE GERENCIAL | D4: ='vacaciones 2023 '!U4 -> 77 | F4: 1 | L4: 6 | M4: 3 | O4: 1 | Q4: =SUM(E4:P4) -> 11 | R4: =+D4-Q4 -> 66 | S4: 45370 | T4: 30 | U4: =+R4+T4 -> 96
A5: 3 | B5: GRANDE PECEROS DAVID | C5: ADMINISTRADOR | D5: ='vacaciones 2023 '!U5 -> 75 | E5: 10 | F5: 18 | J5: 1 | K5: 14 | L5: 25 | Q5: =SUM(E5:P5) -> 68 | R5: =+D5-Q5 -> 7 | S5: 45585 | T5: 30 | U5: =+R5+T5 -> 37
A6: 1 | B6: GRANDE ALCANTRA, RAUL NEVADA | C6: GERENTE GENERAL | D6: ='vacaciones 2023 '!U6 -> 0 | Q6: =SUM(E6:P6) -> 0 | R6: =+D6-Q6 -> 0 | U6: =+R6+T6 -> 0
B7: AREA DE PRESUPUESTO
A8: 7 | B8: YON UTRILLA LUIS | C8: ARQUITECTO | D8: ='vacaciones 2023 '!U8 -> 83 | Q8: =SUM(E8:P8) -> 0 | R8: =+D8-Q8 -> 83 | S8: 45581 | T8: 30 | U8: =+R8+T8 -> 113
B9: OCHOA GUTIERREZ ERICKSON | C9: ING. CIVIL | D9: ='vacaciones 2023 '!U9 -> 10 | J9: 3 | K9: 11 | P9: =23+8 -> 31 | Q9: =SUM(E9:P9) -> 45 | R9: =+D9-Q9 -> -35 | S9: 45372 | T9: 30 | U9: =+R9+T9 -> -5
B10: AREA DE OPERACIONES
A11: 5 | B11: RAMIREZ ROMAN MARCELO | C11: ING. CIVIL | D11: ='vacaciones 2023 '!U11 -> 225 | K11: 15 | Q11: =SUM(E11:O11) -> 15 | R11: =+D11-Q11 -> 210 | S11: 45475 | T11: 30 | U11: =+R11+T11 -> 240
A12: 4 | B12: GOYAS ABRAMONTE, JAVIER ENRRIQUE | C12: ING. CIVIL | D12: ='vacaciones 2023 '!U12 -> 93 | F12: 4 | I12: 4 | Q12: =SUM(E12:P12) -> 8 | R12: =+D12-Q12 -> 85 | S12: 45411 | T12: 30 | U12: =+R12+T12 -> 115
A13: 19 | B13: FLORES MANTILLA MARIANA | C13: ARQUITECTA | D13: ='vacaciones 2023 '!U13 -> 54 | F13: 14 | Q13: =SUM(E13:P13) -> 14 | R13: =+D13-Q13 -> 40 | S13: 45509 | T13: 30 | U13: =+R13+T13 -> 70
A14: 24 | B14: OSCCO GUILLEN EDWIN RAFAEL | C14: ING. CIVIL | D14: ='vacaciones 2023 '!U14 -> 71 | E14: 15 | J14: 3 | Q14: =SUM(E14:P14) -> 18 | R14: =+D14-Q14 -> 53 | S14: 45615 | T14: 30 | U14: =+R14+T14 -> 83
A15: 20 | B15: GRANDE ALCANTARA MILAGROS M. | C15: ARQUITECTA | D15: ='vacaciones 2023 '!U15 -> 29 | Q15: =SUM(E15:P15) -> 0 | R15: =+D15-Q15 -> 29 | S15: 45472 | T15: 30 | U15: =+R15+T15 -> 59
A16: 12 | B16: BAUTISTA MOLINA LUIS FERNANDO | C16: ING. CIVIL | D16: ='vacaciones 2023 '!U16 -> 88 | Q16: =SUM(E16:P16) -> 0 | R16: =+D16-Q16 -> 88 | S16: 45588 | T16: 30 | U16: =+R16+T16 -> 118
A17: 16 | B17: DAMBROSIO RIVERO LIZETH STEFANNY | C17: ARQUITECTA | D17: ='vacaciones 2023 '!U17 -> 35 | J17: 7 | O17: 3 | P17: 10 | Q17: =SUM(E17:P17) -> 20 | R17: =+D17-Q17 -> 15 | S17: 45461 | T17: 30 | U17: =+R17+T17 -> 45
A18: 14 | B18: COLETO PASTOR LUIS ENRIQUE | C18: ING. CIVIL | D18: ='vacaciones 2023 '!U18 -> -15 | K18: 15 | Q18: =SUM(E18:P18) -> 15 | R18: =+D18-Q18 -> -30 | S18: 45292 | T18: 30 | U18: =+R18+T18 -> 0
A19: 13 | B19: BRIONES RIVERA, RICHARD | C19: ARQUITECTO | D19: ='vacaciones 2023 '!U20 -> 10 | Q19: =SUM(E19:P19) -> 0 | R19: =+D19-Q19 -> 10 | S19: 45450 | T19: 30 | U19: =+R19+T19 -> 40
A20: 11 | B20: ARROYO FALLA, VANESSA ALICIA | C20: ARQUITECTA | D20: ='vacaciones 2023 '!U21 -> -6 | G20: 12 | J20: 6 | K20: 15 | Q20: =SUM(E20:P20) -> 33 | R20: =+D20-Q20 -> -39 | S20: 45461 | T20: 30 | U20: =+R20+T20 -> -9
B21: CASTRO VALERIO HASSANAL | C21: ARQUITECTO | D21: ='vacaciones 2023 '!U22 -> 28 | G21: 7 | O21: 13 | P21: 15 | Q21: =SUM(E21:P21) -> 35 | R21: =+D21-Q21 -> -7 | S21: 45643 | T21: 30 | U21: =+R21+T21 -> 23
B22: YUEN VENTURO CESIA SHARON | C22: ING. CIVIL | D22: ='vacaciones 2023 '!U25 -> 0 | Q22: =SUM(E22:P22) -> 0 | R22: =+D22-Q22 -> 0 | S22: 45532 | T22: 30 | U22: =+R22+T22 -> 30
B23: MIRANDA HUAMAN, MILAGROS VIRGINIA ADALETE | C23: ARQUITECTO | S23: 45802 | U23: =+R23+T23 -> 0
A24: ruiz | B24: RUIZ LOPEZ GEYSIN | C24: ING. CIVIL | S24: 45846 | U24: =+R24+T24 -> 0
B25: ASCONA GUELAC BRYAN | C25: ING. MECANICO ELECTRICISTA | D25: ='vacaciones 2023 '!U33 -> 0 | Q25: =SUM(E25:P25) -> 0 | R25: =+D25-Q25 -> 0 | S25: 45353 | T25: 30 | U25: =+R25+T25 -> 30
B26: AREA CONTABLE
A27: 27 | B27: BACA WIESSE JOSE ALBERTO | C27: CONTADOR GENERAL | D27: ='vacaciones 2023 '!U35 -> 64 | F27: 19 | J27: 3 | K27: 1 | N27: 1 | O27: 2 | P27: 1 | Q27: =SUM(E27:P27) -> 27 | R27: =+D27-Q27 -> 37 | S27: 45296 | T27: 30 | U27: =+R27+T27 -> 67
B28: SANCHEZ SOTELO FIORELLA GIULIANA | C28: ASISTENTE CONTABLE | D28: ='vacaciones 2023 '!U36 -> 5 | K28: 7 | M28: =1+1 -> 2 | N28: =1+1 -> 2 | O28: 2 | P28: 14 | Q28: =SUM(E28:P28) -> 27 | R28: =+D28-Q28 -> -22 | S28: 45444 | T28: 30 | U28: =+R28+T28 -> 8 | V28: 45588
B29: VILCHEZ VIDAL ANDREA ELENA | C29: ASISTENTE CONTABLE | D29: ='vacaciones 2023 '!U37 -> 4 | K29: 6 | N29: 3 | O29: 2 | P29: 14 | Q29: =SUM(E29:P29) -> 25 | R29: =+D29-Q29 -> -21 | S29: 45444 | T29: 30 | U29: =+R29+T29 -> 9 | V29: 45596
A30: 29 | B30: GUZMAN MANTARI INGRID | C30: ASISTENTE CONTABLE | D30: ='vacaciones 2023 '!U38 -> 27 | G30: 1 | J30: 1 | L30: 1 | M30: 2 | N30: =1+1+1+1 -> 4 | O30: 2 | P30: 17 | Q30: =SUM(E30:P30) -> 28 | R30: =+D30-Q30 -> -1 | S30: 45588 | T30: 30 | U30: =+R30+T30 -> 29 | V30: =V29-V28+1 -> 9
B31: AREA DE FINANZAS
A32: 30 | B32: GRANDE ALCANTARA GERMAN N. | C32: GERENTE DE FINANZAS | D32: ='vacaciones 2023 '!U40 -> 209 | Q32: =SUM(E32:P32) -> 0 | R32: =+D32-Q32 -> 209 | S32: 45366 | T32: 30 | U32: =+R32+T32 -> 239
A33: 31 | B33: JUAN PEDRO CRUZ, GIOVANNA PAULA | C33: ASISTENTE ADMINISTRATIVO | D33: ='vacaciones 2023 '!U41 -> 26 | E33: 1 | F33: =1+2 -> 3 | G33: 1 | J33: 2 | K33: 1 | L33: 2 | M33: 1 | N33: 2 | P33: 1 | Q33: =SUM(E33:P33) -> 14 | R33: =+D33-Q33 -> 12 | S33: 45356 | T33: 30 | U33: =+R33+T33 -> 42
A34: 17 | B34: ESPEJO PACHECO, URSULA AMELIA | C34: ASISTENTE ADMINISTRATIVO | D34: ='vacaciones 2023 '!U42 -> 0 | Q34: =SUM(E34:P34) -> 0 | R34: =+D34-Q34 -> 0 | U34: =+R34+T34 -> 0
B35: AREA DE LOGISTICA
A36: 34 | B36: BAUTISTA AYESTA WALTER | C36: ADMIN. DE OBRA | D36: ='vacaciones 2023 '!U44 -> 250 | N36: 9 | O36: 30 | P36: 31 | Q36: =SUM(E36:P36) -> 70 | R36: =+D36-Q36 -> 180 | S36: 45447 | T36: 30 | U36: =+R36+T36 -> 210
A37: 33 | B37: BAUTISTA AYESTA HEBER | C37: ADMIN. DE OBRA | D37: ='vacaciones 2023 '!U45 -> 170 | F37: 15 | Q37: =SUM(E37:P37) -> 15 | R37: =+D37-Q37 -> 155 | S37: 45478 | T37: 30 | U37: =+R37+T37 -> 185
A38: 35 | B38: ALHUAY AYESTA, RAMIRO | C38: LOGISTICA | D38: ='vacaciones 2023 '!U46 -> 21 | G38: 12 | P38: 4 | Q38: =SUM(E38:P38) -> 16 | R38: =+D38-Q38 -> 5 | S38: 45586 | T38: 30 | U38: =+R38+T38 -> 35
A39: 36 | B39: GRANDE ALCANTARA PAUL | C39: LOGISTICA | D39: ='vacaciones 2023 '!U47 -> 53 | J39: 7 | K39: 11 | Q39: =SUM(E39:P39) -> 18 | R39: =+D39-Q39 -> 35 | S39: 45647 | T39: 30 | U39: =+R39+T39 -> 65
B40: HERMITAÑO ASPILCUETA DIEGO ALFONSO | C40: LOGISTICA | D40: ='vacaciones 2023 '!U48 -> 0 | S40: 45525 | T40: 30 | U40: =+R40+T40 -> 30
B41: ANAYA ESPINOZA KEVIN RONALD | C41: LOGISTICA | D41: ='vacaciones 2023 '!U49 -> 0 | S41: 45598 | T41: 30 | U41: =+R41+T41 -> 30
B42: AREA DE REGURSOS HUMANOS
A43: 37 | B43: TOMAYLLA TERRONES KATHERINE | C43: RECURSOS HUMANOS | D43: ='vacaciones 2023 '!U52 -> 93 | E43: 3 | F43: 2 | J43: 1 | K43: 7 | O43: 2 | P43: 42 | Q43: =SUM(E43:P43) -> 57 | R43: =+D43-Q43 -> 36 | S43: 45343 | T43: 30 | U43: =+R43+T43 -> 66
A44: 37 | B44: ARROYO MUNIVE IVETTE | C44: RECURSOS HUMANOS | D44: ='vacaciones 2023 '!U53 -> 29 | F44: 1 | H44: 2 | K44: 1 | Q44: =SUM(E44:P44) -> 4 | R44: =+D44-Q44 -> 25 | S44: 45449 | T44: 30 | U44: =+R44+T44 -> 55
B45: AREA DE SEGURIDAD
A46: 40 | B46: ZURITA PEÑA JOANY | C46: PREVENCION | D46: ='vacaciones 2023 '!U55 -> 59 | L46: 11 | Q46: =SUM(E46:P46) -> 11 | R46: =+D46-Q46 -> 48 | S46: 45526 | T46: 30 | U46: =+R46+T46 -> 78
A47: 38 | B47: OSCCO GUILLEN ZORAIDA | C47: JEFA DE SEGURIDAD | D47: ='vacaciones 2023 '!U56 -> 57 | E47: 31 | F47: 17 | Q47: =SUM(E47:P47) -> 48 | R47: =+D47-Q47 -> 9 | S47: 45616 | T47: 30 | U47: =+R47+T47 -> 39
B48: QUISPE FAJARDO LIZ KAREN | C48: PREVENCION | D48: ='vacaciones 2023 '!U57 -> 0 | F48: 2 | O48: 2 | Q48: =SUM(E48:P48) -> 4 | R48: =+D48-Q48 -> -4 | S48: 45536 | T48: 30 | U48: =+R48+T48 -> 26
B49: MENDIETA GRANDE MATEO | C49: PREVENCION | M49: 7 | O49: 7 | Q49: =SUM(E49:P49) -> 14 | R49: =+D49-Q49 -> -14 | T49: 0 | U49: =+R49+T49 -> -14
A50: 39 | B50: OSCCO GUILLEN MARIBEL | C50: PREVENCION | D50: ='vacaciones 2023 '!U58 -> 29 | Q50: =SUM(E50:P50) -> 0 | R50: =+D50-Q50 -> 29 | S50: 45292 | T50: 30 | U50: =+R50+T50 -> 59
B51: AREA COMERCIAL
A52: 41 | B52: PEÑA HERNANDEZ, FERNANDO FAVIAN | C52: GERENTE DE VENTAS | D52: ='vacaciones 2023 '!U60 -> 40 | F52: 3 | L52: 7 | Q52: =SUM(E52:P52) -> 10 | R52: =+D52-Q52 -> 30 | S52: 45479 | T52: 30 | U52: =+R52+T52 -> 60

Sheet vacaciones 2023 
B1: REPORTE DE VACACIONES
B2: EMPLEADOS | D2: SALDOS DE DIAS POR GOZAR 2022 | E2: ENE | F2: FEB | G2: MAR | H2: ABR | I2: MAY | J2: JUN | K2: JUL | L2: AGO | M2: SET | N2: OCT | O2: NOV | P2: DIC | Q2: Total días gozados | R2: PENDIENTES POR GOZAR 2022 | S2: FECHAS DE VENCIMIENTO 2023 | T2: VACACIONES POR VENCER 2023 | U2: Vacaciones Pendientes por gozar 2023
B3: AREA DE GERENCIA
A4: 2 | B4: ASPILCUETA GUTIERREZ KAREN | C4: ASISTENTE GERENCIAL | D4: ='vacaciones 2022'!U4 -> 66 | E4: 1 | G4: 7 | I4: 1 | J4: 1 | K4: 7 | M4: 1 | P4: 1 | Q4: =SUM(E4:P4) -> 19 | R4: =+D4-Q4 -> 47 | S4: 45011 | T4: 30 | U4: =+R4+T4 -> 77
A5: 3 | B5: GRANDE PECEROS DAVID | C5: ADMINISTRADOR | D5: ='vacaciones 2022'!U5 -> 54 | J5: 2 | L5: 7 | Q5: =SUM(E5:P5) -> 9 | R5: =+D5-Q5 -> 45 | S5: 45226 | T5: 30 | U5: =+R5+T5 -> 75
A6: 1 | B6: GRANDE ALCANTRA, RAUL NEVADA | C6: GERENTE GENERAL | D6: ='vacaciones 2022'!U6 -> 0 | Q6: =SUM(E6:P6) -> 0 | R6: =+D6-Q6 -> 0 | U6: =+R6+T6 -> 0
B7: AREA DE PRESUPUESTO
A8: 7 | B8: YON UTRILLA LUIS | C8: ARQUITECTO | D8: ='vacaciones 2022'!U8 -> 53 | Q8: =SUM(E8:P8) -> 0 | R8: =+D8-Q8 -> 53 | S8: 45222 | T8: 30 | U8: =+R8+T8 -> 83
B9: OCHOA GUTIERREZ ERICKSON | C9: ING. CIVIL | D9: ='vacaciones 2022'!U10 -> -12 | J9: 7 | K9: 1 | Q9: =SUM(E9:P9) -> 8 | R9: =+D9-Q9 -> -20 | S9: 45006 | T9: 30 | U9: =+R9+T9 -> 10
B10: AREA DE OPERACIONES
A11: 5 | B11: RAMIREZ ROMAN MARCELO | C11: ING. CIVIL | D11: ='vacaciones 2022'!U12 -> 202 | I11: 7 | Q11: =SUM(E11:O11) -> 7 | R11: =+D11-Q11 -> 195 | S11: 45109 | T11: 30 | U11: =+R11+T11 -> 225
A12: 4 | B12: GOYAS ABRAMONTE, JAVIER ENRRIQUE | C12: ING. CIVIL | D12: ='vacaciones 2022'!U13 -> 79 | G12: 1 | H12: =7 -> 7 | I12: 6 | J12: 2 | Q12: =SUM(E12:P12) -> 16 | R12: =+D12-Q12 -> 63 | S12: 45045 | T12: 30 | U12: =+R12+T12 -> 93
A13: 19 | B13: FLORES MANTILLA MARIANA | C13: ARQUITECTA | D13: ='vacaciones 2022'!U14 -> 39 | E13: 15 | Q13: =SUM(E13:P13) -> 15 | R13: =+D13-Q13 -> 24 | S13: 45143 | T13: 30 | U13: =+R13+T13 -> 54 | V13: REGRESA A OFICINA EL 09/02/2023
A14: 24 | B14: OSCCO GUILLEN EDWIN RAFAEL | C14: ING. CIVIL | D14: ='vacaciones 2022'!U15 -> 65 | F14: 7 | J14: 3 | P14: 14 | Q14: =SUM(E14:P14) -> 24 | R14: =+D14-Q14 -> 41 | S14: 45249 | T14: 30 | U14: =+R14+T14 -> 71
A15: 20 | B15: GRANDE ALCANTARA MILAGROS M. | C15: ARQUITECTA | D15: ='vacaciones 2022'!U16 -> 60 | E15: 31 | H15: 7 | I15: 23 | Q15: =SUM(E15:P15) -> 61 | R15: =+D15-Q15 -> -1 | S15: 45106 | T15: 30 | U15: =+R15+T15 -> 29 | V15: VACACIONES DEL 01/01/2023 Y CONTANDO
A16: 12 | B16: BAUTISTA MOLINA LUIS FERNANDO | C16: ING. CIVIL | D16: ='vacaciones 2022'!U18 -> 58 | Q16: =SUM(E16:P16) -> 0 | R16: =+D16-Q16 -> 58 | S16: 45222 | T16: 30 | U16: =+R16+T16 -> 88
A17: 16 | B17: DAMBROSIO RIVERO LIZETH STEFANNY | C17: ARQUITECTA | D17: ='vacaciones 2022'!U19 -> 31 | F17: 9 | N17: 17 | Q17: =SUM(E17:P17) -> 26 | R17: =+D17-Q17 -> 5 | S17: 45095 | T17: 30 | U17: =+R17+T17 -> 35
A18: 14 | B18: COLETO PASTOR LUIS ENRIQUE | C18: ING. CIVIL | D18: ='vacaciones 2022'!U21 -> 16 | E18: 17 | F18: 29 | G18: 15 | Q18: =SUM(E18:P18) -> 61 | R18: =+D18-Q18 -> -45 | S18: 44927 | T18: 30 | U18: =+R18+T18 -> -15 | V18: LICENCIA POR PATERNIDAD HASTA LE 14/01/2023 | W18: regresa a oficina el 02/03/2023 | Y18: 45291
A19: 21 | B19: MENDOZA GARCÍA, ZINCIA | C19: ARQUITECTA | D19: ='vacaciones 2022'!U23 -> 0 | E19: 7 | Q19: =SUM(E19:P19) -> 7 | R19: =+D19-Q19 -> -7 | S19: 45083 | T19: 30 | U19: =+R19+T19 -> 23 | Y19: =Y18-Y17+1 -> 45292
A20: 13 | B20: BRIONES RIVERA, RICHARD | C20: ARQUITECTO | D20: ='vacaciones 2022'!U24 -> 2 | E20: 22 | Q20: =SUM(E20:P20) -> 22 | R20: =+D20-Q20 -> -20 | S20: 45084 | T20: 30 | U20: =+R20+T20 -> 10 | V20: REGRESA A OFICINA EL 23/01/2023
A21: 11 | B21: ARROYO FALLA, VANESSA ALICIA | C21: ARQUITECTA | D21: ='vacaciones 2022'!U25 -> -15 | J21: 12 | K21: 4 | L21: 5 | Q21: =SUM(E21:P21) -> 21 | R21: =+D21-Q21 -> -36 | S21: 45095 | T21: 30 | U21: =+R21+T21 -> -6 | V21: REGRESA A OFICINA EL 09/01/2023 - DM CVID
B22: CASTRO VALERIO HASSANAL | C22: ARQUITECTO | D22: ='vacaciones 2022'!U26 -> 20 | I22: 7 | P22: 15 | Q22: =SUM(E22:P22) -> 22 | R22: =+D22-Q22 -> -2 | S22: 45277 | T22: 30 | U22: =+R22+T22 -> 28
B23: HABICH ACUÑA, JACQUELINE | C23: ARQUITECTO | D23: ='vacaciones 2022'!U27 -> 0 | S23: 45163 | T23: 30 | U23: =+R23+T23 -> 30
B24: AGURTO MARTINEZ JOEL ARTURO | C24: ING. CIVIL | S24: 45581
B25: YUEN VENTURO CESIA SHARON | C25: ING. CIVIL | S25: 45532
B26: RUIZ LOPEZ GEYSIN YULER | S26: 45570
B27: LEANDRO CAMPOS WILFREDO JUNIOR | S27: 45518
B28: BENITES NAVARRO AGAPITO LEON | S28: 45570
B29: YVANCOVICH VASQUEZ RUBEN | S29: 45497
B30: ARAOZ TUANAMA CARR NATALY | S30: 45588
B31: JAIME HUAMAN FRANK ADAN | C31: SSOMA | S31: 45581
B32: VALEVALENZUELA VILCAMICHE JESSIC | C32: SSOMA | S32: 45536
B33: ASCONA GUELAC BRYAN | C33: ING. MECANICO ELECTRICISTA | S33: 45353 | U33: =+R33+T33 -> 0
B34: AREA CONTABLE
A35: 27 | B35: BACA WIESSE JOSE ALBERTO | C35: CONTADOR GENERAL | D35: ='vacaciones 2022'!U29-5 -> 52 | J35: 4 | L35: 1 | N35: 7 | P35: 6 | Q35: =SUM(E35:P35) -> 18 | R35: =+D35-Q35 -> 34 | S35: 44931 | T35: 30 | U35: =+R35+T35 -> 64
B36: SANCHEZ SOTELO FIORELLA GIULIANA | C36: ASISTENTE CONTABLE | D36: ='vacaciones 2022'!U30 -> -11 | K36: 7 | N36: 1 | P36: 6 | Q36: =SUM(E36:P36) -> 14 | R36: =+D36-Q36 -> -25 | S36: 45078 | T36: 30 | U36: =+R36+T36 -> 5
B37: VILCHEZ VIDAL ANDREA ELENA | C37: ASISTENTE CONTABLE | D37: ='vacaciones 2022'!U31 -> -11 | K37: 7 | M37: 1 | P37: =6+1 -> 7 | Q37: =SUM(E37:P37) -> 15 | R37: =+D37-Q37 -> -26 | S37: 45078 | T37: 30 | U37: =+R37+T37 -> 4
A38: 29 | B38: GUZMAN MANTARI INGRID | C38: ASISTENTE CONTABLE | D38: ='vacaciones 2022'!U32+5 -> 12 | G38: 1 | I38: 2 | J38: 1 | L38: 1 | M38: 1 | N38: 1 | O38: 2 | P38: 6 | Q38: =SUM(E38:P38) -> 15 | R38: =+D38-Q38 -> -3 | S38: 45222 | T38: 30 | U38: =+R38+T38 -> 27
B39: AREA DE FINANZAS
A40: 30 | B40: GRANDE ALCANTARA GERMAN N. | C40: GERENTE DE FINANZAS | D40: ='vacaciones 2022'!U34 -> 179 | Q40: =SUM(E40:P40) -> 0 | R40: =+D40-Q40 -> 179 | S40: 45000 | T40: 30 | U40: =+R40+T40 -> 209
A41: 31 | B41: JUAN PEDRO CRUZ, GIOVANNA PAULA | C41: ASISTENTE ADMINISTRATIVO | D41: ='vacaciones 2022'!U35 -> 14 | E41: 1 | F41: =1+1+1+1 -> 4 | G41: =1+1+1+2 -> 5 | J41: =1+1 -> 2 | K41: =1 -> 1 | M41: 1 | O41: 1 | P41: 3 | Q41: =SUM(E41:P41) -> 18 | R41: =+D41-Q41 -> -4 | S41: 44990 | T41: 30 | U41: =+R41+T41 -> 26
A42: 17 | B42: ESPEJO PACHECO, URSULA AMELIA | C42: ASISTENTE ADMINISTRATIVO | D42: ='vacaciones 2022'!U37 -> 0 | Q42: =SUM(E42:P42) -> 0 | R42: =+D42-Q42 -> 0 | U42: =+R42+T42 -> 0
B43: AREA DE LOGISTICA
A44: 34 | B44: BAUTISTA AYESTA WALTER | C44: ADMIN. DE OBRA | D44: ='vacaciones 2022'!U39 -> 232 | K44: 12 | Q44: =SUM(E44:P44) -> 12 | R44: =+D44-Q44 -> 220 | S44: 45081 | T44: 30 | U44: =+R44+T44 -> 250
A45: 33 | B45: BAUTISTA AYESTA HEBER | C45: ADMIN. DE OBRA | D45: ='vacaciones 2022'!U40 -> 173 | K45: 33 | Q45: =SUM(E45:P45) -> 33 | R45: =+D45-Q45 -> 140 | S45: 45112 | T45: 30 | U45: =+R45+T45 -> 170
A46: 35 | B46: ALHUAY AYESTA, RAMIRO | C46: LOGISTICA | D46: ='vacaciones 2022'!U41 -> 17 | G46: 1 | J46: =1+12 -> 13 | K46: 2 | M46: 1 | P46: 9 | Q46: =SUM(E46:P46) -> 26 | R46: =+D46-Q46 -> -9 | S46: 45220 | T46: 30 | U46: =+R46+T46 -> 21 | X46: 45264
A47: 36 | B47: GRANDE ALCANTARA PAUL | C47: LOGISTICA | D47: ='vacaciones 2022'!U42 -> 46 | O47: 23 | Q47: =SUM(E47:P47) -> 23 | R47: =+D47-Q47 -> 23 | S47: 45281 | T47: 30 | U47: =+R47+T47 -> 53 | X47: 45272
B48: HERMITAÑO ASPILCUETA DIEGO ALFONSO | C48: LOGISTICA | S48: 45525
B49: ANAYA ESPINOZA KEVIN RONALD | C49: LOGISTICA | S49: 45598
B50: PEREZ LARA LUIS ANTONIO | C50: ASISTENTE DE ALMACEN | D50: ='vacaciones 2022'!U43 -> 14 | Q50: =SUM(E50:P50) -> 0 | R50: =+D50-Q50 -> 14 | S50: 45184 | T50: 30 | U50: =+R50+T50 -> 44 | X50: =X47-X46+1 -> 9
B51: AREA DE REGURSOS HUMANOS
A52: 37 | B52: TOMAYLLA TERRONES KATHERINE | C52: RECURSOS HUMANOS | D52: ='vacaciones 2022'!U45 -> 74 | K52: 1 | L52: =6+1 -> 7 | M52: 1 | O52: 1 | P52: 1 | Q52: =SUM(E52:P52) -> 11 | R52: =+D52-Q52 -> 63 | S52: 44978 | T52: 30 | U52: =+R52+T52 -> 93
A53: 37 | B53: ARROYO MUNIVE IVETTE | C53: RECURSOS HUMANOS | D53: ='vacaciones 2022'!U46 -> -1 | Q53: =SUM(E53:P53) -> 0 | R53: =+D53-Q53 -> -1 | S53: 45083 | T53: 30 | U53: =+R53+T53 -> 29
B54: AREA DE SEGURIDAD
A55: 40 | B55: ZURITA PEÑA JOANY | C55: PREVENCION | D55: ='vacaciones 2022'!U48 -> 80 | E55: 31 | F55: 20 | Q55: =SUM(E55:P55) -> 51 | R55: =+D55-Q55 -> 29 | S55: 45160 | T55: 30 | U55: =+R55+T55 -> 59
A56: 38 | B56: OSCCO GUILLEN ZORAIDA | C56: JEFA DE SEGURIDAD | D56: ='vacaciones 2022'!U49 -> 50 | F56: 7 | I56: 1 | K56: 1 | P56: 14 | Q56: =SUM(E56:P56) -> 23 | R56: =+D56-Q56 -> 27 | S56: 45250 | T56: 30 | U56: =+R56+T56 -> 57 | X56: 45210
B57: QUISPE FAJARDO LIZ KAREN | S57: 45536
A58: 39 | B58: OSCCO GUILLEN MARIBEL | C58: PREVENCION | D58: ='vacaciones 2022'!U50 -> 6 | F58: 7 | Q58: =SUM(E58:P58) -> 7 | R58: =+D58-Q58 -> -1 | S58: 44927 | T58: 30 | U58: =+R58+T58 -> 29 | X58: 45212
B59: AREA COMERCIAL | X59: =X58-X56+1 -> 3
A60: 41 | B60: PEÑA HERNANDEZ, FERNANDO FAVIAN | C60: GERENTE DE VENTAS | D60: ='vacaciones 2022'!U52 -> 18 | L60: 5 | N60: 3 | Q60: =SUM(E60:P60) -> 8 | R60: =+D60-Q60 -> 10 | S60: 45113 | T60: 30 | U60: =+R60+T60 -> 40

Sheet vacaciones 2022
B1: REPORTE DE VACACIONES
B2: EMPLEADOS | D2: SALDOS DE DIAS POR GOZAR 2021 | E2: ENE | F2: FEB | G2: MAR | H2: ABR | I2: MAY | J2: JUN | K2: JUL | L2: AGO | M2: SET | N2: OCT | O2: NOV | P2: DIC | Q2: Total días gozados | R2: PENDIENTES POR GOZAR 2021 | S2: FECHAS DE VENCIMIENTO 2022 | T2: VACACIONES POR VENCER 2022 | U2: Vacaciones Pendientes por gozar 2022
B3: AREA DE GERENCIA
A4: 2 | B4: ASPILCUETA GUTIERREZ KAREN | C4: ASISTENTE GERENCIAL | D4: ='vacaciones 2021'!U5 -> 60 | K4: 15 | L4: 1 | M4: =1+1 -> 2 | N4: 5 | P4: 1 | Q4: =SUM(E4:P4) -> 24 | R4: =+D4-Q4 -> 36 | S4: =vacaciones!L9+360 -> 44646 | T4: 30 | U4: =+R4+T4 -> 66
A5: 3 | B5: GRANDE PECEROS DAVID | C5: ADMINISTRADOR | D5: ='vacaciones 2021'!U6 -> 33 | E5: 5 | P5: 4 | Q5: =SUM(E5:P5) -> 9 | R5: =+D5-Q5 -> 24 | S5: =vacaciones!L25+360 -> 44861 | T5: 30 | U5: =+R5+T5 -> 54
A6: 1 | B6: GRANDE ALCANTRA, RAUL NEVADA | C6: GERENTE GENERAL | D6: ='vacaciones 2021'!U4 -> 0 | Q6: =SUM(E6:P6) -> 0 | R6: =+D6-Q6 -> 0 | S6: =vacaciones!I26 -> 0 | U6: =+R6+T6 -> 0
B7: AREA DE PRESUPUESTO
A8: 7 | B8: YON UTRILLA LUIS | C8: ARQUITECTO | D8: ='vacaciones 2021'!U9 -> 34 | G8: =7 -> 7 | P8: 4 | Q8: =SUM(E8:P8) -> 11 | R8: =+D8-Q8 -> 23 | S8: =vacaciones!L42+360 -> 44857 | T8: 30 | U8: =+R8+T8 -> 53
A9: 6 | B9: OROSCO BALAREZO SILVIA | C9: ING. CIVIL | D9: ='vacaciones 2021'!U8 -> 21 | I9: 5 | N9: =1+1 -> 2 | O9: 3 | P9: 4 | Q9: =SUM(E9:P9) -> 14 | R9: =+D9-Q9 -> 7 | S9: =vacaciones!L31+360 -> 44764 | T9: 30 | U9: =+R9+T9 -> 37
B10: OCHOA GUTIERREZ ERICKSON | C10: ING. CIVIL | N10: 1 | P10: 11 | Q10: =SUM(E10:P10) -> 12 | R10: =+D10-Q10 -> -12 | S10: 45006 | U10: =+R10+T10 -> -12
B11: AREA DE OPERACIONES
A12: 5 | B12: RAMIREZ ROMAN MARCELO | C12: ING. CIVIL | D12: ='vacaciones 2021'!U15 -> 179 | O12: 7 | Q12: =SUM(E12:O12) -> 7 | R12: =+D12-Q12 -> 172 | S12: =vacaciones!L35+360 -> 44744 | T12: 30 | U12: =+R12+T12 -> 202
A13: 4 | B13: GOYAS ABRAMONTE, JAVIER ENRRIQUE | C13: ING. CIVIL | D13: ='vacaciones 2021'!U14 -> 57 | E13: 1 | G13: =1+1+1 -> 3 | O13: =1+3 -> 4 | Q13: =SUM(E13:P13) -> 8 | R13: =+D13-Q13 -> 49 | S13: =vacaciones!L21+360 -> 44680 | T13: 30 | U13: =+R13+T13 -> 79
A14: 19 | B14: FLORES MANTILLA MARIANA | C14: ARQUITECTA | D14: ='vacaciones 2021'!U16 -> 63 | F14: 15 | G14: 6 | O14: 3 | P14: 30 | Q14: =SUM(E14:P14) -> 54 | R14: =+D14-Q14 -> 9 | S14: =vacaciones!L20+360 -> 44778 | T14: 30 | U14: =+R14+T14 -> 39
A15: 24 | B15: OSCCO GUILLEN EDWIN RAFAEL | C15: ING. CIVIL | D15: ='vacaciones 2021'!U18 -> 35 | Q15: =SUM(E15:P15) -> 0 | R15: =+D15-Q15 -> 35 | S15: =vacaciones!L32+360 -> 44884.5 | T15: 30 | U15: =+R15+T15 -> 65
A16: 20 | B16: GRANDE ALCANTARA MILAGROS M. | C16: ARQUITECTA | D16: ='vacaciones 2021'!U19 -> 30 | Q16: =SUM(E16:P16) -> 0 | R16: =+D16-Q16 -> 30 | S16: =vacaciones!L23+360 -> 44741 | T16: 30 | U16: =+R16+T16 -> 60
A17: 10 | B17: ALTAMIRANO SULCA MANUEL | C17: ING. ELECTRICISTA | D17: ='vacaciones 2021'!U20 -> 29 | O17: 3 | P17: =26+5 -> 31 | Q17: =SUM(E17:P17) -> 34 | R17: =+D17-Q17 -> -5 | S17: =vacaciones!L7+360 -> 44815 | T17: 30 | U17: =+R17+T17 -> 25 | V17: FALTA FIRMA DE VACACIONES SE ENVIO SU BOLETA DE VACA PERO NO FIRMA
A18: 12 | B18: BAUTISTA MOLINA LUIS FERNANDO | C18: ING. CIVIL | D18: ='vacaciones 2021'!U22 -> 28 | Q18: =SUM(E18:P18) -> 0 | R18: =+D18-Q18 -> 28 | S18: =vacaciones!L14+360 -> 44857 | T18: 30 | U18: =+R18+T18 -> 58
A19: 16 | B19: DAMBROSIO RIVERO LIZETH STEFANNY | C19: ARQUITECTA | D19: ='vacaciones 2021'!U23 -> 16 | N19: 15 | Q19: =SUM(E19:P19) -> 15 | R19: =+D19-Q19 -> 1 | S19: =vacaciones!L18+360 -> 44730 | T19: 30 | U19: =+R19+T19 -> 31
B20: ARANYA MAMANI, NELSON | C20: ING. MECANICO ELECTRICISTA | D20: ='vacaciones 2021'!U27 -> 0 | Q20: =SUM(E20:P20) -> 0 | R20: =+D20-Q20 -> 0 | S20: 44682 | T20: 30 | U20: =+R20+T20 -> 30
A21: 14 | B21: COLETO PASTOR LUIS ENRIQUE | C21: ING. CIVIL | D21: ='vacaciones 2021'!U30 -> 0 | P21: 14 | Q21: =SUM(E21:P21) -> 14 | R21: =+D21-Q21 -> -14 | S21: 44562 | T21: 30 | U21: =+R21+T21 -> 16 | V21: FALTA FIRMA DE VACACIONES
B22: DAVILA MINA DANIEL SEBASTIAN | C22: ING. MECANICO ELECTRICISTA | D22: ='vacaciones 2021'!U31 -> 0 | Q22: =SUM(E22:P22) -> 0 | R22: =+D22-Q22 -> 0 | S22: 44806 | T22: 30 | U22: =+R22+T22 -> 30
A23: 21 | B23: MENDOZA GARCÍA, ZINCIA | C23: ARQUITECTA | D23: ='vacaciones 2021'!U21 -> 29 | N23: 30 | O23: 29 | Q23: =SUM(E23:P23) -> 59 | R23: =+D23-Q23 -> -30 | S23: =vacaciones!L28+360 -> 44718 | T23: 30 | U23: =+R23+T23 -> 0 | X23: 45272
A24: 13 | B24: BRIONES RIVERA, RICHARD | C24: ARQUITECTO | D24: ='vacaciones 2021'!U26 -> -9 | E24: 6 | P24: 13 | Q24: =SUM(E24:P24) -> 19 | R24: =+D24-Q24 -> -28 | S24: =vacaciones!L15+360 -> 44719 | T24: 30 | U24: =+R24+T24 -> 2 | X24: 45285
A25: 11 | B25: ARROYO FALLA, VANESSA ALICIA | C25: ARQUITECTA | D25: ='vacaciones 2021'!U24 -> 0 | E25: 14 | H25: 7 | N25: 4 | O25: 4 | P25: =3+13 -> 16 | Q25: =SUM(E25:P25) -> 45 | R25: =+D25-Q25 -> -45 | S25: =vacaciones!L8+360 -> 44730 | T25: 30 | U25: =+R25+T25 -> -15
B26: CASTRO VALERIO HASSANAL | C26: ARQUITECTO | P26: 10 | Q26: =SUM(E26:P26) -> 10 | R26: =+D26-Q26 -> -10 | S26: 44912 | T26: 30 | U26: =+R26+T26 -> 20 | V26: REINTEGRO A OBRA 29/12/2022
B27: HABICH ACUÑA, JACQUELINE | C27: ARQUITECTO | P27: 18 | S27: 45163 | V27: REINTEGRO A OBRA 31/12/2022
B28: AREA CONTABLE
A29: 27 | B29: BACA WIESSE JOSE ALBERTO | C29: CONTADOR GENERAL | D29: ='vacaciones 2021'!U39 -> 42 | F29: 1 | K29: 1 | L29: 1 | N29: 1 | P29: 11 | Q29: =SUM(E29:P29) -> 15 | R29: =+D29-Q29 -> 27 | S29: =vacaciones!L10+360 -> 44566 | T29: 30 | U29: =+R29+T29 -> 57 | V29: FALTA FIRMA DE VACA
B30: SANCHEZ SOTELO FIORELLA GIULIANA | C30: ASISTENTE CONTABLE | P30: 11 | Q30: =SUM(E30:P30) -> 11 | R30: =+D30-Q30 -> -11 | S30: 45078 | U30: =+R30+T30 -> -11
B31: VILCHEZ VIDAL ANDREA ELENA | C31: ASISTENTE CONTABLE | P31: 11 | Q31: =SUM(E31:P31) -> 11 | R31: =+D31-Q31 -> -11 | S31: 45078 | U31: =+R31+T31 -> -11
A32: 29 | B32: GUZMAN MANTARI INGRID | C32: ASISTENTE CONTABLE | D32: ='vacaciones 2021'!U42 -> -4 | F32: 2 | G32: 1 | J32: 2 | K32: 1 | L32: 1 | N32: 1 | P32: 11 | Q32: =SUM(E32:P32) -> 19 | R32: =+D32-Q32 -> -23 | S32: =vacaciones!L26+360 -> 44857 | T32: 30 | U32: =+R32+T32 -> 7
B33: AREA DE FINANZAS
A34: 30 | B34: GRANDE ALCANTARA GERMAN N. | C34: GERENTE DE FINANZAS | D34: ='vacaciones 2021'!U44 -> 149 | Q34: =SUM(E34:P34) -> 0 | R34: =+D34-Q34 -> 149 | S34: =vacaciones!L22+360 -> 44635 | T34: 30 | U34: =+R34+T34 -> 179
A35: 31 | B35: JUAN PEDRO CRUZ, GIOVANNA PAULA | C35: ASISTENTE ADMINISTRATIVO | D35: ='vacaciones 2021'!U45 -> 5 | E35: 1 | F35: =1+1 -> 2 | H35: =1+1 -> 2 | I35: =2+1 -> 3 | J35: 1 | L35: =1+1 -> 2 | M35: =1+1 -> 2 | N35: =4 -> 4 | O35: =1+1 -> 2 | P35: =1+1 -> 2 | Q35: =SUM(E35:P35) -> 21 | R35: =+D35-Q35 -> -16 | S35: =vacaciones!L27+360 -> 44625 | T35: 30 | U35: =+R35+T35 -> 14
B36: LOPEZ FERNANDEZ WUIMAR NAIRIM | C36: RECEPCION | D36: ='vacaciones 2021'!U46 -> -2 | E36: 1 | K36: 1 | L36: 2 | M36: =1+7 -> 8 | O36: =7+1 -> 8 | P36: 11 | Q36: =SUM(E36:P36) -> 31 | R36: =+D36-Q36 -> -33 | S36: 44652 | T36: 30 | U36: =+R36+T36 -> -3
A37: 17 | B37: ESPEJO PACHECO, URSULA AMELIA | C37: ASISTENTE ADMINISTRATIVO | D37: ='vacaciones 2021'!U47 -> 0 | Q37: =SUM(E37:P37) -> 0 | R37: =+D37-Q37 -> 0 | U37: =+R37+T37 -> 0
B38: AREA DE LOGISTICA
A39: 34 | B39: BAUTISTA AYESTA WALTER | C39: ADMIN. DE OBRA | D39: ='vacaciones 2021'!U49 -> 202 | Q39: =SUM(E39:P39) -> 0 | R39: =+D39-Q39 -> 202 | S39: =vacaciones!L13+360 -> 44716 | T39: 30 | U39: =+R39+T39 -> 232
A40: 33 | B40: BAUTISTA AYESTA HEBER | C40: ADMIN. DE OBRA | D40: ='vacaciones 2021'!U50 -> 143 | Q40: =SUM(E40:P40) -> 0 | R40: =+D40-Q40 -> 143 | S40: =vacaciones!L12+360 -> 44747 | T40: 30 | U40: =+R40+T40 -> 173
A41: 35 | B41: ALHUAY AYESTA, RAMIRO | C41: LOGISTICA | D41: ='vacaciones 2021'!U52 -> 7 | E41: 1 | N41: 14 | P41: 5 | Q41: =SUM(E41:P41) -> 20 | R41: =+D41-Q41 -> -13 | S41: =vacaciones!L6+360 -> 44855 | T41: 30 | U41: =+R41+T41 -> 17 | X41: 44917
A42: 36 | B42: GRANDE ALCANTARA PAUL | C42: LOGISTICA | D42: ='vacaciones 2021'!U51 -> 30 | J42: 14 | Q42: =SUM(E42:P42) -> 14 | R42: =+D42-Q42 -> 16 | S42: =vacaciones!L24+360 -> 44916 | T42: 30 | U42: =+R42+T42 -> 46 | X42: 44921
B43: PEREZ LARA LUIS ANTONIO | C43: ASISTENTE DE ALMACEN | D43: ='vacaciones 2021'!U53 -> -7 | M43: 9 | Q43: =SUM(E43:P43) -> 9 | R43: =+D43-Q43 -> -16 | S43: 44819 | T43: 30 | U43: =+R43+T43 -> 14 | X43: =X42-X41+1 -> 5
B44: AREA DE REGURSOS HUMANOS
A45: 37 | B45: TOMAYLLA TERRONES KATHERINE | C45: RECURSOS HUMANOS | D45: ='vacaciones 2021'!U55 -> 76 | L45: 1 | N45: 23 | O45: 6 | P45: 2 | Q45: =SUM(E45:P45) -> 32 | R45: =+D45-Q45 -> 44 | S45: =vacaciones!L39+360 -> 44613 | T45: 30 | U45: =+R45+T45 -> 74
A46: 37 | B46: ARROYO MUNIVE IVETTE | C46: RECURSOS HUMANOS | D46: ='vacaciones 2021'!U56 -> 0 | P46: 1 | Q46: =SUM(E46:P46) -> 1 | R46: =+D46-Q46 -> -1 | S46: 45083 | U46: =+R46+T46 -> -1
B47: AREA DE SEGURIDAD
A48: 40 | B48: ZURITA PEÑA JOANY | C48: PREVENCION | D48: ='vacaciones 2021'!U57 -> 60 | P48: 10 | Q48: =SUM(E48:P48) -> 10 | R48: =+D48-Q48 -> 50 | S48: =vacaciones!L43+360 -> 44795 | T48: 30 | U48: =+R48+T48 -> 80
A49: 38 | B49: OSCCO GUILLEN ZORAIDA | C49: JEFA DE SEGURIDAD | D49: ='vacaciones 2021'!U58 -> 42 | J49: 1 | N49: =3+1+3 -> 7 | P49: =5+9 -> 14 | Q49: =SUM(E49:P49) -> 22 | R49: =+D49-Q49 -> 20 | S49: =vacaciones!L33+360 -> 44885 | T49: 30 | U49: =+R49+T49 -> 50
A50: 39 | B50: OSCCO GUILLEN MARIBEL | C50: PREVENCION | D50: ='vacaciones 2021'!U59 -> -1 | G50: =4+4 -> 8 | L50: =2+1+1 -> 4 | N50: =1+3 -> 4 | O50: 2 | P50: 5 | Q50: =SUM(E50:P50) -> 23 | R50: =+D50-Q50 -> -24 | S50: 44562 | T50: 30 | U50: =+R50+T50 -> 6
B51: AREA COMERCIAL
A52: 41 | B52: PEÑA HERNANDEZ, FERNANDO FAVIAN | C52: GERENTE DE VENTAS | D52: ='vacaciones 2021'!U61 -> 36 | E52: 8 | I52: 15 | P52: 25 | Q52: =SUM(E52:P52) -> 48 | R52: =+D52-Q52 -> -12 | S52: =vacaciones!L34+360 -> 44748 | T52: 30 | U52: =+R52+T52 -> 18

Sheet vacaciones 2021
B1: REPORTE DE VACACIONES | E1: ENERO - DICIEMBRE 2021
B2: EMPLEADOS | D2: SALDOS DE DIAS POR GOZAR 2020 | E2: ENE | F2: FEB | G2: MAR | H2: ABR | I2: MAY | J2: JUN | K2: JUL | L2: AGO | M2: SET | N2: OCT | O2: NOV | P2: DIC | Q2: Total días gozados | R2: PENDIENTES POR GOZAR 2020 | S2: FECHAS DE VENCIMIENTO 2021 | T2: VACACIONES POR VENCER 2021 | U2: Pendientes por gozar 2021
B3: AREA DE GERENCIA
A4: 1 | B4: GRANDE ALCANTRA, RAUL NEVADA | C4: GERENTE GENERAL | D4: ='vacaciones 2020'!T25 -> 0 | Q4: =SUM(E4:P4) -> 0 | R4: =+D4-Q4 -> 0 | S4: =vacaciones!I26 -> 0 | U4: =+R4+T4 -> 0
A5: 2 | B5: ASPILCUETA GUTIERREZ KAREN | C5: ASISTENTE GERENCIAL | D5: ='vacaciones 2020'!T8 -> 70 | E5: 9 | I5: 1 | K5: 12 | L5: 18 | Q5: =SUM(E5:P5) -> 40 | R5: =+D5-Q5 -> 30 | S5: =vacaciones!L9 -> 44286 | T5: 30 | U5: =+R5+T5 -> 60
A6: 3 | B6: GRANDE PECEROS DAVID | C6: ADMINISTRADOR | D6: ='vacaciones 2020'!T26 -> 10 | E6: 1 | F6: 2 | G6: 1 | K6: 1 | M6: 1 | O6: 1 | Q6: =SUM(E6:P6) -> 7 | R6: =+D6-Q6 -> 3 | S6: =vacaciones!L25 -> 44501 | T6: 30 | U6: =+R6+T6 -> 33
B7: AREA DE PRESUPUESTO
A8: 6 | B8: OROSCO BALAREZO SILVIA | C8: ING. CIVIL | D8: ='vacaciones 2020'!T32 -> -2 | N8: 7 | Q8: =SUM(E8:P8) -> 7 | R8: =+D8-Q8 -> -9 | S8: =vacaciones!L31 -> 44404 | T8: 30 | U8: =+R8+T8 -> 21
A9: 7 | B9: YON UTRILLA LUIS | C9: ARQUITECTO | D9: ='vacaciones 2020'!T43 -> 4 | Q9: =SUM(E9:P9) -> 0 | R9: =+D9-Q9 -> 4 | S9: =vacaciones!L42 -> 44497 | T9: 30 | U9: =+R9+T9 -> 34
A10: 9 | B10: VENEGAS MARCHAND, FRANCISCO MARTIN | C10: ING. CIVIL | D10: ='vacaciones 2020'!T41 -> 0 | N10: 7 | O10: 1 | Q10: =SUM(E10:P10) -> 8 | R10: =+D10-Q10 -> -8 | S10: 44593 | U10: =+R10+T10 -> -8
A11: 8 | B11: MATINELLA TORREALBA, YUBRAHIM RAMON | C11: ING. CIVIL | N11: 1 | S11: 44562
B12: CASTRO AGUIRRE ANTHONY | C12: ING. CIVIL | Q12: =SUM(E12:P12) -> 0 | R12: =+D12-Q12 -> 0 | S12: 44806 | U12: =+R12+T12 -> 0
B13: AREA DE OPERACIONES
A14: 4 | B14: GOYAS ABRAMONTE, JAVIER ENRRIQUE | C14: ING. CIVIL | D14: ='vacaciones 2020'!T21 -> 28 | J14: 1 | Q14: =SUM(E14:P14) -> 1 | R14: =+D14-Q14 -> 27 | S14: =vacaciones!L21 -> 44320 | T14: 30 | U14: =+R14+T14 -> 57
A15: 5 | B15: RAMIREZ ROMAN MARCELO | C15: ING. CIVIL | D15: ='vacaciones 2020'!T36 -> 150 | J15: 1 | P15: 13 | Q15: =SUM(E15:O15) -> 1 | R15: =+D15-Q15 -> 149 | S15: =vacaciones!L35 -> 44384 | T15: 30 | U15: =+R15+T15 -> 179
A16: 19 | B16: FLORES MANTILLA MARIANA | C16: ARQUITECTA | D16: ='vacaciones 2020'!T20 -> 61 | K16: 19 | L16: 9 | Q16: =SUM(E16:P16) -> 28 | R16: =+D16-Q16 -> 33 | S16: =vacaciones!L20 -> 44418 | T16: 30 | U16: =+R16+T16 -> 63
A17: 23 | B17: OCHOA GUTIERREZ ERICKSON | C17: ING. CIVIL | D17: ='vacaciones 2020'!T31 -> 30 | J17: 1 | K17: 6 | P17: =15+8 -> 23 | Q17: =SUM(E17:P17) -> 30 | R17: =+D17-Q17 -> 0 | S17: =vacaciones!L30 -> 44442 | T17: 30 | U17: =+R17+T17 -> 30
A18: 24 | B18: OSCCO GUILLEN EDWIN RAFAEL | C18: ING. CIVIL | D18: ='vacaciones 2020'!T33 -> 25 | K18: 20 | Q18: =SUM(E18:P18) -> 20 | R18: =+D18-Q18 -> 5 | S18: =vacaciones!L32 -> 44524.5 | T18: 30 | U18: =+R18+T18 -> 35
A19: 20 | B19: GRANDE ALCANTARA MILAGROS M. | C19: ARQUITECTA | D19: ='vacaciones 2020'!T23 -> 81 | E19: 31 | F19: 28 | G19: 22 | Q19: =SUM(E19:P19) -> 81 | R19: =+D19-Q19 -> 0 | S19: =vacaciones!L23 -> 44381 | T19: 30 | U19: =+R19+T19 -> 30
A20: 10 | B20: ALTAMIRANO SULCA MANUEL | C20: ING. ELECTRICISTA | D20: ='vacaciones 2020'!T6 -> 44 | E20: 30 | F20: 14 | J20: 1 | Q20: =SUM(E20:P20) -> 45 | R20: =+D20-Q20 -> -1 | S20: =vacaciones!L7 -> 44455 | T20: 30 | U20: =+R20+T20 -> 29
A21: 21 | B21: MENDOZA GARCÍA, ZINCIA | C21: ARQUITECTA | D21: ='vacaciones 2020'!T29 -> 20 | K21: 21 | Q21: =SUM(E21:P21) -> 21 | R21: =+D21-Q21 -> -1 | S21: =vacaciones!L28 -> 44358 | T21: 30 | U21: =+R21+T21 -> 29
A22: 12 | B22: BAUTISTA MOLINA LUIS FERNANDO | C22: ING. CIVIL | D22: ='vacaciones 2020'!T13 -> -2 | Q22: =SUM(E22:P22) -> 0 | R22: =+D22-Q22 -> -2 | S22: =vacaciones!L14 -> 44497 | T22: 30 | U22: =+R22+T22 -> 28
A23: 16 | B23: DAMBROSIO RIVERO LIZETH STEFANNY | C23: ARQUITECTA | D23: ='vacaciones 2020'!T17 -> -12 | K23: =1+1 -> 2 | Q23: =SUM(E23:P23) -> 2 | R23: =+D23-Q23 -> -14 | S23: =vacaciones!L18 -> 44370 | T23: 30 | U23: =+R23+T23 -> 16
A24: 11 | B24: ARROYO FALLA, VANESSA ALICIA | C24: ARQUITECTA | D24: ='vacaciones 2020'!T7 -> -10 | J24: =8+1 -> 9 | P24: 11 | Q24: =SUM(E24:P24) -> 20 | R24: =+D24-Q24 -> -30 | S24: =vacaciones!L8 -> 44370 | T24: 30 | U24: =+R24+T24 -> 0
A25: 15 | B25: CORDOVA VELEZ, JULISSA | C25: ARQUITECTA | O25: =7+15 -> 22 | P25: 13 | Q25: =SUM(E25:P25) -> 35 | R25: =+D25-Q25 -> -35 | S25: =vacaciones!L17 -> 44359 | T25: 30 | U25: =+R25+T25 -> -5
A26: 13 | B26: BRIONES RIVERA, RICHARD | C26: ARQUITECTO | K26: 4 | O26: =7+15 -> 22 | P26: 13 | Q26: =SUM(E26:P26) -> 39 | R26: =+D26-Q26 -> -39 | S26: =vacaciones!L15 -> 44359 | T26: 30 | U26: =+R26+T26 -> -9
B27: ARANYA MAMANI, NELSON | C27: ING. MECANICO ELECTRICISTA | R27: =+D27-Q27 -> 0 | S27: 44682 | U27: =+R27+T27 -> 0
B28: ASCONA GUELAC JOHNNY BRYAN | C28: ING. CIVIL | R28: =+D28-Q28 -> 0 | S28: 44810 | U28: =+R28+T28 -> 0
B29: BENAVIDES SALAZAR MERY YOLANDA | C29: ING. CIVIL | R29: =+D29-Q29 -> 0 | S29: 44810 | U29: =+R29+T29 -> 0
A30: 14 | B30: COLETO PASTOR LUIS ENRIQUE | C30: ING. CIVIL | D30: ='vacaciones 2020'!T15 -> 0 | Q30: =SUM(E30:P30) -> 0 | R30: =+D30-Q30 -> 0 | S30: 44562 | U30: =+R30+T30 -> 0
B31: DAVILA MINA DANIEL SEBASTIAN | C31: ING. MECANICO ELECTRICISTA | R31: =+D31-Q31 -> 0 | S31: 44806 | U31: =+R31+T31 -> 0
B32: GALVEZ CACERES FIORELA | C32: ING. CIVIL | R32: =+D32-Q32 -> 0 | S32: 44813 | U32: =+R32+T32 -> 0
B33: LUCHINI SARMIENTO TERESA DE JESUS | C33: ING. CIVIL | R33: =+D33-Q33 -> 0 | S33: 44797 | U33: =+R33+T33 -> 0
B34: MACHA HUACHO ANDONI | C34: ING. CIVIL | R34: =+D34-Q34 -> 0 | S34: 44805 | U34: =+R34+T34 -> 0
B35: MOGROVEJO MENACHO MARIA BELEN | C35: ARQUITECTA | R35: =+D35-Q35 -> 0 | S35: 44810 | U35: =+R35+T35 -> 0
B36: RAMIREZ CHIRCCA ABED NEGO | C36: ARQUITECTO | R36: =+D36-Q36 -> 0 | S36: 44824 | U36: =+R36+T36 -> 0
B37: YVANCOVICH VASQUEZ ZVONKO RUBEN | C37: ING. CIVIL | R37: =+D37-Q37 -> 0 | S37: 44797 | U37: =+R37+T37 -> 0
B38: AREA CONTABLE
A39: 27 | B39: BACA WIESSE JOSE ALBERTO | C39: CONTADOR GENERAL | D39: ='vacaciones 2020'!T9 -> 50 | G39: 3 | H39: 11 | I39: 1 | J39: 6 | K39: =2+6 -> 8 | L39: 8 | O39: 1 | Q39: =SUM(E39:P39) -> 38 | R39: =+D39-Q39 -> 12 | S39: =vacaciones!L10 -> 44206 | T39: 30 | U39: =+R39+T39 -> 42
A40: 32 | B40: ALEJOS TORIBIO, SULELMA MELISA | C40: AUXILIAR CONTABLE | D40: ='vacaciones 2020'!T4 -> 55 | G40: 1 | H40: 5 | I40: =2+1+2 -> 5 | J40: 14 | K40: 6 | L40: =8+1 -> 9 | N40: 1 | Q40: =SUM(E40:P40) -> 41 | R40: =+D40-Q40 -> 14 | S40: =vacaciones!L5 -> 44511 | T40: 30 | U40: =+R40+T40 -> 44
A41: 28 | B41: ALARCON PEREZ LUIS | C41: ASISTENTE CONTABLE | D41: ='vacaciones 2020'!T3 -> 48 | H41: 5 | I41: =2+7 -> 9 | J41: =10 -> 10 | K41: =4+14 -> 18 | L41: =1+1 -> 2 | Q41: =SUM(E41:P41) -> 44 | R41: =+D41-Q41 -> 4 | S41: =vacaciones!L4 -> 44232 | T41: 30 | U41: =+R41+T41 -> 34
A42: 29 | B42: GUZMAN MANTARI INGRID | C42: ASISTENTE CONTABLE | D42: ='vacaciones 2020'!T27 -> -15 | K42: 1 | L42: 1 | O42: =1+15 -> 16 | P42: 1 | Q42: =SUM(E42:P42) -> 19 | R42: =+D42-Q42 -> -34 | S42: =vacaciones!L26 -> 44497 | T42: 30 | U42: =+R42+T42 -> -4
B43: AREA DE FINANZAS
A44: 30 | B44: GRANDE ALCANTARA GERMAN N. | C44: GERENTE DE FINANZAS | D44: ='vacaciones 2020'!T22 -> 175 | F44: 28 | G44: 28 | Q44: =SUM(E44:P44) -> 56 | R44: =+D44-Q44 -> 119 | S44: =vacaciones!L22 -> 44275 | T44: 30 | U44: =+R44+T44 -> 149
A45: 31 | B45: JUAN PEDRO CRUZ, GIOVANNA PAULA | C45: ASISTENTE ADMINISTRATIVO | D45: ='vacaciones 2020'!T28 -> -9 | E45: 1 | F45: 1 | I45: 1 | J45: =1+1 -> 2 | K45: 1 | L45: =1+1+1+1 -> 4 | M45: 1 | N45: =1+1 -> 2 | O45: 2 | P45: 1 | Q45: =SUM(E45:P45) -> 16 | R45: =+D45-Q45 -> -25 | S45: =vacaciones!L27 -> 44265 | T45: 30 | U45: =+R45+T45 -> 5
B46: LOPEZ FERNANDEZ WUIMAR NAIRIM | C46: RECEPCION | N46: 1 | P46: 1 | Q46: =SUM(E46:P46) -> 2 | R46: =+D46-Q46 -> -2 | S46: 44652 | U46: =+R46+T46 -> -2
A47: 17 | B47: ESPEJO PACHECO, URSULA AMELIA | C47: ASISTENTE ADMINISTRATIVO | D47: ='vacaciones 2020'!T18 -> 0 | R47: =+D47-Q47 -> 0 | U47: =+R47+T47 -> 0
B48: AREA DE LOGISTICA
A49: 34 | B49: BAUTISTA AYESTA WALTER | C49: ADMIN. DE OBRA | D49: ='vacaciones 2020'!T12 -> 262 | G49: 30 | L49: 15 | M49: 30 | N49: 15 | Q49: =SUM(E49:P49) -> 90 | R49: =+D49-Q49 -> 172 | S49: =vacaciones!L13 -> 44356 | T49: 30 | U49: =+R49+T49 -> 202
A50: 33 | B50: BAUTISTA AYESTA HEBER | C50: ADMIN. DE OBRA | D50: ='vacaciones 2020'!T11 -> 203 | K50: 20 | L50: 10 | M50: 30 | N50: 30 | Q50: =SUM(E50:P50) -> 90 | R50: =+D50-Q50 -> 113 | S50: =vacaciones!L12 -> 44387 | T50: 30 | U50: =+R50+T50 -> 143
A51: 36 | B51: GRANDE ALCANTARA PAUL | C51: LOGISTICA | D51: ='vacaciones 2020'!T24 -> 60 | E51: 31 | F51: 28 | G51: 1 | Q51: =SUM(E51:P51) -> 60 | R51: =+D51-Q51 -> 0 | S51: =vacaciones!L24 -> 44556 | T51: 30 | U51: =+R51+T51 -> 30
A52: 35 | B52: ALHUAY AYESTA, RAMIRO | C52: LOGISTICA | D52: ='vacaciones 2020'!T5 -> 0 | H52: 1 | P52: 22 | Q52: =SUM(E52:P52) -> 23 | R52: =+D52-Q52 -> -23 | S52: =vacaciones!L6 -> 44495 | T52: 30 | U52: =+R52+T52 -> 7
B53: PEREZ LARA LUIS ANTONIO | C53: ASISTENTE DE ALMACEN | N53: 7 | Q53: =SUM(E53:P53) -> 7 | R53: =+D53-Q53 -> -7 | S53: 44819 | U53: =+R53+T53 -> -7
B54: AREA DE REGURSOS HUMANOS
A55: 37 | B55: TOMAYLLA TERRONES KATHERINE | C55: RECURSOS HUMANOS | D55: ='vacaciones 2020'!T40 -> 121 | H55: 1 | J55: =1+14 -> 15 | K55: 14 | M55: 1 | N55: 14 | O55: =7+23 -> 30 | Q55: =SUM(E55:P55) -> 75 | R55: =+D55-Q55 -> 46 | S55: =vacaciones!L39 -> 44253 | T55: 30 | U55: =+R55+T55 -> 76
B56: AREA DE SEGURIDAD
A57: 40 | B57: ZURITA PEÑA JOANY | C57: PREVENCION | D57: ='vacaciones 2020'!T44 -> 81 | G57: 22 | H57: 15 | K57: 14 | Q57: =SUM(E57:P57) -> 51 | R57: =+D57-Q57 -> 30 | S57: =vacaciones!L43 -> 44435 | T57: 30 | U57: =+R57+T57 -> 60
A58: 38 | B58: OSCCO GUILLEN ZORAIDA | C58: JEFA DE SEGURIDAD | D58: ='vacaciones 2020'!T34 -> 86 | J58: 10 | K58: =20+11 -> 31 | L58: 31 | M58: 2 | Q58: =SUM(E58:P58) -> 74 | R58: =+D58-Q58 -> 12 | S58: =vacaciones!L33 -> 44525 | T58: 30 | U58: =+R58+T58 -> 42
A59: 39 | B59: OSCCO GUILLEN MARIBEL | C59: PREVENCION | M59: 1 | Q59: =SUM(E59:P59) -> 1 | R59: =+D59-Q59 -> -1 | S59: 44562 | U59: =+R59+T59 -> -1
B60: AREA COMERCIAL
A61: 41 | B61: PEÑA HERNANDEZ, FERNANDO FAVIAN | C61: GERENTE DE VENTAS | D61: ='vacaciones 2020'!T35 -> 72 | E61: 14 | I61: 1 | J61: 14 | K61: 24 | L61: 6 | N61: 7 | Q61: =SUM(E61:P61) -> 66 | R61: =+D61-Q61 -> 6 | S61: =vacaciones!L34 -> 44388 | T61: 30 | U61: =+R61+T61 -> 36

Sheet Deuda por vacaciones
A5: VACACIONES POR PAGAR
A6: 2021
A9: N° | B9: EMPLEADOS | C9: DIAS POR GOZAR | E9: BASE DE CALCULO | F9: MONTO POR PAGAR | H9: MESES DE VACACIONES COMPRADOS | I9: SALDO POR PAGAR
A10: 1 | B10: ALHUAY AYESTA, RAMIRO | C10: ='vacaciones 2023 '!U46 -> 21 | E10: 5500 | F10: =E10/30*C10 -> 3850 | I10: =F10-H10 -> 3850
A11: 3 | B11: ARANYA MAMANI, NELSON | C11: ='vacaciones 2023 '!#REF! -> #REF! | E11: 4102.5 | F11: =E11/30*C11 -> #REF! | I11: =F11-H11 -> #REF!
A12: 4 | B12: ARROYO FALLA VANESSA | C12: ='vacaciones 2023 '!U21 -> -6 | E12: 7200 | F12: =E12/30*C12 -> -1440 | I12: =F12-H12 -> -1440
A13: 5 | B13: ARROYO MUNIVE IVETTE | C13: ='vacaciones 2023 '!U53 -> 29 | E13: 2500 | F13: =E13/30*C13 -> 2416.6667 | I13: =F13-H13 -> 2416.6667
A14: 6 | B14: ASCONA GUELAC JOHNNY BRYAN | C14: ='vacaciones 2023 '!U33 -> 0 | E14: 5102.5 | F14: =E14/30*C14 -> 0 | I14: =F14-H14 -> 0
A15: 7 | B15: ASPILCUETA GUTIERREZ, KAREN CRISTINA | C15: ='vacaciones 2023 '!U4 -> 77 | E15: 7102.5 | F15: =E15/30*C15 -> 18229.75 | I15: =F15-H15 -> 18229.75
A16: 8 | B16: BACA WIEESE, JOSE ALBERTO | C16: ='vacaciones 2023 '!U35 -> 64 | E16: 7602.5 | F16: =E16/30*C16 -> 16218.667 | I16: =F16-H16 -> 16218.667
A17: 9 | B17: BAUTISTA AYESTA, HEBERT | C17: ='vacaciones 2023 '!U45 -> 170 | E17: 5902.5 | F17: =E17/30*C17 -> 33447.5 | I17: =F17-H17 -> 33447.5
A18: 10 | B18: BAUTISTA AYESTA, WALTER | C18: ='vacaciones 2023 '!U44 -> 250 | E18: 8000 | F18: =E18/30*C18 -> 66666.667 | I18: =F18-H18 -> 66666.667
A19: 11 | B19: BAUTISTA MOLINA LUIS FERNANDO | C19: ='vacaciones 2023 '!U16 -> 88 | E19: 3500 | F19: =E19/30*C19 -> 10266.667 | I19: =F19-H19 -> 10266.667
A20: 12 | B20: BRIONES RIVERA, RICHARD | C20: ='vacaciones 2023 '!U20 -> 10 | E20: 7302.5 | F20: =E20/30*C20 -> 2434.1667 | I20: =F20-H20 -> 2434.1667
A21: 13 | B21: CASTRO VALERIO HASSANAL | C21: ='vacaciones 2023 '!U22 -> 28 | E21: 4500 | F21: =E21/30*C21 -> 4200 | I21: =F21-H21 -> 4200
A22: 14 | B22: COLETO PASTOR LUIS | C22: ='vacaciones 2023 '!U18 -> -15 | E22: 7000 | F22: =E22/30*C22 -> -3500 | I22: =F22-H22 -> -3500
A23: 15 | B23: DAMBROSIO RIVERO, LIZETH STEFANNY | C23: ='vacaciones 2023 '!U17 -> 35 | E23: 5300 | F23: =E23/30*C23 -> 6183.3333 | I23: =F23-H23 -> 6183.3333
A24: 16 | B24: ESPEJO PACHECO, URSULA AMELIA | C24: ='vacaciones 2023 '!U42 -> 0 | E24: 2402.5 | F24: =E24/30*C24 -> 0 | I24: =F24-H24 -> 0
A25: 17 | B25: FLORES MANTILLA, MARIANA LORENA | C25: ='vacaciones 2023 '!U13 -> 54 | E25: 6102.5 | F25: =E25/30*C25 -> 10984.5 | I25: =F25-H25 -> 10984.5
A26: 18 | B26: GOYAS ABRAMONTE, JAVIER ENRRIQUE | C26: ='vacaciones 2023 '!U12 -> 93 | E26: 12702.5 | F26: =E26/30*C26 -> 39377.75 | I26: =F26-H26 -> 39377.75
A27: 19 | B27: GRANDE ALCANTARA, GERMAN NICOLAS | C27: ='vacaciones 2023 '!U40 -> 209 | E27: 8102.5 | F27: =E27/30*C27 -> 56447.417 | I27: =F27-H27 -> 56447.417
A28: 20 | B28: GRANDE ALCANTARA, MILAGROS MARGARITA | C28: ='vacaciones 2023 '!U15 -> 29 | E28: 7302.5 | F28: =E28/30*C28 -> 7059.0833 | I28: =F28-H28 -> 7059.0833
A29: 21 | B29: GRANDE ALCANTARA, PAUL JOSEPH | C29: ='vacaciones 2023 '!U47 -> 53 | E29: 5900 | F29: =E29/30*C29 -> 10423.333 | I29: =F29-H29 -> 10423.333
A30: 22 | B30: GRANDE ALCANTARA, RAUL NEVADA | C30: ='vacaciones 2023 '!U6 -> 0 | E30: 12702.5 | F30: =E30/30*C30 -> 0 | I30: =F30-H30 -> 0
A31: 23 | B31: GRANDE PECEROS, DAVID ISAAC | C31: ='vacaciones 2023 '!U5 -> 75 | E31: 5600 | F31: =E31/30*C31 -> 14000 | I31: =F31-H31 -> 14000
A32: 24 | B32: GUZMAN MANTARI, INGRID | C32: ='vacaciones 2023 '!U38 -> 27 | E32: 3500 | F32: =E32/30*C32 -> 3150 | I32: =F32-H32 -> 3150
A33: 25 | B33: HABICH ACUÑA, JACQUELINE | C33: ='vacaciones 2023 '!U23 -> 30 | E33: 1500 | F33: =E33/30*C33 -> 1500 | I33: =F33-H33 -> 1500
A34: 26 | B34: JUAN PEDRO CRUZ, GIOVANNA PAULA | C34: ='vacaciones 2023 '!U41 -> 26 | E34: 4052.5 | F34: =E34/30*C34 -> 3512.1667 | I34: =F34-H34 -> 3512.1667
A35: 27 | B35: LOPEZ FERNANDEZ WUILMAR NAIRIM | C35: ='vacaciones 2023 '!#REF! -> #REF! | E35: 2000 | F35: =E35/30*C35 -> #REF! | I35: =F35-H35 -> #REF!
A36: 28 | B36: MENDOZA GARCIA, ZINCIA ISAURA | C36: ='vacaciones 2023 '!U19 -> 23 | E36: 5367 | F36: =E36/30*C36 -> 4114.7 | I36: =F36-H36 -> 4114.7
A37: 29 | B37: OCHOA GUTIERREZ ERICKSON JAVIER | C37: ='vacaciones 2023 '!U9 -> 10 | E37: 4200 | F37: =E37/30*C37 -> 1400 | I37: =F37-H37 -> 1400
A38: 30 | B38: OROSCCO BALEREZO SILVIA | C38: ='vacaciones 2023 '!#REF! -> #REF! | E38: 9602.5 | F38: =E38/30*C38 -> #REF! | I38: =F38-H38 -> #REF!
A39: 31 | B39: OSCCO GUILLEN EDWIN RAFAEL | C39: ='vacaciones 2023 '!U14 -> 71 | E39: 6602.5 | F39: =E39/30*C39 -> 15625.917 | I39: =F39-H39 -> 15625.917
A40: 32 | B40: OSCCO GUILLEN MARIBEL | C40: ='vacaciones 2023 '!U58 -> 29 | E40: 2000 | F40: =E40/30*C40 -> 1933.3333 | I40: =F40-H40 -> 1933.3333
A41: 33 | B41: OSCO GUILLEN, ORMINDA ZORAIDA | C41: ='vacaciones 2023 '!U56 -> 57 | E41: 5202.5 | F41: =E41/30*C41 -> 9884.75 | I41: =F41-H41 -> 9884.75
A42: 34 | B42: PEÑA HERNANDEZ, FERNANDO FABIAN | C42: ='vacaciones 2023 '!U60 -> 40 | E42: 4102.5 | F42: =E42/30*C42 -> 5470 | I42: =F42-H42 -> 5470
A43: 35 | B43: PEREZ LARA LUIS ANTONIO | C43: ='vacaciones 2023 '!U50 -> 44 | E43: 1802.5 | F43: =E43/30*C43 -> 2643.6667 | I43: =F43-H43 -> 2643.6667
A44: 36 | B44: RAMIREZ ROMAN, JOSE MARCELO | C44: ='vacaciones 2023 '!U11 -> 225 | E44: 9302.5 | F44: =E44/30*C44 -> 69768.75 | I44: =F44-H44 -> 69768.75
A45: 37 | B45: SANCHEZ SOTELO FIORELLA | C45: ='vacaciones 2023 '!U36 -> 5 | E45: 2500 | F45: =E45/30*C45 -> 416.66667 | I45: =F45-H45 -> 416.66667
A46: 38 | B46: TOMAYLLA TERRONES, KATHERINE | C46: ='vacaciones 2023 '!U52 -> 93 | E46: 3500 | F46: =E46/30*C46 -> 10850 | I46: =F46-H46 -> 10850
A47: 39 | B47: VILCHEZ VIDAL ANDREA | C47: ='vacaciones 2023 '!U37 -> 4 | E47: 2200 | F47: =E47/30*C47 -> 293.33333 | I47: =F47-H47 -> 293.33333
A48: 40 | B48: YON UTRILLA, LUISCARLOS | C48: ='vacaciones 2023 '!U8 -> 83 | E48: 4602.5 | F48: =E48/30*C48 -> 12733.583 | I48: =F48-H48 -> 12733.583
A49: 41 | B49: ZURITA PEÑA, JOANY LINDAURA | C49: ='vacaciones 2023 '!U55 -> 59 | E49: 5000 | F49: =E49/30*C49 -> 9833.3333 | I49: =F49-H49 -> 9833.3333
C50: =SUM(C10:C49) -> #REF! | I50: =SUM(I10:I49) -> #REF!

Sheet CRONOGRAMA
B1: REPORTE DE VACACIONES
B2: EMPLEADOS | D2: 44197 | E2: 44228 | F2: 44256 | G2: 44287 | H2: 44317 | I2: 44348 | J2: 44349 | K2: 44350 | L2: 44351 | M2: 44352 | N2: 44353 | O2: 44354 | P2: 44355 | Q2: 44356 | R2: 44357 | S2: 44358 | T2: 44359 | U2: 44360 | V2: 44361 | W2: 44362 | X2: 44363 | Y2: 44364 | Z2: 44365 | AA2: 44366 | AB2: 44367 | AC2: 44368 | AD2: 44369 | AE2: 44370 | AF2: 44371 | AG2: 44372 | AH2: 44373 | AI2: 44374 | AJ2: 44375 | AK2: 44376 | AL2: 44377 | AM2: 44348 | AN2: 44378 | AO2: 44379 | AP2: 44380 | AQ2: 44381 | AR2: 44382 | AS2: 44383 | AT2: 44384 | AU2: 44385 | AV2: 44386 | AW2: 44387 | AX2: 44388 | AY2: 44389 | AZ2: 44390 | BA2: 44391 | BB2: 44392 | BC2: 44393 | BD2: 44394 | BE2: 44395 | BF2: 44396 | BG2: 44397 | BH2: 44398 | BI2: 44399 | BJ2: 44400 | BK2: 44401 | BL2: 44402 | BM2: 44403 | BN2: 44404 | BO2: 44405 | BP2: 44406 | BQ2: 44407 | BR2: 44408 | BS2: 44378 | BT2: 44409 | BU2: 44410 | BV2: 44411 | BW2: 44412 | BX2: 44413 | BY2: 44414 | BZ2: 44415 | CA2: 44416 | CB2: 44417 | CC2: 44418 | CD2: 44419 | CE2: 44420 | CF2: 44421 | CG2: 44422 | CH2: 44423 | CI2: 44424 | CJ2: 44425 | CK2: 44426 | CL2: 44427 | CM2: 44428 | CN2: 44429 | CO2: 44430 | CP2: 44431 | CQ2: 44432 | CR2: 44433 | CS2: 44434 | CT2: 44435 | CU2: 44436 | CV2: 44437 | CW2: 44438 | CX2: 44439 | CY2: 44409 | CZ2: 44440 | DA2: 44441 | DB2: 44442 | DC2: 44443 | DD2: 44444 | DE2: 44445 | DF2: 44446 | DG2: 44447 | DH2: 44448 | DI2: 44449 | DJ2: 44450 | DK2: 44451 | DL2: 44452 | DM2: 44453 | DN2: 44454 | DO2: 44455 | DP2: 44456 | DQ2: 44457 | DR2: 44458 | DS2: 44459 | DT2: 44460 | DU2: 44461 | DV2: 44462 | DW2: 44463 | DX2: 44464 | DY2: 44465 | DZ2: 44466 | EA2: 44467 | EB2: 44468 | EC2: 44469 | ED2: 44440 | EE2: 44470 | EF2: 44471 | EG2: 44472 | EH2: 44473 | EI2: 44474 | EJ2: 44475 | EK2: 44476 | EL2: 44477 | EM2: 44478 | EN2: 44479 | EO2: 44480 | EP2: 44481 | EQ2: 44482 | ER2: 44483 | ES2: 44484 | ET2: 44485 | EU2: 44486 | EV2: 44487 | EW2: 44488 | EX2: 44489 | EY2: 44490 | EZ2: 44491 | FA2: 44492 | FB2: 44493 | FC2: 44494 | FD2: 44495 | FE2: 44496 | FF2: 44497 | FG2: 44498 | FH2: 44499 | FI2: 44500 | FJ2: 44470 | FK2: 44501 | FL2: 44502 | FM2: 44503 | FN2: 44504 | FO2: 44505 | FP2: 44506 | FQ2: 44507 | FR2: 44508 | FS2: 44509 | FT2: 44510 | FU2: 44511 | FV2: 44512 | FW2: 44513 | FX2: 44514 | FY2: 44515 | FZ2: 44516 | GA2: 44517 | GB2: 44518 | GC2: 44519 | GD2: 44520 | GE2: 44521 | GF2: 44522 | GG2: 44523 | GH2: 44524 | GI2: 44525 | GJ2: 44526 | GK2: 44527 | GL2: 44528 | GM2: 44529 | GN2: 44530 | GO2: 44501 | GP2: 44531 | GQ2: 44532 | GR2: 44533 | GS2: 44534 | GT2: 44535 | GU2: 44536 | GV2: 44537 | GW2: 44538 | GX2: 44539 | GY2: 44540 | GZ2: 44541 | HA2: 44542 | HB2: 44543 | HC2: 44544 | HD2: 44545 | HE2: 44546 | HF2: 44547 | HG2: 44548 | HH2: 44549 | HI2: 44550 | HJ2: 44551 | HK2: 44552 | HL2: 44553 | HM2: 44554 | HN2: 44555 | HO2: 44556 | HP2: 44557 | HQ2: 44558 | HR2: 44559 | HS2: 44560 | HT2: 44561 | HU2: 44531 | HV2: Pendientes por gozar 2021
B3: AREA DE GERENCIA
A4: 1 | B4: GRANDE ALCANTRA, RAUL NEVADA | C4: GERENTE GENERAL | AM4: =SUM(I4:AL4) -> 0 | BS4: =SUM(AN4:BR4) -> 0 | HV4: ='vacaciones 2021'!U4 -> 0
A5: 2 | B5: ASPILCUETA GUTIERREZ KAREN | C5: ASISTENTE GERENCIAL | AM5: =SUM(I5:AL5) -> 0 | BS5: =SUM(AN5:BR5) -> 0 | HV5: ='vacaciones 2021'!U5 -> 60
A6: 3 | B6: GRANDE PECEROS DAVID | C6: ADMINISTRADOR | AM6: =SUM(I6:AL6) -> 0 | BS6: =SUM(AN6:BR6) -> 0 | HV6: ='vacaciones 2021'!U6 -> 33
B7: AREA DE OPERACIONES
A8: 4 | B8: GOYAS ABRAMONTE, JAVIER ENRRIQUE | C8: ING. CIVIL | Y8: 1 | AM8: =SUM(I8:AL8) -> 1 | HV8: ='vacaciones 2021'!U14 -> 57
A9: 5 | B9: RAMIREZ ROMAN MARCELO | C9: ING. CIVIL | V9: 1 | AM9: =SUM(I9:AL9) -> 1 | HV9: ='vacaciones 2021'!U15 -> 179
B10: AREA DE PRESUPUESTO
A11: 6 | B11: OROSCO BALAREZO SILVIA | C11: ING. CIVIL | AM11: =SUM(I11:AL11) -> 0 | HV11: ='vacaciones 2021'!U8 -> 21
A12: 7 | B12: YON UTRILLA LUIS | C12: ARQUITECTO | AM12: =SUM(I12:AL12) -> 0 | HV12: ='vacaciones 2021'!U9 -> 34
A13: 8 | B13: MATINELLA TORREALBA, YUBRAHIM RAMON | C13: ING. CIVIL | AM13: =SUM(I13:AL13) -> 0 | HV13: ='vacaciones 2021'!U12 -> 0
A14: 9 | B14: VENEGAS MARCHAND, FRANCISCO MARTIN | C14: ING. CIVIL | AM14: =SUM(I14:AL14) -> 0 | EO14: 1 | EP14: 1 | EQ14: 1 | ER14: 1 | ES14: 1 | ET14: 1 | EU14: 1 | HV14: ='vacaciones 2021'!U10 -> -8
B15: AREA TECNICA
A16: 10 | B16: ALTAMIRANO SULCA MANUEL | C16: ING. ELECTRICISTA | AC16: 1 | AM16: =SUM(I16:AL16) -> 1 | HV16: ='vacaciones 2021'!U16 -> 63
A17: 11 | B17: ARROYO FALLA, VANESSA ALICIA | C17: ARQUITECTA | O17: 1 | AC17: 1 | AD17: 1 | AE17: 1 | AF17: 1 | AG17: 1 | AH17: 1 | AI17: 1 | AJ17: 1 | AM17: =SUM(I17:AL17) -> 9 | HV17: ='vacaciones 2021'!U18 -> 35
A18: 12 | B18: BAUTISTA MOLINA LUIS FERNANDO | C18: ING. CIVIL | AM18: =SUM(I18:AL18) -> 0 | HV18: ='vacaciones 2021'!U20 -> 29
A19: 13 | B19: BRIONES RIVERA, RICHARD | C19: ARQUITECTO | AM19: =SUM(I19:AL19) -> 0 | HV19: ='vacaciones 2021'!U22 -> 28
A20: 14 | B20: COLETO PASTOR LUIS ENRIQUE | C20: ING. CIVIL | AM20: =SUM(I20:AL20) -> 0 | HV20: ='vacaciones 2021'!U23 -> 16
A21: 15 | B21: CORDOVA VELEZ, JULISSA | C21: ARQUITECTA | AM21: =SUM(I21:AL21) -> 0 | HV21: ='vacaciones 2021'!U24 -> 0
A22: 16 | B22: DAMBROSIO RIVERO LIZETH STEFANNY | C22: ARQUITECTA | AM22: =SUM(I22:AL22) -> 0 | HV22: ='vacaciones 2021'!U26 -> -9
A23: 17 | B23: ESPEJO PACHECO, URSULA AMELIA | C23: ASISTENTE ADMINISTRATIVO | AM23: =SUM(I23:AL23) -> 0 | HV23: ='vacaciones 2021'!U46 -> -2
A24: 18 | B24: FLORES GUARDIA CLAUDIA | AM24: =SUM(I24:AL24) -> 0 | HV24: ='vacaciones 2021'!#REF! -> #REF!
A25: 19 | B25: FLORES MANTILLA MARIANA | C25: ARQUITECTA | AM25: =SUM(I25:AL25) -> 0 | HV25: ='vacaciones 2021'!U27 -> 0
A26: 20 | B26: GRANDE ALCANTARA MILAGROS M. | C26: ARQUITECTA | AM26: =SUM(I26:AL26) -> 0 | HV26: ='vacaciones 2021'!U29 -> 0
A27: 21 | B27: MENDOZA GARCÍA, ZINCIA | C27: ARQUITECTA | AM27: =SUM(I27:AL27) -> 0 | HV27: ='vacaciones 2021'!U32 -> 0
A28: 22 | B28: MURGA SALCEDO, ANTHONY EDGAR | C28: ING. CIVIL | AM28: =SUM(I28:AL28) -> 0 | HV28: ='vacaciones 2021'!#REF! -> #REF!
A29: 23 | B29: OCHOA GUTIERREZ ERICKSON | C29: ING. CIVIL | AL29: 1 | AM29: =SUM(I29:AL29) -> 1 | AN29: 1 | AO29: 1 | AP29: 1 | AQ29: 1 | AR29: 1 | AS29: 1 | HV29: ='vacaciones 2021'!U34 -> 0
A30: 24 | B30: OSCCO GUILLEN EDWIN RAFAEL | C30: ING. CIVIL | AM30: =SUM(I30:AL30) -> 0 | HV30: ='vacaciones 2021'!U35 -> 0
A31: 25 | B31: REYNA COSTA CLARA | C31: ARQUITECTA | M31: 1 | N31: 1 | O31: 1 | P31: 1 | AM31: =M31+N31+O31+P31 -> 4 | HV31: ='vacaciones 2021'!#REF! -> #REF!
B32: AREA CONTABLE
A33: 27 | B33: BACA WIESSE JOSE ALBERTO | C33: CONTADOR GENERAL | H33: 1 | I33: 1 | J33: 1 | K33: 1 | L33: 1 | M33: 1 | N33: 1 | AM33: =SUM(I33:AL33) -> 6 | HV33: ='vacaciones 2021'!U39 -> 42
A34: 28 | B34: ALARCON PEREZ LUIS | C34: ASISTENTE CONTABLE | AC34: 1 | AD34: 1 | AE34: 1 | AF34: 1 | AG34: 1 | AH34: 1 | AI34: 1 | AJ34: 1 | AK34: 1 | AL34: 1 | AM34: =SUM(I34:AL34) -> 10 | AN34: 1 | AO34: 1 | AP34: 1 | AQ34: 1 | CJ34: 1 | CL34: 1 | HV34: ='vacaciones 2021'!U40 -> 44
A35: 29 | B35: GUZMAN MANTARI INGRID | C35: ASISTENTE CONTABLE | AM35: =SUM(I35:AL35) -> 0 | CQ35: 1 | HV35: ='vacaciones 2021'!U41 -> 34
A36: 32 | B36: ALEJOS TORIBIO, SULELMA MELISA | C36: AUXILIAR CONTABLE | V36: 1 | W36: 1 | X36: 1 | Y36: 1 | Z36: 1 | AA36: 1 | AB36: 1 | AC36: 1 | AD36: 1 | AE36: 1 | AF36: 1 | AG36: 1 | AH36: 1 | AI36: 1 | AJ36: 1 | AM36: =SUM(I36:AL36) -> 15 | CR36: 1 | HV36: ='vacaciones 2021'!U42 -> -4
B37: AREA DE FINANZAS | AM37: =SUM(I37:AL37) -> 0
A38: 30 | B38: GRANDE ALCANTARA GERMAN N. | C38: GERENTE DE FINANZAS | AM38: =SUM(I38:AL38) -> 0 | HV38: ='vacaciones 2021'!U44 -> 149
A39: 31 | B39: JUAN PEDRO CRUZ, GIOVANNA PAULA | C39: ASISTENTE ADMINISTRATIVO | O39: 1 | AD39: 1 | AM39: =SUM(I39:AL39) -> 2 | CD39: 1 | CI39: 1 | CP39: 1 | DE39: 1 | HV39: ='vacaciones 2021'!U47 -> 0
B40: AREA DE LOGISTICA
A41: 33 | B41: BAUTISTA AYESTA HEBER | C41: ADMIN. DE OBRA | AM41: =SUM(I41:AL41) -> 0 | HV41: ='vacaciones 2021'!U49 -> 202
A42: 34 | B42: BAUTISTA AYESTA WALTER | C42: ADMIN. DE OBRA | AM42: =SUM(I42:AL42) -> 0 | CI42: 1 | CJ42: 1 | CK42: 1 | CL42: 1 | CM42: 1 | CN42: 1 | CO42: 1 | CP42: 1 | CQ42: 1 | CR42: 1 | CS42: 1 | CT42: 1 | CU42: 1 | CV42: 1 | CW42: 1 | HV42: ='vacaciones 2021'!U50 -> 143
A43: 35 | B43: ALHUAY AYESTA, RAMIRO | C43: LOGISTICA | AM43: =SUM(I43:AL43) -> 0 | HV43: ='vacaciones 2021'!U51 -> 30
A44: 36 | B44: GRANDE ALCANTARA PAUL | C44: LOGISTICA | AM44: =SUM(I44:AL44) -> 0 | HV44: ='vacaciones 2021'!U52 -> 7
B45: AREA DE REGURSOS HUMANOS
A46: 37 | B46: TOMAYLLA TERRONES KATHERINE | C46: RECURSOS HUMANOS | L46: 1 | Y46: 1 | Z46: 1 | AA46: 1 | AB46: 1 | AC46: 1 | AD46: 1 | AE46: 1 | AF46: 1 | AG46: 1 | AH46: 1 | AI46: 1 | AJ46: 1 | AK46: 1 | AL46: 1 | AM46: =SUM(I46:AL46) -> 15 | BD46: 1 | BE46: 1 | BF46: 1 | BG46: 1 | BH46: 1 | BI46: 1 | BJ46: 1 | BK46: 1 | BL46: 1 | BM46: 1 | BN46: 1 | BO46: 1 | BP46: 1 | BQ46: 1 | HV46: ='vacaciones 2021'!U55 -> 76
B47: AREA DE SEGURIDAD
A48: 38 | B48: OSCCO GUILLEN ZORAIDA | C48: JEFA DE SEGURIDAD | AC48: 1 | AD48: 1 | AE48: 1 | AF48: 1 | AG48: 1 | AH48: 1 | AI48: 1 | AJ48: 1 | AK48: 1 | AL48: 1 | AM48: =SUM(I48:AL48) -> 10 | AN48: 1 | AO48: 1 | AP48: 1 | AQ48: 1 | AR48: 1 | AS48: 1 | AT48: 1 | AU48: 1 | AV48: 1 | AW48: 1 | AX48: 1 | AY48: 1 | AZ48: 1 | BA48: 1 | BB48: 1 | BC48: 1 | BD48: 1 | BE48: 1 | BF48: 1 | BG48: 1 | BH48: 1 | BI48: 1 | BJ48: 1 | BK48: 1 | BL48: 1 | BM48: 1 | BN48: 1 | BO48: 1 | BP48: 1 | BQ48: 1 | BR48: 1 | BT48: 1 | BU48: 1 | BV48: 1 | BW48: 1 | BX48: 1 | BY48: 1 | BZ48: 1 | CA48: 1 | CB48: 1 | CC48: 1 | CD48: 1 | CE48: 1 | CF48: 1 | CG48: 1 | CH48: 1 | CI48: 1 | CJ48: 1 | CK48: 1 | CL48: 1 | CM48: 1 | CN48: 1 | CO48: 1 | CP48: 1 | CQ48: 1 | CR48: 1 | CS48: 1 | CT48: 1 | CU48: 1 | CV48: 1 | CW48: 1 | CX48: 1 | HV48: ='vacaciones 2021'!U57 -> 60
A49: 39 | B49: OSCCO GUILLEN MARIBEL | C49: PREVENCION | AM49: =SUM(I49:AL49) -> 0 | HV49: ='vacaciones 2021'!U58 -> 42
A50: 40 | B50: ZURITA PEÑA JOANY | C50: PREVENCION | AM50: =SUM(I50:AL50) -> 0 | HV50: ='vacaciones 2021'!U59 -> -1
B51: AREA COMERCIAL
A52: 41 | B52: PEÑA HERNANDEZ, FERNANDO FAVIAN | C52: GERENTE DE VENTAS | H52: 1 | I52: 1 | J52: 1 | K52: 1 | L52: 1 | M52: 1 | N52: 1 | O52: 1 | P52: 1 | Q52: 1 | R52: 1 | S52: 1 | T52: 1 | U52: 1 | V52: 1 | AM52: =SUM(I52:AL52) -> 14 | HV52: ='vacaciones 2021'!U61 -> 36
B53: YNCIO JIMENEZ SILVIA | HV53: =#REF!-D53-E53-F53-G53-H53-AM53-BS53-CY53-ED53-FJ53-GO53-HU53 -> #REF!

Sheet vacaciones 2020
A1: EMPLEADOS | B1: REPORTE DE VACACIONES | D1: ENERO - DICIEMBRE 2020
B2: EMPLEADOS | C2: SALDOS DE DIAS POR GOZAR 2019 | D2: ENE | E2: FEB | F2: MAR | G2: ABR | H2: MAY | I2: JUN | J2: JUL | K2: AGO | L2: SET | M2: OCT | N2: NOV | O2: DIC | P2: Total días gozados | Q2: PENDIENTES POR GOZAR 2019 | R2: FECHAS DE VENCIMIENTO 2020 | S2: VACACIONES POR VENCER 2020 | T2: Pendientes por gozar 2020
A3: 1 | B3: ALARCON PEREZ LUIS | C3: ='Control de dias gozados 2019'!CS6 -> 69 | E3: 1 | L3: 9 | O3: 11 | P3: =SUM(D3:O3) -> 21 | Q3: =+C3-P3 -> 48 | R3: =vacaciones!I4 -> 44232 | S3: =vacaciones!J4 -> 0 | T3: =+Q3+S3 -> 48
A4: =+A3+1 -> 2 | B4: ALEJOS TORIBIO, SULELMA MELISA | C4: ='Control de dias gozados 2019'!CS7 -> 50 | L4: 13 | M4: 1 | O4: 11 | P4: =SUM(D4:O4) -> 25 | Q4: =+C4-P4 -> 25 | R4: =vacaciones!I5 -> 44151 | S4: 30 | T4: =+Q4+S4 -> 55
A5: =+A4+1 -> 3 | B5: ALHUAY AYESTA, RAMIRO | C5: ='Control de dias gozados 2019'!CS8 -> 26 | E5: 4 | M5: 31 | N5: 21 | P5: =SUM(D5:O5) -> 56 | Q5: =+C5-P5 -> -30 | R5: =vacaciones!I6 -> 44135 | S5: =vacaciones!J6 -> 30 | T5: =+Q5+S5 -> 0
A6: 4 | B6: ALTAMIRANO SULCA MANUEL | C6: ='Control de dias gozados 2019'!CS9 -> 16 | O6: 2 | P6: =SUM(D6:O6) -> 2 | Q6: =+C6-P6 -> 14 | R6: =vacaciones!I7 -> 44095 | S6: =vacaciones!J7 -> 30 | T6: =+Q6+S6 -> 44
A7: =+A6+1 -> 5 | B7: ARROYO FALLA, VANESSA ALICIA | C7: ='Control de dias gozados 2019'!CS10 -> -17 | E7: 10 | F7: 11 | O7: 2 | P7: =SUM(D7:O7) -> 23 | Q7: =+C7-P7 -> -40 | R7: =vacaciones!I8 -> 44010 | S7: =vacaciones!J8 -> 30 | T7: =+Q7+S7 -> -10
A8: =+A7+1 -> 6 | B8: ASPILCUETA GUTIERREZ KAREN | C8: ='Control de dias gozados 2019'!CS11 -> 72 | E8: 7 | F8: 8 | L8: 15 | O8: 2 | P8: =SUM(D8:O8) -> 32 | Q8: =+C8-P8 -> 40 | R8: =vacaciones!I9 -> 43885 | S8: =vacaciones!J9 -> 30 | T8: =+Q8+S8 -> 70
A9: 7 | B9: BACA WIESSE JOSE ALBERTO | C9: ='Control de dias gozados 2019'!CS12 -> 122 | E9: 12 | L9: 15 | M9: 15 | N9: 15 | O9: 15 | P9: =SUM(D9:O9) -> 72 | Q9: =+C9-P9 -> 50 | R9: =vacaciones!I10 -> 44206 | S9: =vacaciones!J10 -> 0 | T9: =+Q9+S9 -> 50
A10: =+A9+1 -> 8 | B10: BALLENA CASTILLO ITALA ADRIANA | C10: ='Control de dias gozados 2019'!CS13 -> 31 | N10: 30 | O10: 31 | P10: =SUM(D10:O10) -> 61 | Q10: =+C10-P10 -> -30 | R10: =vacaciones!I11 -> 43843 | S10: =vacaciones!J11 -> 30 | T10: =+Q10+S10 -> 0
A11: =+A10+1 -> 9 | B11: BAUTISTA AYESTA HEBER | C11: ='Control de dias gozados 2019'!CS14 -> 175 | O11: 2 | P11: =SUM(D11:O11) -> 2 | Q11: =+C11-P11 -> 173 | R11: =vacaciones!I12 -> 44027 | S11: =vacaciones!J12 -> 30 | T11: =+Q11+S11 -> 203
A12: 10 | B12: BAUTISTA AYESTA WALTER | C12: ='Control de dias gozados 2019'!CS15 -> 234 | O12: 2 | P12: =SUM(D12:O12) -> 2 | Q12: =+C12-P12 -> 232 | R12: =vacaciones!I13 -> 43904 | S12: =vacaciones!J13 -> 30 | T12: =+Q12+S12 -> 262
A13: =+A12+1 -> 11 | B13: BAUTISTA MOLINA LUIS FERNANDO | C13: ='Control de dias gozados 2019'!CS16 -> 0 | O13: 2 | P13: =SUM(D13:O13) -> 2 | Q13: =+C13-P13 -> -2 | R13: =vacaciones!L14 -> 44497 | S13: =vacaciones!J14 -> 0 | T13: =+Q13+S13 -> -2
A14: =+A13+1 -> 12 | B14: BRIONES RIVERA, RICHARD | C14: ='Control de dias gozados 2019'!CS17 -> 0 | O14: 2 | P14: =SUM(D14:O14) -> 2 | Q14: =+C14-P14 -> -2 | R14: =vacaciones!L15 -> 44359 | S14: =vacaciones!J15 -> 0 | T14: =+Q14+S14 -> -2
A15: 13 | B15: COLETO PASTOR LUIS ENRIQUE | C15: ='Control de dias gozados 2019'!CS18 -> 40 | M15: 10 | N15: 30 | P15: =SUM(D15:O15) -> 40 | Q15: =+C15-P15 -> 0 | R15: =vacaciones!I16 -> 44149 | T15: =+Q15+S15 -> 0
A16: =+A15+1 -> 14 | B16: CORDOVA VELEZ, JULISSA | C16: ='Control de dias gozados 2019'!CS19 -> 0 | O16: 2 | P16: =SUM(D16:O16) -> 2 | Q16: =+C16-P16 -> -2 | R16: =vacaciones!L17 -> 44359 | S16: =vacaciones!J17 -> 0 | T16: =+Q16+S16 -> -2
A17: =+A16+1 -> 15 | B17: DAMBROSIO RIVERO LIZETH STEFANNY | C17: ='Control de dias gozados 2019'!CS20 -> 23 | K17: 31 | L17: 2 | O17: 2 | P17: =SUM(D17:O17) -> 35 | Q17: =+C17-P17 -> -12 | R17: =vacaciones!I18 -> 44370 | S17: =vacaciones!J18 -> 0 | T17: =+Q17+S17 -> -12
A18: 16 | B18: ESPEJO PACHECO, URSULA AMELIA | C18: ='Control de dias gozados 2019'!CS21 -> 0 | Q18: =+C18-P18 -> 0 | T18: =+Q18+S18 -> 0
A19: =+A18+1 -> 17 | B19: FLORES GUARDIA CLAUDIA | C19: ='Control de dias gozados 2019'!CS22 -> 0 | L19: 18 | O19: 2 | P19: =SUM(D19:O19) -> 20 | Q19: =+C19-P19 -> -20 | R19: =vacaciones!I19 -> 44237 | S19: =vacaciones!J19 -> 0 | T19: =+Q19+S19 -> -20
A20: =+A19+1 -> 18 | B20: FLORES MANTILLA MARIANA | C20: ='Control de dias gozados 2019'!CS23 -> 41 | E20: 6 | M20: 2 | O20: 2 | P20: =SUM(D20:O20) -> 10 | Q20: =+C20-P20 -> 31 | R20: =vacaciones!I20 -> 44058 | S20: =vacaciones!J20 -> 30 | T20: =+Q20+S20 -> 61
A21: 19 | B21: GOYAS ABRAMONTE, JAVIER ENRRIQUE | C21: ='Control de dias gozados 2019'!CS24 -> 0 | O21: 2 | P21: =SUM(D21:O21) -> 2 | Q21: =+C21-P21 -> -2 | R21: =vacaciones!I21 -> 43960 | S21: =vacaciones!J21 -> 30 | T21: =+Q21+S21 -> 28
A22: =+A21+1 -> 20 | B22: GRANDE ALCANTARA GERMAN N. | C22: ='Control de dias gozados 2019'!CS25 -> 183 | G22: 30 | L22: 3 | M22: 3 | O22: 2 | P22: =SUM(D22:O22) -> 38 | Q22: =+C22-P22 -> 145 | R22: =vacaciones!I22 -> 43874 | S22: =vacaciones!J22 -> 30 | T22: =+Q22+S22 -> 175
A23: =+A22+1 -> 21 | B23: GRANDE ALCANTARA MILAGROS M. | C23: ='Control de dias gozados 2019'!CS26 -> 163 | D23: 31 | M23: 20 | N23: 30 | O23: 31 | P23: =SUM(D23:O23) -> 112 | Q23: =+C23-P23 -> 51 | R23: =vacaciones!I23 -> 44021 | S23: =vacaciones!J23 -> 30 | T23: =+Q23+S23 -> 81
A24: 22 | B24: GRANDE ALCANTARA PAUL | C24: ='Control de dias gozados 2019'!CS27 -> 152 | L24: 30 | M24: 31 | N24: 30 | O24: 31 | P24: =SUM(D24:O24) -> 122 | Q24: =+C24-P24 -> 30 | R24: =vacaciones!I24 -> 44196 | S24: 30 | T24: =+Q24+S24 -> 60
A25: =+A24+1 -> 23 | B25: GRANDE ALCANTRA, RAUL NEVADA | C25: ='Control de dias gozados 2019'!CS28 -> 0 | P25: =SUM(D25:O25) -> 0 | Q25: =+C25-P25 -> 0 | T25: =+Q25+S25 -> 0
A26: =+A25+1 -> 24 | B26: GRANDE PECEROS DAVID | C26: ='Control de dias gozados 2019'!CS29 -> 10 | E26: 15 | L26: 12 | N26: 1 | O26: 2 | P26: =SUM(D26:O26) -> 30 | Q26: =+C26-P26 -> -20 | R26: =vacaciones!I25 -> 44141 | S26: =vacaciones!J25 -> 30 | T26: =+Q26+S26 -> 10
A27: 25 | B27: GUZMAN MANTARI INGRID | C27: ='Control de dias gozados 2019'!CS30 -> 0 | N27: 4 | O27: 11 | P27: =SUM(D27:O27) -> 15 | Q27: =+C27-P27 -> -15 | R27: =vacaciones!L26 -> 44497 | S27: =vacaciones!J26 -> 0 | T27: =+Q27+S27 -> -15
A28: =+A27+1 -> 26 | B28: JUAN PEDRO CRUZ, GIOVANNA PAULA | C28: ='Control de dias gozados 2019'!CS31 -> -10 | E28: 7 | L28: 15 | M28: 3 | N28: 1 | O28: 3 | P28: =SUM(D28:O28) -> 29 | Q28: =+C28-P28 -> -39 | R28: =vacaciones!I27 -> 43849 | S28: =vacaciones!J27 -> 30 | T28: =+Q28+S28 -> -9
A29: =+A28+1 -> 27 | B29: MENDOZA GARCÍA, ZINCIA | C29: ='Control de dias gozados 2019'!CS32 -> 25 | K29: 31 | L29: 2 | O29: 2 | P29: =SUM(D29:O29) -> 35 | Q29: =+C29-P29 -> -10 | R29: =vacaciones!I28 -> 44186 | S29: 30 | T29: =+Q29+S29 -> 20
A30: 28 | B30: MURGA SALCEDO, ANTHONY EDGAR | C30: ='Control de dias gozados 2019'!CS33 -> 0 | O30: 2 | P30: =SUM(D30:O30) -> 2 | Q30: =+C30-P30 -> -2 | R30: =vacaciones!L29 -> 44479 | S30: =vacaciones!J29 -> 0 | T30: =+Q30+S30 -> -2
A31: =+A30+1 -> 29 | B31: OCHOA GUTIERREZ ERICKSON | C31: ='Control de dias gozados 2019'!CS34 -> 0 | P31: =SUM(D31:O31) -> 0 | Q31: =+C31-P31 -> 0 | R31: =vacaciones!I30 -> 44082 | S31: =vacaciones!J30 -> 30 | T31: =+Q31+S31 -> 30
A32: =+A31+1 -> 30 | B32: OROSCO BALAREZO SILVIA | C32: ='Control de dias gozados 2019'!CS35 -> 0 | O32: 2 | P32: =SUM(D32:O32) -> 2 | Q32: =+C32-P32 -> -2 | R32: =vacaciones!L31 -> 44404 | S32: =vacaciones!J31 -> 0 | T32: =+Q32+S32 -> -2
A33: 31 | B33: OSCCO GUILLEN EDWIN RAFAEL | C33: ='Control de dias gozados 2019'!CS36 -> 30 | D33: 7 | L33: 5 | M33: 21 | O33: 2 | P33: =SUM(D33:O33) -> 35 | Q33: =+C33-P33 -> -5 | R33: =vacaciones!I32 -> 44164.5 | S33: 30 | T33: =+Q33+S33 -> 25
A34: =+A33+1 -> 32 | B34: OSCCO GUILLEN ZORAIDA | C34: ='Control de dias gozados 2019'!CS37 -> 85 | L34: 14 | M34: 9 | N34: 4 | O34: 2 | P34: =SUM(D34:O34) -> 29 | Q34: =+C34-P34 -> 56 | R34: =vacaciones!I33 -> 44165 | S34: 30 | T34: =+Q34+S34 -> 86 | U34: 12 | V34: 30
A35: =+A34+1 -> 33 | B35: PEÑA HERNANDEZ, FERNANDO FAVIAN | C35: ='Control de dias gozados 2019'!CS38 -> 44 | O35: 2 | P35: =SUM(D35:O35) -> 2 | Q35: =+C35-P35 -> 42 | R35: =vacaciones!I34 -> 44028 | S35: =vacaciones!J34 -> 30 | T35: =+Q35+S35 -> 72 | U35: 9.5 | V35: =U35*V34/U34 -> 23.75
A36: 34 | B36: RAMIREZ ROMAN MARCELO | C36: ='Control de dias gozados 2019'!CS39 -> 127 | E36: 5 | O36: 2 | P36: =SUM(D36:O36) -> 7 | Q36: =+C36-P36 -> 120 | R36: =vacaciones!I35 -> 44024 | S36: =vacaciones!J35 -> 30 | T36: =+Q36+S36 -> 150 | V36: 18
A37: =+A36+1 -> 35 | B37: REYNA COSTA CLARA | C37: ='Control de dias gozados 2019'!CS40 -> 34 | K37: 8 | L37: 30 | M37: 14 | P37: =SUM(D37:O37) -> 52 | Q37: =+C37-P37 -> -18 | R37: =vacaciones!I36 -> 44279 | S37: =vacaciones!J36 -> 0 | V37: =V35-V36 -> 5.75
A38: =+A37+1 -> 36 | B38: SALIRROSAS PONCE LILIANA | C38: ='Control de dias gozados 2019'!CS41 -> 0 | O38: 10 | P38: =SUM(D38:O38) -> 10 | Q38: =+C38-P38 -> -10 | R38: =vacaciones!L37 -> 44435 | S38: =vacaciones!J37 -> 0
A39: 37 | B39: TERRONES BECERRA MARISSA | C39: ='Control de dias gozados 2019'!CS42 -> 106 | D39: 3 | E39: 6 | O39: 24 | P39: =SUM(D39:O39) -> 33 | Q39: =+C39-P39 -> 73 | R39: =vacaciones!I38 -> 44006 | S39: =vacaciones!J38 -> 30 | T39: =+Q39+S39 -> 103 | U39: 44300 | V39: FIN DE VACACIONES
A40: =+A39+1 -> 38 | B40: TOMAYLLA TERRONES KATHERINE | C40: ='Control de dias gozados 2019'!CS43 -> 120 | E40: 1 | L40: 12 | N40: 1 | O40: 15 | P40: =SUM(D40:O40) -> 29 | Q40: =+C40-P40 -> 91 | R40: =vacaciones!I39 -> 43893 | S40: =vacaciones!J39 -> 30 | T40: =+Q40+S40 -> 121
A41: =+A40+1 -> 39 | B41: VENEGAS MARCHAND, FRANCISCO MARTIN | C41: ='Control de dias gozados 2019'!CS44 -> 30 | O41: 30 | P41: =SUM(D41:O41) -> 30 | Q41: =+C41-P41 -> 0 | R41: =vacaciones!I40 -> 44248 | S41: =vacaciones!J40 -> 0 | T41: =+Q41+S41 -> 0
A42: 40 | B42: YNCIO JIMENEZ SILVIA | C42: ='Control de dias gozados 2019'!CS45 -> -3 | L42: 15 | O42: 10 | P42: =SUM(D42:O42) -> 25 | Q42: =+C42-P42 -> -28 | R42: =vacaciones!I41 -> 44228 | S42: =vacaciones!J41 -> 0 | T42: =+Q42+S42 -> -28
A43: =+A42+1 -> 41 | B43: YON UTRILLA LUIS | C43: ='Control de dias gozados 2019'!CS46 -> 15 | F43: 7 | K43: 30 | L43: 2 | O43: 2 | P43: =SUM(D43:O43) -> 41 | Q43: =+C43-P43 -> -26 | R43: =vacaciones!I42 -> 44137 | S43: =vacaciones!J42 -> 30 | T43: =+Q43+S43 -> 4
A44: =+A43+1 -> 42 | B44: ZURITA PEÑA JOANY | C44: ='Control de dias gozados 2019'!CS47 -> 53 | O44: 2 | P44: =SUM(D44:O44) -> 2 | Q44: =+C44-P44 -> 51 | R44: =vacaciones!I43 -> 44075 | S44: =vacaciones!J43 -> 30 | T44: =+Q44+S44 -> 81
Q46: 44075
Q47: 44172
Q48: 44196
Q49: =Q48-Q47 -> 24
Q50: 44197
Q51: 44241
Q52: =Q51-Q50 -> 44
Q53: =T39-Q52 -> 59
Q55: 30 | R55: 360 | S55: 30 | T55: 1
Q56: 59 | R56: =Q56*R55/Q55 -> 708 | S56: =S55*T56/T55 -> 18 | T56: 0.6
R57: =R56/30 -> 23.6
Q59: equivale: | R59: 1 año
R60: 11 meses
R61: 18 dias

Sheet vacaciones
B1: 44137
B2: REPORTE DE VACACIONES | D2: 2019 | F2: 2020 | L2: 2021
B3: EMPLEADOS | C3: Fecha de ingreso a planilla | F3: NO AFECTO A COVID | G3: Dias no trabajados X COVID | H3: LICENCIA SIN GOCE DE HABER | I3: NUEVA FECHA DE VACACIONES AFECTO A COVID | J3: DIAS EFECTIVOS | K3: TOTAL ACUMULADO AL 2020 | N3: Total días gozados | O3: Pendientes por gozar
A4: 1 | B4: ALARCON PEREZ LUIS | C4: 01/01/2017 | D4: =+C4+3*360 -> 43816 | E4: 90 | F4: =+D4+360 -> 44176 | G4: ='Determ días de vacaciones'!S10 -> 56 | I4: =F4+G4 -> 44232 | J4: 0 | K4: =+E4+J4 -> 90 | L4: 44232 | N4: =+'Control de dias gozados 2019'!CR6+'vacaciones 2020'!P3 -> 42 | O4: =K4-N4 -> 48
A5: 2 | B5: ALEJOS TORIBIO, SULELMA MELISA | C5: 01/09/2017 | D5: =+C5+2*360 -> 43699 | E5: 60 | F5: =D5+360 -> 44059 | G5: ='Determ días de vacaciones'!S11 -> 92 | I5: =F5+G5 -> 44151 | J5: 0 | K5: =+E5+J5 -> 60 | L5: =+I5+360 -> 44511 | N5: =+'Control de dias gozados 2019'!CR7+'vacaciones 2020'!P4 -> 35 | O5: =K5-N5 -> 25
A6: 3 | B6: ALHUAY AYESTA, RAMIRO | C6: 01/09/2014 | D6: =+C6+5*360 -> 43683 | E6: 150 | F6: =D6+360 -> 44043 | G6: ='Determ días de vacaciones'!S12 -> 92 | I6: =F6+G6 -> 44135 | J6: 30 | K6: =+E6+J6 -> 180 | L6: =+I6+360 -> 44495 | N6: =+'Control de dias gozados 2019'!CR8+'vacaciones 2020'!P5 -> 180 | O6: =K6-N6 -> 0
A7: 4 | B7: ALTAMIRANO SULCA MANUEL | C7: 01/08/2018 | D7: =+C7+360 -> 43673 | E7: 30 | F7: =D7+360 -> 44033 | G7: ='Determ días de vacaciones'!S13 -> 62 | I7: =F7+G7 -> 44095 | J7: 30 | K7: =+E7+J7 -> 60 | L7: =+I7+360 -> 44455 | N7: =+'Control de dias gozados 2019'!CR9+'vacaciones 2020'!P6 -> 16 | O7: =K7-N7 -> 44
A8: 5 | B8: ARROYO FALLA, VANESSA ALICIA | C8: 01/04/2019 | F8: =+C8+360 -> 43916 | G8: 64 | H8: 30 | I8: =F8+G8+H8 -> 44010 | J8: 30 | K8: =+E8+J8 -> 30 | L8: =+I8+360 -> 44370 | N8: =+'Control de dias gozados 2019'!CR10+'vacaciones 2020'!P7 -> 40 | O8: =K8-N8 -> -10
A9: 6 | B9: ASPILCUETA GUTIERREZ KAREN | C9: 01/04/2013 | D9: =+C9+6*360 -> 43525 | E9: 180 | F9: =D9+360 -> 43885 | G9: ='Determ días de vacaciones'!S15 -> 41 | I9: 43885 | J9: 30 | K9: =+E9+J9 -> 210 | L9: =+F9+G9+360 -> 44286 | N9: =+'Control de dias gozados 2019'!CR11+'vacaciones 2020'!P8 -> 140 | O9: =K9-N9 -> 70
A10: 7 | B10: BACA WIESSE JOSE ALBERTO | C10: 01/01/2011 | D10: =+C10+9*360 -> 43784 | E10: 270 | F10: =D10+360 -> 44144 | G10: ='Determ días de vacaciones'!S16 -> 62 | I10: =F10+G10 -> 44206 | J10: 0 | K10: =+E10+J10 -> 270 | L10: 44206 | N10: =+'Control de dias gozados 2019'!CR12+'vacaciones 2020'!P9 -> 220 | O10: =K10-N10 -> 50
A11: 8 | B11: BALLENA CASTILLO ITALA ADRIANA | C11: 01/03/2011 | D11: =+C11+8*360 -> 43483 | E11: 240 | F11: =D11+360 -> 43843 | G11: ='Determ días de vacaciones'!S17 -> 44 | I11: 43843 | J11: 30 | K11: =+E11+J11 -> 270 | L11: =+F11+G11+360 -> 44247 | N11: =+'Control de dias gozados 2019'!CR13+'vacaciones 2020'!P10 -> 270 | O11: =K11-N11 -> 0
A12: 9 | B12: BAUTISTA AYESTA HEBER (INGRESO PLANILLA 01/07/2007) | C12: 01/07/2011 | D12: =+C12+8*360 -> 43605 | E12: 240 | F12: =D12+360 -> 43965 | G12: ='Determ días de vacaciones'!S18 -> 62 | I12: =F12+G12 -> 44027 | J12: 30 | K12: =+E12+J12 -> 270 | L12: =+I12+360 -> 44387 | N12: =+'Control de dias gozados 2019'!CR14+'vacaciones 2020'!P11 -> 67 | O12: =K12-N12 -> 203
A13: 10 | B13: BAUTISTA AYESTA WALTER (INGRESO A PLANILLA 01/05/2007) | C13: 01/05/2011 | D13: =+C13+8*360 -> 43544 | E13: 240 | F13: =D13+360 -> 43904 | G13: ='Determ días de vacaciones'!S19 -> 92 | I13: 43904 | J13: 30 | K13: =+E13+J13 -> 270 | L13: =F13+G13+360 -> 44356 | N13: =+'Control de dias gozados 2019'!CR15+'vacaciones 2020'!P12 -> 8 | O13: =K13-N13 -> 262
A14: 11 | B14: BAUTISTA MOLINA LUIS FERNANDO | C14: 02/11/2020 | F14: 44137 | J14: 0 | K14: 0 | L14: =F14+G14+360 -> 44497 | N14: 0 | O14: 0
A15: 12 | B15: BRIONES RIVERA, RICHARD (INGRESO A PLANILLA 01/02/2020) | C15: 01/02/2020 | F15: 01/02/2020 | G15: ='Determ días de vacaciones'!S20 -> 137 | J15: 0 | K15: =+E15+J15 -> 0 | L15: =+F15+G15+360 -> 44359 | N15: 0 | O15: =K15-N15 -> 0
A16: 13 | B16: COLETO PASTOR LUIS ENRIQUE (INGRESO A PLANILLA 01/10/2010) | C16: 01/10/2011 | D16: =+C16+8*360 -> 43697 | E16: 240 | F16: =D16+360 -> 44057 | G16: ='Determ días de vacaciones'!S21 -> 92 | I16: =F16+G16 -> 44149 | J16: 30 | K16: =+E16+J16 -> 270 | L16: =+I16+360 -> 44509 | N16: =+'Control de dias gozados 2019'!CR18+'vacaciones 2020'!P15 -> 240 | O16: =K16-N16 -> 30
A17: 14 | B17: CORDOVA VELEZ, JULISSA (INGRESO A PLANILLA 01/02/2020) | C17: 01/02/2020 | F17: 01/02/2020 | G17: ='Determ días de vacaciones'!S22 -> 137 | J17: 0 | K17: =+E17+J17 -> 0 | L17: =+F17+G17+360 -> 44359 | N17: =+'Control de dias gozados 2019'!CR19+'vacaciones 2020'!P16 -> 2 | O17: =K17-N17 -> -2
A18: 15 | B18: DAMBROSIO RIVERO LIZETH STEFANNY | C18: 01/01/2019 | D18: =+C18+360 -> 43826 | E18: 30 | F18: =+D18+360 -> 44186 | G18: 96 | H18: 88 | I18: =F18+G18+H18 -> 44370 | J18: 0 | K18: 0 | L18: 44370 | N18: =+'Control de dias gozados 2019'!CR20+'vacaciones 2020'!P17 -> 42 | O18: =K18-N18 -> -42
A19: 16 | B19: FLORES GUARDIA CLAUDIA | C19: 01/11/2019 | F19: =+C19+360 -> 44130 | G19: 70 | H19: 37 | I19: =+F19+G19+H19 -> 44237 | J19: 0 | K19: =+E19+J19 -> 0 | L19: =+I19 -> 44237 | N19: ='Control de dias gozados 2019'!CR22+'vacaciones 2020'!P19 -> 20 | O19: =K19-N19 -> -20
A20: 17 | B20: FLORES MANTILLA MARIANA | C20: 01/07/2014 | D20: =+C20+5*360 -> 43621 | E20: 150 | F20: =D20+360 -> 43981 | G20: ='Determ días de vacaciones'!S26 -> 77 | I20: =F20+G20 -> 44058 | J20: 30 | K20: =+E20+J20 -> 180 | L20: =+I20+360 -> 44418 | N20: ='Control de dias gozados 2019'!CR23+'vacaciones 2020'!P20 -> 119 | O20: =K20-N20 -> 61
A21: 18 | B21: GOYAS ABRAMONTE JAVIER | C21: 01/04/2019 | F21: =+C21+360 -> 43916 | G21: ='Determ días de vacaciones'!S27 -> 44 | I21: =F21+G21 -> 43960 | J21: 30 | K21: =+E21+J21 -> 30 | L21: =+I21+360 -> 44320 | N21: ='Control de dias gozados 2019'!CR24+'vacaciones 2020'!P21 -> 2 | O21: =K21-N21 -> 28
A22: 19 | B22: GRANDE ALCANTARA GERMAN N. (INGRESO A PLANILLA 01/04/2007) | C22: 01/04/2011 | D22: =+C22+8*360 -> 43514 | E22: 240 | F22: =D22+360 -> 43874 | G22: ='Determ días de vacaciones'!S28 -> 41 | I22: 43874 | J22: 30 | K22: =+E22+J22 -> 270 | L22: =F22+G22+360 -> 44275 | N22: ='Control de dias gozados 2019'!CR25+'vacaciones 2020'!P22 -> 95 | O22: =K22-N22 -> 175
A23: 20 | B23: GRANDE ALCANTARA MILAGROS M. (INGRESO PLANILLA 01/07/2008) | C23: 01/07/2011 | D23: =+C23+8*360 -> 43605 | E23: 240 | F23: =D23+360 -> 43965 | G23: ='Determ días de vacaciones'!S29 -> 56 | I23: =F23+G23 -> 44021 | J23: 30 | K23: =+E23+J23 -> 270 | L23: =+I23+360 -> 44381 | N23: ='Control de dias gozados 2019'!CR26+'vacaciones 2020'!P23 -> 189 | O23: =K23-N23 -> 81
A24: 21 | B24: GRANDE ALCANTARA PAUL | C24: 01/01/2012 | D24: =+C24+8*360 -> 43789 | E24: 240 | F24: =D24+360 -> 44149 | G24: ='Determ días de vacaciones'!S30 -> 47 | I24: =+F24+G24 -> 44196 | J24: 0 | K24: =+E24+J24 -> 240 | L24: =+I24+360 -> 44556 | N24: ='Control de dias gozados 2019'!CR27+'vacaciones 2020'!P24 -> 210 | O24: =K24-N24 -> 30
A25: 22 | B25: GRANDE PECEROS DAVID | C25: 01/10/2018 | D25: =+C25+360 -> 43734 | E25: 30 | F25: =D25+360 -> 44094 | G25: ='Determ días de vacaciones'!S32 -> 47 | I25: =F25+G25 -> 44141 | J25: 30 | K25: =+E25+J25 -> 60 | L25: =+I25+360 -> 44501 | N25: ='Control de dias gozados 2019'!CR29+'vacaciones 2020'!P26 -> 50 | O25: =K25-N25 -> 10
A26: 23 | B26: GUZMAN MANTARI INGRID | C26: 02/11/2020 | F26: 44137 | J26: 0 | K26: 0 | L26: =F26+G26+360 -> 44497 | N26: ='Control de dias gozados 2019'!CR30+'vacaciones 2020'!P27 -> 15 | O26: 0
A27: 24 | B27: JUAN PEDRO CRUZ, GIOVANNA PAULA | C27: 01/03/2012 | D27: =C27+7*360 -> 43489 | E27: 210 | F27: =D27+360 -> 43849 | G27: ='Determ días de vacaciones'!S33 -> 56 | I27: 43849 | J27: 30 | K27: =+E27+J27 -> 240 | L27: =F27+G27+360 -> 44265 | N27: ='Control de dias gozados 2019'!CR31+'vacaciones 2020'!P28 -> 249 | O27: =K27-N27 -> -9
A28: 25 | B28: MENDOZA GARCÍA, ZINCIA | C28: 01/01/2019 | D28: =+C28+360 -> 43826 | E28: 30 | F28: =+D28+360 -> 44186 | G28: ='Determ días de vacaciones'!S34 -> 122 | H28: 50 | I28: =+F28 -> 44186 | J28: 0 | K28: =+E28+J28 -> 30 | L28: =+F28+G28+H28 -> 44358 | N28: ='Control de dias gozados 2019'!CR32+'vacaciones 2020'!P29 -> 40 | O28: =K28-N28 -> -10
A29: 26 | B29: MURGA SALCEDO ANTHONY EDGAR (INGRESO A PLANILLA 15/10/2020) | C29: 15/10/2020 | F29: 44119 | J29: 0 | K29: =+E29+J29 -> 0 | L29: =+C29+G29+360 -> 44479 | N29: ='Control de dias gozados 2019'!CR33+'vacaciones 2020'!P30 -> 2 | O29: =K29-N29 -> -2
A30: 27 | B30: OCHOA GUTIERREZ ERICKSON | C30: 01/08/2019 | F30: =+C30+360 -> 44038 | G30: ='Determ días de vacaciones'!S35 -> 44 | I30: =F30+G30 -> 44082 | J30: 30 | K30: =+E30+J30 -> 30 | L30: =+I30+360 -> 44442 | N30: ='Control de dias gozados 2019'!CR34+'vacaciones 2020'!P31 -> 0 | O30: =K30-N30 -> 30
A31: 28 | B31: OROZCO BALAREZO SILVIA (INGRESO A PLANILLA 01/08/2020) | C31: 01/08/2020 | F31: 44044 | J31: 0 | K31: =+E31+J31 -> 0 | L31: =+C31+G31+360 -> 44404 | N31: ='Control de dias gozados 2019'!CR35+'vacaciones 2020'!P32 -> 2 | O31: =K31-N31 -> -2
A32: 29 | B32: OSCCO GUILLEN EDWIN | C32: 01/11/2018 | D32: =C32+360 -> 43765 | E32: 30 | F32: =D32+360 -> 44125 | G32: ='Determ días de vacaciones'!S36 -> 39.5 | I32: =F32+G32 -> 44164.5 | J32: 0 | K32: =+E32+J32 -> 30 | L32: =+I32+360 -> 44524.5 | N32: ='Control de dias gozados 2019'!CR36+'vacaciones 2020'!P33 -> 35 | O32: =K32-N32 -> -5
A33: 30 | B33: OSCCO GUILLEN ZORAIDA | C33: 09/01/2013 | D33: =C33+7*360 -> 43803 | E33: 210 | F33: =D33+360 -> 44163 | G33: ='Determ días de vacaciones'!S37 -> 2 | I33: =F33+G33 -> 44165 | J33: 0 | K33: =+E33+J33 -> 210 | L33: =+I33+360 -> 44525 | N33: ='Control de dias gozados 2019'!CR37+'vacaciones 2020'!P34 -> 154 | O33: =K33-N33 -> 56
A34: 31 | B34: PEÑA HERNANDEZ, FERNANDO FAVIAN | C34: 01/05/2017 | D34: =C34+2*360 -> 43576 | E34: 60 | F34: =D34+360 -> 43936 | G34: ='Determ días de vacaciones'!S38 -> 92 | I34: =F34+G34 -> 44028 | J34: 30 | K34: =+E34+J34 -> 90 | L34: =+I34+360 -> 44388 | N34: ='Control de dias gozados 2019'!CR38+'vacaciones 2020'!P35 -> 18 | O34: =K34-N34 -> 72
A35: 32 | B35: RAMIREZ ROMAN MARCELO (INGRESO A PLANILLA 01/07/2008) | C35: 01/07/2011 | D35: =C35+8*360 -> 43605 | E35: 240 | F35: =D35+360 -> 43965 | G35: ='Determ días de vacaciones'!S39 -> 59 | I35: =F35+G35 -> 44024 | J35: 30 | K35: =+E35+J35 -> 270 | L35: =+I35+360 -> 44384 | N35: ='Control de dias gozados 2019'!CR39+'vacaciones 2020'!P36 -> 120 | O35: =K35-N35 -> 150
A36: 33 | B36: REYNA COSTA CLARA | C36: 01/12/2017 | D36: =C36+2*360 -> 43790 | E36: 60 | F36: =D36+360 -> 44150 | G36: 52 | H36: 77 | I36: =+F36+G36+H36 -> 44279 | J36: 0 | K36: =+E36+J36 -> 60 | L36: =+F36+G36+H36 -> 44279 | N36: ='Control de dias gozados 2019'!CR40+'vacaciones 2020'!P37 -> 78 | O36: =K36-N36 -> -18
A37: 34 | B37: SALIRROSAS PONCE LILIANA (INGRESO A PLANILLA 01/09/2020) | C37: 01/09/2020 | F37: 01/09/2020 | J37: 0 | K37: =+E37+J37 -> 0 | L37: =F37+G37+360 -> 44435 | N37: ='Control de dias gozados 2019'!CR41+'vacaciones 2020'!P38 -> 10 | O37: =K37-N37 -> -10
A38: 35 | B38: TERRONES BECERRA MARISSA (INGRESO PLANILLA 01/07/2008) | C38: 01/07/2011 | D38: =C38+8*360 -> 43605 | E38: 240 | F38: =D38+360 -> 43965 | G38: ='Determ días de vacaciones'!S41 -> 41 | I38: =F38+G38 -> 44006 | J38: 30 | K38: =+E38+J38 -> 270 | L38: =+I38+360 -> 44366 | N38: ='Control de dias gozados 2019'!CR42+'vacaciones 2020'!P39 -> 167 | O38: =K38-N38 -> 103
A39: 36 | B39: TOMAYLLA TERRONES KATHERINE | C39: 01/02/2014 | D39: =C39+5*360 -> 43471 | E39: 150 | F39: =D39+360 -> 43831 | G39: ='Determ días de vacaciones'!S42 -> 62 | I39: =F39+G39 -> 43893 | J39: 30 | K39: =+E39+J39 -> 180 | L39: =F39+G39+360 -> 44253 | N39: ='Control de dias gozados 2019'!CR43+'vacaciones 2020'!P40 -> 59 | O39: =K39-N39 -> 121
A40: 37 | B40: VENEGAS MARCHAND FRANCISCO | C40: 01/01/2019 | D40: =+C40+360 -> 43826 | E40: 30 | F40: =+D40+360 -> 44186 | G40: ='Determ días de vacaciones'!S43 -> 62 | I40: =F40+G40 -> 44248 | J40: 0 | K40: =+E40+J40 -> 30 | L40: =F40+G40 -> 44248 | N40: ='Control de dias gozados 2019'!CR44+'vacaciones 2020'!P41 -> 30 | O40: =K40-N40 -> 0
A41: 38 | B41: YNCIO JIMENEZ SILVIA | C41: 01/01/2018 | D41: =C41+2*360 -> 43821 | E41: 60 | F41: =D41+360 -> 44181 | G41: ='Determ días de vacaciones'!S44 -> 47 | I41: =F41+G41 -> 44228 | J41: 0 | K41: =+E41+J41 -> 60 | L41: 44228 | N41: ='Control de dias gozados 2019'!CR45+'vacaciones 2020'!P42 -> 88 | O41: =K41-N41 -> -28
A42: 39 | B42: YON UTRILLA LUIS | C42: 01/08/2018 | D42: =C42+360 -> 43673 | E42: 30 | F42: =D42+360 -> 44033 | G42: ='Determ días de vacaciones'!S45 -> 77 | H42: 27 | I42: =F42+G42+H42 -> 44137 | J42: 30 | K42: =+E42+J42 -> 60 | L42: =+I42+360 -> 44497 | N42: ='Control de dias gozados 2019'!CR46+'vacaciones 2020'!P43 -> 56 | O42: =K42-N42 -> 4
A43: 40 | B43: ZURITA PEÑA JOANY | C43: 01/10/2014 | D43: =C43+5*360 -> 43713 | E43: 150 | F43: =D43+360 -> 44073 | G43: ='Determ días de vacaciones'!S46 -> 2 | I43: =F43+G43 -> 44075 | J43: 30 | K43: =+E43+J43 -> 180 | L43: =+I43+360 -> 44435 | N43: ='Control de dias gozados 2019'!CR47+'vacaciones 2020'!P44 -> 99 | O43: =K43-N43 -> 81
H45: 2.5 | I45: 1
H46: 12 | I46: =H46*I45/H45 -> 4.8

Sheet Control de dias gozados 2019
A1: CONTROL DE DIAS GOZADOS DE VACACIONES
A2: 2019
A4: EMPLEADOS | C4: Gozados (2012) | D4: Enero - diciembre 2013 | P4: Gozadas (2013) | Q4: Enero - diciembre 2014 | AC4: Gozadas (2014) | AD4: Enero - diciembre 2015 | AP4: Gozadas (2015) | AQ4: Enero - diciembre 2016 | BC4: Gozadas (2016) | BD4: Enero - diciembre 2017 | BP4: Gozadas (2017) | BQ4: Enero - diciembre 2018 | CC4: Gozadas (2018) | CD4: Enero - diciembre 2019 | CP4: Gozadas (2019) | CQ4: Dias por gozar 2019 | CR4: Gozadas 2019 | CS4: saldos de dias por gozar 2019
A6: 1 | B6: ALARCON PEREZ LUIS | P6: =SUM(D6:O6) -> 0 | AC6: =SUM(Q6:AB6) -> 0 | AP6: =SUM(AD6:AO6) -> 0 | BC6: =SUM(AQ6:BB6) -> 0 | BI6: 1 | BM6: 1 | BO6: 6 | BP6: =SUM(BD6:BO6) -> 8 | BS6: 1 | BV6: 1 | BW6: 1 | BY6: 7 | BZ6: =2+1 -> 3 | CC6: =SUM(BQ6:CB6) -> 13 | CP6: =SUM(CD6:CO6) -> 0 | CQ6: =vacaciones!E4 -> 90 | CR6: =C6+P6+AC6+AP6+BC6+BP6+CC6+CP6 -> 21 | CS6: =CQ6-CR6 -> 69
A7: =+A6+1 -> 2 | B7: ALEJOS TORIBIO, SULELMA MELISA | P7: =SUM(D7:O7) -> 0 | AC7: =SUM(Q7:AB7) -> 0 | AP7: =SUM(AD7:AO7) -> 0 | BC7: =SUM(AQ7:BB7) -> 0 | BM7: 1 | BP7: =SUM(BD7:BO7) -> 1 | BS7: 1 | BT7: 2 | BU7: 2 | BV7: 2 | CC7: =SUM(BQ7:CB7) -> 7 | CJ7: 1 | CO7: 1 | CP7: =SUM(CD7:CO7) -> 2 | CQ7: =vacaciones!E5 -> 60 | CR7: =C7+P7+AC7+AP7+BC7+BP7+CC7+CP7 -> 10 | CS7: =CQ7-CR7 -> 50
A8: =+A7+1 -> 3 | B8: ALHUAY AYESTA, RAMIRO | P8: =SUM(D8:O8) -> 0 | Z8: 5 | AB8: 10 | AC8: =SUM(Q8:AB8) -> 15 | AE8: 1 | AG8: 3 | AI8: 6 | AJ8: 2 | AK8: 1 | AP8: =SUM(AD8:AO8) -> 13 | BA8: 1 | BB8: 15 | BC8: =SUM(AQ8:BB8) -> 16 | BG8: 2 | BO8: 6 | BP8: =SUM(BD8:BO8) -> 8 | BR8: 2 | BT8: 7 | BX8: 1 | BZ8: 3 | CB8: 11 | CC8: =SUM(BQ8:CB8) -> 24 | CI8: 15 | CJ8: 7 | CL8: 14 | CO8: 12 | CP8: =SUM(CD8:CO8) -> 48 | CQ8: =vacaciones!E6 -> 150 | CR8: =C8+P8+AC8+AP8+BC8+BP8+CC8+CP8 -> 124 | CS8: =CQ8-CR8 -> 26
A9: 4 | B9: ALTAMIRANO SULCA MANUEL | P9: =SUM(D9:O9) -> 0 | AC9: =SUM(Q9:AB9) -> 0 | AP9: =SUM(AD9:AO9) -> 0 | BC9: =SUM(AQ9:BB9) -> 0 | BP9: =SUM(BD9:BO9) -> 0 | CC9: =SUM(BQ9:CB9) -> 0 | CD9: 14 | CP9: =SUM(CD9:CO9) -> 14 | CQ9: =vacaciones!E7 -> 30 | CR9: =C9+P9+AC9+AP9+BC9+BP9+CC9+CP9 -> 14 | CS9: =CQ9-CR9 -> 16
A10: =+A9+1 -> 5 | B10: ARROYO FALLA, VANESSA ALICIA | P10: =SUM(D10:O10) -> 0 | AC10: =SUM(Q10:AB10) -> 0 | AP10: =SUM(AD10:AO10) -> 0 | BC10: =SUM(AQ10:BB10) -> 0 | BP10: =SUM(BD10:BO10) -> 0 | CC10: =SUM(BQ10:CB10) -> 0 | CJ10: 10 | CK10: 7 | CP10: =SUM(CD10:CO10) -> 17 | CQ10: =vacaciones!E8 -> 0 | CR10: =C10+P10+AC10+AP10+BC10+BP10+CC10+CP10 -> 17 | CS10: =CQ10-CR10 -> -17
A11: =+A10+1 -> 6 | B11: ASPILCUETA GUTIERREZ KAREN | H11: 1 | P11: =SUM(D11:O11) -> 1 | X11: 7 | AB11: 1 | AC11: =SUM(Q11:AB11) -> 8 | AD11: 1 | AE11: 4 | AF11: 2 | AH11: 1 | AJ11: 1 | AM11: 1 | AO11: 3 | AP11: =SUM(AD11:AO11) -> 13 | AQ11: 2 | AR11: 1 | AT11: 1 | AU11: 7 | AW11: 2 | AX11: 1 | BA11: 1 | BB11: 1 | BC11: =SUM(AQ11:BB11) -> 16 | BD11: 2 | BE11: 7 | BG11: 1 | BI11: 1 | BJ11: 1 | BK11: 1 | BM11: 2 | BN11: 1 | BO11: 8 | BP11: =SUM(BD11:BO11) -> 24 | BQ11: 13 | BR11: 1 | BU11: 1 | BW11: 8 | BY11: 1 | CB11: 2 | CC11: =SUM(BQ11:CB11) -> 26 | CE11: 7 | CI11: 1 | CJ11: 10 | CK11: 1 | CO11: 1 | CP11: =SUM(CD11:CO11) -> 20 | CQ11: =vacaciones!E9 -> 180 | CR11: =C11+P11+AC11+AP11+BC11+BP11+CC11+CP11 -> 108 | CS11: =CQ11-CR11 -> 72
A12: 7 | B12: BACA WIESSE JOSE ALBERTO | C12: 45 | E12: 1 | G12: 1 | I12: 4 | J12: 1 | K12: 3 | O12: 1 | P12: =SUM(D12:O12) -> 11 | Q12: 1 | R12: 1 | T12: 1 | U12: 4 | Y12: 1 | Z12: 1 | AB12: 3 | AC12: =SUM(Q12:AB12) -> 12 | AE12: 4 | AG12: 1 | AI12: 4 | AJ12: 2 | AL12: 1 | AM12: 4 | AN12: 1 | AO12: 3 | AP12: =SUM(AD12:AO12) -> 20 | AR12: 14 | AS12: 2 | AZ12: 1 | BA12: 3 | BB12: 3 | BC12: =SUM(AQ12:BB12) -> 23 | BP12: =SUM(BD12:BO12) -> 0 | BR12: 10 | BW12: 1 | BX12: 1 | CC12: =SUM(BQ12:CB12) -> 12 | CE12: 11 | CO12: 14 | CP12: =SUM(CD12:CO12) -> 25 | CQ12: =vacaciones!E10 -> 270 | CR12: =C12+P12+AC12+AP12+BC12+BP12+CC12+CP12 -> 148 | CS12: =CQ12-CR12 -> 122
A13: =+A12+1 -> 8 | B13: BALLENA CASTILLO ITALA ADRIANA | C13: 15 | F13: 5 | I13: 5 | J13: 8 | P13: =SUM(D13:O13) -> 18 | X13: 2 | Y13: 1 | AB13: 3 | AC13: =SUM(Q13:AB13) -> 6 | AD13: 1 | AE13: 15 | AJ13: 4 | AK13: 1 | AP13: =SUM(AD13:AO13) -> 21 | AV13: 14 | AX13: 1 | BB13: 22 | BC13: =SUM(AQ13:BB13) -> 37 | BK13: 37 | BM13: 1 | BO13: 14 | BP13: =SUM(BD13:BO13) -> 52 | BQ13: 4 | BZ13: 30 | CC13: =SUM(BQ13:CB13) -> 34 | CG13: 3 | CL13: 8 | CO13: 15 | CP13: =SUM(CD13:CO13) -> 26 | CQ13: =vacaciones!E11 -> 240 | CR13: =C13+P13+AC13+AP13+BC13+BP13+CC13+CP13 -> 209 | CS13: =CQ13-CR13 -> 31
A14: =+A13+1 -> 9 | B14: BAUTISTA AYESTA HEBER | C14: 15 | P14: =SUM(D14:O14) -> 0 | AC14: =SUM(Q14:AB14) -> 0 | AE14: 14 | AP14: =SUM(AD14:AO14) -> 14 | AR14: 1 | AT14: 1 | AV14: 5 | BC14: =SUM(AQ14:BB14) -> 7 | BP14: =SUM(BD14:BO14) -> 0 | BS14: 15 | CC14: =SUM(BQ14:CB14) -> 15 | CJ14: 14 | CP14: =SUM(CD14:CO14) -> 14 | CQ14: =vacaciones!E12 -> 240 | CR14: =C14+P14+AC14+AP14+BC14+BP14+CC14+CP14 -> 65 | CS14: =CQ14-CR14 -> 175
A15: 10 | B15: BAUTISTA AYESTA WALTER | P15: =SUM(D15:O15) -> 0 | AC15: =SUM(Q15:AB15) -> 0 | AI15: 6 | AP15: =SUM(AD15:AO15) -> 6 | BC15: =SUM(AQ15:BB15) -> 0 | BP15: =SUM(BD15:BO15) -> 0 | CC15: =SUM(BQ15:CB15) -> 0 | CP15: =SUM(CD15:CO15) -> 0 | CQ15: =vacaciones!E13 -> 240 | CR15: =C15+P15+AC15+AP15+BC15+BP15+CC15+CP15 -> 6 | CS15: =CQ15-CR15 -> 234
A16: =+A15+1 -> 11 | B16: BAUTISTA MOLINA LUIS FERNANDO | CQ16: =vacaciones!E14 -> 0 | CR16: =C16+P16+AC16+AP16+BC16+BP16+CC16+CP16 -> 0 | CS16: =CQ16-CR16 -> 0
A17: =+A16+1 -> 12 | B17: BRIONES RIVERA, RICHARD | P17: =SUM(D17:O17) -> 0 | AC17: =SUM(Q17:AB17) -> 0 | AP17: =SUM(AD17:AO17) -> 0 | BC17: =SUM(AQ17:BB17) -> 0 | BP17: =SUM(BD17:BO17) -> 0 | CC17: =SUM(BQ17:CB17) -> 0 | CP17: =SUM(CD17:CO17) -> 0 | CQ17: =vacaciones!E15 -> 0 | CR17: =C17+P17+AC17+AP17+BC17+BP17+CC17+CP17 -> 0 | CS17: =CQ17-CR17 -> 0
A18: 13 | B18: COLETO PASTOR LUIS ENRIQUE | P18: =SUM(D18:O18) -> 0 | Q18: 10 | X18: 16 | Y18: 30 | Z18: 30 | AC18: =SUM(Q18:AB18) -> 86 | AK18: 3 | AM18: 23 | AO18: 1 | AP18: =SUM(AD18:AO18) -> 27 | AQ18: 1 | BA18: 1 | BC18: =SUM(AQ18:BB18) -> 2 | BF18: 7 | BO18: 4 | BP18: =SUM(BD18:BO18) -> 11 | BQ18: 54 | CC18: =SUM(BQ18:CB18) -> 54 | CJ18: 9 | CN18: 11 | CP18: =SUM(CD18:CO18) -> 20 | CQ18: =vacaciones!E16 -> 240 | CR18: =C18+P18+AC18+AP18+BC18+BP18+CC18+CP18 -> 200 | CS18: =CQ18-CR18 -> 40
A19: =+A18+1 -> 14 | B19: CORDOVA VELEZ, JULISSA | P19: =SUM(D19:O19) -> 0 | AC19: =SUM(Q19:AB19) -> 0 | AP19: =SUM(AD19:AO19) -> 0 | BC19: =SUM(AQ19:BB19) -> 0 | BP19: =SUM(BD19:BO19) -> 0 | CC19: =SUM(BQ19:CB19) -> 0 | CP19: =SUM(CD19:CO19) -> 0 | CQ19: =vacaciones!E17 -> 0 | CR19: =C19+P19+AC19+AP19+BC19+BP19+CC19+CP19 -> 0 | CS19: =CQ19-CR19 -> 0
A20: =+A19+1 -> 15 | B20: DAMBROSIO RIVERO LIZETH STEFANNY | P20: =SUM(D20:O20) -> 0 | AC20: =SUM(Q20:AB20) -> 0 | AP20: =SUM(AD20:AO20) -> 0 | BC20: =SUM(AQ20:BB20) -> 0 | BP20: =SUM(BD20:BO20) -> 0 | CC20: =SUM(BQ20:CB20) -> 0 | CH20: 3 | CO20: 4 | CP20: =SUM(CD20:CO20) -> 7 | CQ20: =vacaciones!E18 -> 30 | CR20: =C20+P20+AC20+AP20+BC20+BP20+CC20+CP20 -> 7 | CS20: =CQ20-CR20 -> 23
A21: 16 | B21: ESPEJO PACHECO, URSULA AMELIA | CR21: =C21+P21+AC21+AP21+BC21+BP21+CC21+CP21 -> 0 | CS21: =CQ21-CR21 -> 0
A22: =+A21+1 -> 17 | B22: FLORES GUARDIA CLAUDIA | P22: =SUM(D22:O22) -> 0 | AC22: =SUM(Q22:AB22) -> 0 | AP22: =SUM(AD22:AO22) -> 0 | BC22: =SUM(AQ22:BB22) -> 0 | BP22: =SUM(BD22:BO22) -> 0 | CC22: =SUM(BQ22:CB22) -> 0 | CP22: =SUM(CD22:CO22) -> 0 | CQ22: =vacaciones!E19 -> 0 | CR22: =C22+P22+AC22+AP22+BC22+BP22+CC22+CP22 -> 0 | CS22: =CQ22-CR22 -> 0
A23: =+A22+1 -> 18 | B23: FLORES MANTILLA MARIANA | P23: =SUM(D23:O23) -> 0 | W23: 1 | AC23: =SUM(Q23:AB23) -> 1 | AE23: 30 | AF23: 30 | AJ23: 1 | AP23: =SUM(AD23:AO23) -> 61 | AR23: 7 | AW23: 3 | BA23: 1 | BC23: =SUM(AQ23:BB23) -> 11 | BH23: 1 | BJ23: 1 | BO23: 1 | BP23: =SUM(BD23:BO23) -> 3 | BR23: 1 | BS23: 7 | BW23: 7 | BZ23: 8 | CC23: =SUM(BQ23:CB23) -> 23 | CF23: 1 | CI23: 7 | CJ23: 2 | CP23: =SUM(CD23:CO23) -> 10 | CQ23: =vacaciones!E20 -> 150 | CR23: =C23+P23+AC23+AP23+BC23+BP23+CC23+CP23 -> 109 | CS23: =CQ23-CR23 -> 41
A24: 19 | B24: GOYAS ABRAMONTE, JAVIER ENRRIQUE | P24: =SUM(D24:O24) -> 0 | AC24: =SUM(Q24:AB24) -> 0 | AP24: =SUM(AD24:AO24) -> 0 | BC24: =SUM(AQ24:BB24) -> 0 | BP24: =SUM(BD24:BO24) -> 0 | CC24: =SUM(BQ24:CB24) -> 0 | CP24: =SUM(CD24:CO24) -> 0 | CQ24: =vacaciones!E21 -> 0 | CR24: =C24+P24+AC24+AP24+BC24+BP24+CC24+CP24 -> 0 | CS24: =CQ24-CR24 -> 0
A25: =+A24+1 -> 20 | B25: GRANDE ALCANTARA GERMAN N. | P25: =SUM(D25:O25) -> 0 | AC25: =SUM(Q25:AB25) -> 0 | AE25: 7 | AH25: 2 | AP25: =SUM(AD25:AO25) -> 9 | AQ25: 20 | BA25: 1 | BC25: =SUM(AQ25:BB25) -> 21 | BH25: 7 | BJ25: 20 | BP25: =SUM(BD25:BO25) -> 27 | CC25: =SUM(BQ25:CB25) -> 0 | CP25: =SUM(CD25:CO25) -> 0 | CQ25: =vacaciones!E22 -> 240 | CR25: =C25+P25+AC25+AP25+BC25+BP25+CC25+CP25 -> 57 | CS25: =CQ25-CR25 -> 183
A26: =+A25+1 -> 21 | B26: GRANDE ALCANTARA MILAGROS M. | C26: 15 | P26: =SUM(D26:O26) -> 0 | AC26: =SUM(Q26:AB26) -> 0 | AE26: 8 | AJ26: 8 | AP26: =SUM(AD26:AO26) -> 16 | BA26: 1 | BC26: =SUM(AQ26:BB26) -> 1 | BJ26: 10 | BP26: =SUM(BD26:BO26) -> 10 | BR26: 5 | CC26: =SUM(BQ26:CB26) -> 5 | CD26: 30 | CP26: =SUM(CD26:CO26) -> 30 | CQ26: =vacaciones!E23 -> 240 | CR26: =C26+P26+AC26+AP26+BC26+BP26+CC26+CP26 -> 77 | CS26: =CQ26-CR26 -> 163
A27: 22 | B27: GRANDE ALCANTARA PAUL | C27: 15 | P27: =SUM(D27:O27) -> 0 | Q27: 4 | U27: 3 | AC27: =SUM(Q27:AB27) -> 7 | AE27: 7 | AI27: 7 | AN27: 2 | AO27: 3 | AP27: =SUM(AD27:AO27) -> 19 | AQ27: 10 | AR27: 2 | AW27: 7 | BC27: =SUM(AQ27:BB27) -> 19 | BE27: 2 | BP27: =SUM(BD27:BO27) -> 2 | BS27: 6 | BT27: 8 | CC27: =SUM(BQ27:CB27) -> 14 | CK27: 12 | CP27: =SUM(CD27:CO27) -> 12 | CQ27: =vacaciones!E24 -> 240 | CR27: =C27+P27+AC27+AP27+BC27+BP27+CC27+CP27 -> 88 | CS27: =CQ27-CR27 -> 152
A28: =+A27+1 -> 23 | B28: GRANDE ALCANTRA, RAUL NEVADA | CR28: =C28+P28+AC28+AP28+BC28+BP28+CC28+CP28 -> 0 | CS28: =CQ28-CR28 -> 0
A29: =+A28+1 -> 24 | B29: GRANDE PECEROS DAVID | P29: =SUM(D29:O29) -> 0 | AC29: =SUM(Q29:AB29) -> 0 | AP29: =SUM(AD29:AO29) -> 0 | BC29: =SUM(AQ29:BB29) -> 0 | BP29: =SUM(BD29:BO29) -> 0 | CB29: 4 | CC29: =SUM(BQ29:CB29) -> 4 | CE29: 7 | CJ29: 1 | CL29: 8 | CP29: =SUM(CD29:CO29) -> 16 | CQ29: =vacaciones!E25 -> 30 | CR29: =C29+P29+AC29+AP29+BC29+BP29+CC29+CP29 -> 20 | CS29: =CQ29-CR29 -> 10
A30: 25 | B30: GUZMAN MANTARI INGRID | CQ30: =vacaciones!E26 -> 0 | CR30: =C30+P30+AC30+AP30+BC30+BP30+CC30+CP30 -> 0 | CS30: =CQ30-CR30 -> 0
A31: =+A30+1 -> 26 | B31: JUAN PEDRO CRUZ, GIOVANNA PAULA | E31: 1 | I31: 1 | K31: 2 | P31: =SUM(D31:O31) -> 4 | R31: 2 | S31: 1 | U31: 1 | AC31: =SUM(Q31:AB31) -> 4 | AD31: 1 | AF31: 2 | AG31: 5 | AI31: 1 | AJ31: 2 | AK31: 5 | AN31: 1 | AP31: =SUM(AD31:AO31) -> 17 | AQ31: 1 | AR31: 1 | AT31: 2 | BA31: 1 | BC31: =SUM(AQ31:BB31) -> 5 | BD31: 2 | BE31: 2 | BF31: 1 | BG31: 2 | BH31: 3 | BN31: 4 | BO31: 6 | BP31: =SUM(BD31:BO31) -> 20 | BQ31: 1 | BR31: 5 | BU31: 5 | BV31: 2 | BW31: 3 | BY31: 2 | CC31: =SUM(BQ31:CB31) -> 18 | CD31: 60 | CF31: 2 | CH31: 60 | CL31: 30 | CP31: =SUM(CD31:CO31) -> 152 | CQ31: =vacaciones!E27 -> 210 | CR31: =C31+P31+AC31+AP31+BC31+BP31+CC31+CP31 -> 220 | CS31: =CQ31-CR31 -> -10
A32: =+A31+1 -> 27 | B32: MENDOZA GARCÍA, ZINCIA | P32: =SUM(D32:O32) -> 0 | AC32: =SUM(Q32:AB32) -> 0 | AP32: =SUM(AD32:AO32) -> 0 | BC32: =SUM(AQ32:BB32) -> 0 | BP32: =SUM(BD32:BO32) -> 0 | CC32: =SUM(BQ32:CB32) -> 0 | CK32: 5 | CP32: =SUM(CD32:CO32) -> 5 | CQ32: =vacaciones!E28 -> 30 | CR32: =C32+P32+AC32+AP32+BC32+BP32+CC32+CP32 -> 5 | CS32: =CQ32-CR32 -> 25
A33: 28 | B33: MURGA SALCEDO, ANTHONY EDGAR | CR33: =C33+P33+AC33+AP33+BC33+BP33+CC33+CP33 -> 0 | CS33: =CQ33-CR33 -> 0
A34: =+A33+1 -> 29 | B34: OCHOA GUTIERREZ ERICKSON | P34: =SUM(D34:O34) -> 0 | AC34: =SUM(Q34:AB34) -> 0 | AP34: =SUM(AD34:AO34) -> 0 | BC34: =SUM(AQ34:BB34) -> 0 | BP34: =SUM(BD34:BO34) -> 0 | CC34: =SUM(BQ34:CB34) -> 0 | CP34: =SUM(CD34:CO34) -> 0 | CQ34: =vacaciones!E30 -> 0 | CR34: =C34+P34+AC34+AP34+BC34+BP34+CC34+CP34 -> 0 | CS34: =CQ34-CR34 -> 0
A35: =+A34+1 -> 30 | B35: OROSCO BALAREZO SILVIA | CQ35: =vacaciones!E31 -> 0 | CR35: =C35+P35+AC35+AP35+BC35+BP35+CC35+CP35 -> 0 | CS35: =CQ35-CR35 -> 0
A36: 31 | B36: OSCCO GUILLEN EDWIN RAFAEL | P36: =SUM(D36:O36) -> 0 | AC36: =SUM(Q36:AB36) -> 0 | AP36: =SUM(AD36:AO36) -> 0 | BC36: =SUM(AQ36:BB36) -> 0 | BP36: =SUM(BD36:BO36) -> 0 | CC36: =SUM(BQ36:CB36) -> 0 | CP36: =SUM(CD36:CO36) -> 0 | CQ36: =vacaciones!E32 -> 30 | CR36: =C36+P36+AC36+AP36+BC36+BP36+CC36+CP36 -> 0 | CS36: =CQ36-CR36 -> 30
A37: =+A36+1 -> 32 | B37: OSCCO GUILLEN ZORAIDA | I37: 2 | O37: 24 | P37: =SUM(D37:O37) -> 26 | AC37: =SUM(Q37:AB37) -> 0 | AF37: 1 | AH37: 1 | AI37: 5 | AJ37: 1 | AK37: 1 | AM37: 1 | AN37: 1 | AO37: 29 | AP37: =SUM(AD37:AO37) -> 40 | BA37: 1 | BC37: =SUM(AQ37:BB37) -> 1 | BM37: 1 | BN37: 3 | BO37: 5 | BP37: =SUM(BD37:BO37) -> 9 | BQ37: 8 | BR37: 3 | BU37: 1 | CB37: 2 | CC37: =SUM(BQ37:CB37) -> 14 | CH37: 2 | CK37: 1 | CL37: 1 | CN37: 1 | CO37: 30 | CP37: =SUM(CD37:CO37) -> 35 | CQ37: =vacaciones!E33 -> 210 | CR37: =C37+P37+AC37+AP37+BC37+BP37+CC37+CP37 -> 125 | CS37: =CQ37-CR37 -> 85
A38: =+A37+1 -> 33 | B38: PEÑA HERNANDEZ, FERNANDO FAVIAN | P38: =SUM(D38:O38) -> 0 | AC38: =SUM(Q38:AB38) -> 0 | AP38: =SUM(AD38:AO38) -> 0 | BC38: =SUM(AQ38:BB38) -> 0 | BP38: =SUM(BD38:BO38) -> 0 | BU38: 5 | BZ38: 7 | CC38: =SUM(BQ38:CB38) -> 12 | CG38: 1 | CK38: 3 | CP38: =SUM(CD38:CO38) -> 4 | CQ38: =vacaciones!E34 -> 60 | CR38: =C38+P38+AC38+AP38+BC38+BP38+CC38+CP38 -> 16 | CS38: =CQ38-CR38 -> 44
A39: 34 | B39: RAMIREZ ROMAN MARCELO | C39: 30 | H39: 1 | L39: 3 | O39: 15 | P39: =SUM(D39:O39) -> 19 | S39: 5 | T39: 8 | U39: 1 | Y39: 3 | AB39: 9 | AC39: =SUM(Q39:AB39) -> 26 | AG39: 1 | AH39: 7 | AJ39: 1 | AK39: 4 | AL39: 1 | AP39: =SUM(AD39:AO39) -> 14 | AS39: 1 | BA39: 1 | BC39: =SUM(AQ39:BB39) -> 2 | BJ39: 15 | BP39: =SUM(BD39:BO39) -> 15 | CC39: =SUM(BQ39:CB39) -> 0 | CH39: 7 | CP39: =SUM(CD39:CO39) -> 7 | CQ39: =vacaciones!E35 -> 240 | CR39: =C39+P39+AC39+AP39+BC39+BP39+CC39+CP39 -> 113 | CS39: =CQ39-CR39 -> 127
A40: =+A39+1 -> 35 | B40: REYNA COSTA CLARA | P40: =SUM(D40:O40) -> 0 | AC40: =SUM(Q40:AB40) -> 0 | AP40: =SUM(AD40:AO40) -> 0 | BC40: =SUM(AQ40:BB40) -> 0 | BP40: =SUM(BD40:BO40) -> 0 | BT40: 22 | CC40: =SUM(BQ40:CB40) -> 22 | CH40: 4 | CP40: =SUM(CD40:CO40) -> 4 | CQ40: =vacaciones!E36 -> 60 | CR40: =C40+P40+AC40+AP40+BC40+BP40+CC40+CP40 -> 26 | CS40: =CQ40-CR40 -> 34
A41: =+A40+1 -> 36 | B41: SALIRROSAS PONCE LILIANA | CQ41: =vacaciones!E37 -> 0 | CS41: =CQ41-CR41 -> 0
A42: 37 | B42: TERRONES BECERRA MARISSA | F42: 1 | H42: 1 | J42: 2 | M42: 1 | P42: =SUM(D42:O42) -> 5 | Q42: 7 | V42: 1 | W42: 1 | AC42: =SUM(Q42:AB42) -> 9 | AF42: 4 | AG42: 1 | AJ42: 6 | AK42: 1 | AL42: 1 | AM42: 1 | AN42: 3 | AP42: =SUM(AD42:AO42) -> 17 | AT42: 2 | AU42: 10 | AW42: 1 | AY42: 2 | AZ42: 1 | BA42: 3 | BB42: 1 | BC42: =SUM(AQ42:BB42) -> 20 | BD42: 1 | BE42: 8 | BG42: 2 | BH42: 2 | BJ42: 3 | BK42: 7 | BM42: 2 | BO42: 6 | BP42: =SUM(BD42:BO42) -> 31 | BQ42: 2 | BR42: 2 | BS42: 6 | BU42: 4 | BX42: 5 | BZ42: =3+1 -> 4 | CB42: 1 | CC42: =SUM(BQ42:CB42) -> 24 | CD42: 1 | CE42: 1 | CF42: 5 | CH42: 3 | CJ42: 8 | CL42: =1+1 -> 2 | CM42: =1+1+1 -> 3 | CN42: =1+2 -> 3 | CO42: =1+1 -> 2 | CP42: =SUM(CD42:CO42) -> 28 | CQ42: =vacaciones!E38 -> 240 | CR42: =C42+P42+AC42+AP42+BC42+BP42+CC42+CP42 -> 134 | CS42: =CQ42-CR42 -> 106
A43: =+A42+1 -> 38 | B43: TOMAYLLA TERRONES KATHERINE | P43: =SUM(D43:O43) -> 0 | V43: 1 | Z43: 1 | AC43: =SUM(Q43:AB43) -> 2 | AG43: 2 | AI43: 1 | AJ43: 1 | AL43: 1 | AM43: 1 | AN43: 1 | AO43: 1 | AP43: =SUM(AD43:AO43) -> 8 | AQ43: 2 | AR43: 1 | AT43: 1 | AW43: 1 | BA43: 1 | BC43: =SUM(AQ43:BB43) -> 6 | BO43: 6 | BP43: =SUM(BD43:BO43) -> 6 | BR43: 1 | CC43: =SUM(BQ43:CB43) -> 1 | CF43: 1 | CI43: 1 | CJ43: 1 | CK43: 1 | CL43: 1 | CM43: 2 | CP43: =SUM(CD43:CO43) -> 7 | CQ43: =vacaciones!E39 -> 150 | CR43: =C43+P43+AC43+AP43+BC43+BP43+CC43+CP43 -> 30 | CS43: =CQ43-CR43 -> 120
A44: =+A43+1 -> 39 | B44: VENEGAS MARCHAND, FRANCISCO MARTIN | P44: =SUM(D44:O44) -> 0 | AC44: =SUM(Q44:AB44) -> 0 | AP44: =SUM(AD44:AO44) -> 0 | BC44: =SUM(AQ44:BB44) -> 0 | BP44: =SUM(BD44:BO44) -> 0 | CC44: =SUM(BQ44:CB44) -> 0 | CP44: =SUM(CD44:CO44) -> 0 | CQ44: =vacaciones!E40 -> 30 | CR44: =C44+P44+AC44+AP44+BC44+BP44+CC44+CP44 -> 0 | CS44: =CQ44-CR44 -> 30
A45: 40 | B45: YNCIO JIMENEZ SILVIA | P45: =SUM(D45:O45) -> 0 | AC45: =SUM(Q45:AB45) -> 0 | AP45: =SUM(AD45:AO45) -> 0 | BC45: =SUM(AQ45:BB45) -> 0 | BP45: =SUM(BD45:BO45) -> 0 | BS45: 6 | BU45: 1 | BW45: 2 | BY45: 7 | CB45: 14 | CC45: =SUM(BQ45:CB45) -> 30 | CI45: 17 | CJ45: 3 | CO45: 13 | CP45: =SUM(CD45:CO45) -> 33 | CQ45: =vacaciones!E41 -> 60 | CR45: =C45+P45+AC45+AP45+BC45+BP45+CC45+CP45 -> 63 | CS45: =CQ45-CR45 -> -3
A46: =+A45+1 -> 41 | B46: YON UTRILLA LUIS | P46: =SUM(D46:O46) -> 0 | AC46: =SUM(Q46:AB46) -> 0 | AP46: =SUM(AD46:AO46) -> 0 | BC46: =SUM(AQ46:BB46) -> 0 | BP46: =SUM(BD46:BO46) -> 0 | BQ46: 1 | CC46: =SUM(BQ46:CB46) -> 1 | CE46: 14 | CP46: =SUM(CD46:CO46) -> 14 | CQ46: =vacaciones!E42 -> 30 | CR46: =C46+P46+AC46+AP46+BC46+BP46+CC46+CP46 -> 15 | CS46: =CQ46-CR46 -> 15
A47: =+A46+1 -> 42 | B47: ZURITA PEÑA JOANY | P47: =SUM(D47:O47) -> 0 | Z47: 1 | AB47: 4 | AC47: =SUM(Q47:AB47) -> 5 | AF47: 2 | AH47: 2 | AJ47: 1 | AO47: 15 | AP47: =SUM(AD47:AO47) -> 20 | AR47: 3 | AT47: 2 | AZ47: 7 | BA47: 2 | BB47: 11 | BC47: =SUM(AQ47:BB47) -> 25 | BH47: 1 | BJ47: 7 | BM47: 2 | BO47: 15 | BP47: =SUM(BD47:BO47) -> 25 | BS47: 7 | BU47: 1 | BX47: 3 | CB47: 2 | CC47: =SUM(BQ47:CB47) -> 13 | CF47: 2 | CL47: 7 | CP47: =SUM(CD47:CO47) -> 9 | CQ47: =vacaciones!E43 -> 150 | CR47: =C47+P47+AC47+AP47+BC47+BP47+CC47+CP47 -> 97 | CS47: =CQ47-CR47 -> 53

Sheet Determ días de vacaciones
A5: DETERMINACION DE DIAS DE VACACIONES
A6: =+'Control de dias gozados 2019'!B2 -> 0
G8: 44134 | W8: 44043
A9: N° | B9: EMPLEADOS | C9: FECHA DE INGRESO A RUAG | D9: INGRESO A PLANILLA | E9: FECHA DE INGRESO | G9: AL 15 MAR | H9: 16 MAR- 30 JUN | J9: JULIO | K9: AGOSTO | L9: SETIEMBRE | M9: OCTUBRE | N9: NOVIEMBRE | O9: TOTAL DIAS TRABAJADOS (a) | P9: TOTAL DIAS VACAC (a/365*30) | Q9: DIAS GOZADOS | R9: DIAS POR GOZAR | W9: 43906
A10: 1 | B10: ALARCON PEREZ LUIS | C10: 42736 | D10: 42736 | E10: =+D10 -> 42736 | G10: =$G$8-E10 -> 1398 | H10: 2.2 | I10: =H10*30 -> 66 | J10: 15 | K10: 30 | L10: 30 | M10: 30 | N10: 30 | O10: =+G10+I10+J10++K10+L10+M10+N10 -> 1599 | P10: =(O10/365)*30 -> 131.42466 | Q10: =+'Control de dias gozados 2019'!#REF! -> #REF! | R10: =P10-Q10 -> #REF! | S10: =$W$10-I10-J10 -> 56 | W10: =W8-W9 -> 137
A11: =+A10+1 -> 2 | B11: ALEJOS TORIBIO, SULELMA MELISA | C11: 42979 | D11: 42979 | E11: =+D11 -> 42979 | G11: =$G$8-E11 -> 1155 | H11: 1 | I11: =H11*30 -> 30 | J11: 15 | K11: 30 | L11: 30 | M11: 30 | N11: 30 | O11: =+G11+I11+J11++K11+L11+M11+N11 -> 1320 | P11: =(O11/365)*30 -> 108.49315 | Q11: =+'Control de dias gozados 2019'!#REF! -> #REF! | R11: =P11-Q11 -> #REF! | S11: =$W$10-I11-J11 -> 92 | W11: =I11+J11 -> 45
A12: =+A11+1 -> 3 | B12: ALHUAY AYESTA, RAMIRO | D12: 41883 | E12: =+D12 -> 41883 | G12: =$G$8-E12 -> 2251 | H12: 1.5 | I12: =H12*30 -> 45 | J12: 0 | K12: 30 | L12: 30 | M12: 30 | N12: 21 | O12: =+G12+I12+J12++K12+L12+M12+N12 -> 2407 | P12: =(O12/365)*30 -> 197.83562 | Q12: =+'Control de dias gozados 2019'!#REF! -> #REF! | R12: =P12-Q12 -> #REF! | S12: =$W$10-I12-J12 -> 92 | W12: =W10-W11 -> 92
A13: =+A12+1 -> 4 | B13: ALTAMIRANO SULCA MANUEL | D13: 43313 | E13: =+D13 -> 43313 | G13: =$G$8-E13 -> 821 | H13: 1.5 | I13: =H13*30 -> 45 | J13: 30 | K13: 30 | L13: 30 | M13: 30 | N13: 30 | O13: =+G13+I13+J13++K13+L13+M13+N13 -> 1016 | P13: =(O13/365)*30 -> 83.506849 | Q13: =+'Control de dias gozados 2019'!#REF! -> #REF! | R13: =P13-Q13 -> #REF! | S13: =$W$10-I13-J13 -> 62
A14: =+A13+1 -> 5 | B14: ARROYO FALLA, VANESSA ALICIA | C14: 16/05/2012 BAJA | D14: 43556 | E14: =+D14 -> 43556 | G14: =$G$8-E14 -> 578 | H14: 1.45 | I14: =H14*30 -> 43.5 | J14: 30 | K14: 30 | M14: 30 | N14: 30 | O14: =+G14+I14+J14++K14+L14+M14+N14 -> 741.5 | P14: =(O14/365)*30 -> 60.945205 | Q14: =+'Control de dias gozados 2019'!#REF! -> #REF! | R14: =P14-Q14 -> #REF! | S14: =$W$10-I14-J14 -> 63.5
A15: =+A14+1 -> 6 | B15: ASPILCUETA GUTIERREZ KAREN | C15: 41365 | D15: 41365 | E15: =+D15 -> 41365 | G15: =$G$8-E15 -> 2769 | H15: 2.2 | I15: =H15*30 -> 66 | J15: 30 | K15: 30 | L15: 30 | M15: 30 | N15: 30 | O15: =+G15+I15+J15++K15+L15+M15+N15 -> 2985 | P15: =(O15/365)*30 -> 245.34247 | Q15: =+'Control de dias gozados 2019'!#REF! -> #REF! | R15: =P15-Q15 -> #REF! | S15: =$W$10-I15-J15 -> 41
A16: =+A15+1 -> 7 | B16: BACA WIESSE JOSE ALBERTO | C16: 38504 | D16: 40544 | E16: =+D16 -> 40544 | G16: =$G$8-E16 -> 3590 | H16: 1.5 | I16: =H16*30 -> 45 | J16: 30 | K16: 30 | L16: 30 | M16: 30 | N16: 30 | O16: =+G16+I16+J16++K16+L16+M16+N16 -> 3785 | P16: =(O16/365)*30 -> 311.09589 | Q16: =+'Control de dias gozados 2019'!#REF! -> #REF! | R16: =P16-Q16 -> #REF! | S16: =$W$10-I16-J16 -> 62
A17: =+A16+1 -> 8 | B17: BALLENA CASTILLO ITALA ADRIANA | C17: 40210 | D17: 40603 | E17: =+D17 -> 40603 | G17: =$G$8-E17 -> 3531 | H17: 2.1 | I17: =H17*30 -> 63 | J17: 30 | K17: 30 | L17: 30 | M17: 30 | N17: 30 | O17: =+G17+I17+J17++K17+L17+M17+N17 -> 3744 | P17: =(O17/365)*30 -> 307.72603 | Q17: =+'Control de dias gozados 2019'!#REF! -> #REF! | R17: =P17-Q17 -> #REF! | S17: =$W$10-I17-J17 -> 44
A18: =+A17+1 -> 9 | B18: BAUTISTA AYESTA HEBER | C18: 38565 | D18: 39630 | E18: 40725 | G18: =$G$8-E18 -> 3409 | H18: 1.5 | I18: =H18*30 -> 45 | J18: 30 | K18: 30 | L18: 30 | M18: 30 | N18: 30 | O18: =+G18+I18+J18++K18+L18+M18+N18 -> 3604 | P18: =(O18/365)*30 -> 296.21918 | Q18: =+'Control de dias gozados 2019'!#REF! -> #REF! | R18: =P18-Q18 -> #REF! | S18: =$W$10-I18-J18 -> 62
A19: =+A18+1 -> 10 | B19: BAUTISTA AYESTA WALTER | C19: 38565 | D19: 39203 | E19: 40664 | G19: =$G$8-E19 -> 3470 | H19: 0.5 | I19: =H19*30 -> 15 | J19: 30 | K19: 30 | L19: 30 | M19: 30 | N19: 30 | O19: =+G19+I19+J19++K19+L19+M19+N19 -> 3635 | P19: =(O19/365)*30 -> 298.76712 | Q19: =+'Control de dias gozados 2019'!#REF! -> #REF! | R19: =P19-Q19 -> #REF! | S19: =$W$10-I19-J19 -> 92
A20: =+A19+1 -> 11 | B20: BRIONES RIVERA, RICHARD | C20: 39814 | D20: 43862 | E20: =+D20 -> 43862 | G20: =$G$8-E20 -> 272 | H20: 0 | I20: =H20*30 -> 0 | J20: 0 | K20: 30 | L20: 30 | M20: 30 | N20: 30 | O20: =+G20+I20+J20++K20+L20+M20+N20 -> 392 | P20: =(O20/365)*30 -> 32.219178 | Q20: =+'Control de dias gozados 2019'!#REF! -> #REF! | R20: =P20-Q20 -> #REF! | S20: =$W$10-I20-J20 -> 137
A21: =+A20+1 -> 12 | B21: COLETO PASTOR LUIS ENRIQUE | D21: 40452 | E21: 40817 | G21: =$G$8-E21 -> 3317 | H21: 0.5 | I21: =H21*30 -> 15 | J21: 30 | K21: 30 | L21: 30 | M21: 30 | N21: 30 | O21: =+G21+I21+J21++K21+L21+M21+N21 -> 3482 | P21: =(O21/365)*30 -> 286.19178 | Q21: =+'Control de dias gozados 2019'!#REF! -> #REF! | R21: =P21-Q21 -> #REF! | S21: =$W$10-I21-J21 -> 92
A22: =+A21+1 -> 13 | B22: CORDOVA VELEZ, JULISSA | C22: 40634 | D22: 43862 | E22: =+D22 -> 43862 | G22: =$G$8-E22 -> 272 | H22: 0 | I22: =H22*30 -> 0 | J22: 0 | K22: 30 | L22: 30 | M22: 30 | N22: 30 | O22: =+G22+I22+J22++K22+L22+M22+N22 -> 392 | P22: =(O22/365)*30 -> 32.219178 | Q22: =+'Control de dias gozados 2019'!#REF! -> #REF! | R22: =P22-Q22 -> #REF! | S22: =$W$10-I22-J22 -> 137
A23: =+A22+1 -> 14 | B23: DAMBROSIO RIVERO LIZETH STEFANNY | C23: 39142 | D23: 43466 | E23: =+D23 -> 43466 | G23: =$G$8-E23 -> 668 | H23: 1.375 | I23: =H23*30 -> 41.25 | J23: 0 | K23: 30 | L23: 2 | O23: =+G23+I23+J23++K23+L23+M23+N23 -> 741.25 | P23: =(O23/365)*30 -> 60.924658 | Q23: =+'Control de dias gozados 2019'!#REF! -> #REF! | R23: =P23-Q23 -> #REF! | S23: =$W$10-I23-J23 -> 95.75
A24: =+A23+1 -> 15 | B24: ESPEJO PACHECO, URSULA AMELIA | D24: 40238 | E24: =+D24 -> 40238 | H24: 2.2 | K24: 30 | O24: =+G24+I24+J24++K24+L24+M24+N24 -> 30 | S24: =$W$10-I24-J24 -> 137
A25: =+A24+1 -> 16 | B25: FLORES GUARDIA CLAUDIA | C25: 39142 | D25: 43789 | E25: =+D25 -> 43789 | G25: =$G$8-E25 -> 345 | H25: 1.25 | I25: =H25*30 -> 37.5 | J25: 30 | K25: 30 | L25: 18 | M25: 7 | N25: 30 | O25: =+G25+I25+J25++K25+L25+M25+N25 -> 497.5 | P25: =(O25/365)*30 -> 40.890411 | Q25: =+'Control de dias gozados 2019'!#REF! -> #REF! | R25: =P25-Q25 -> #REF! | S25: =$W$10-I25-J25 -> 69.5
A26: =+A25+1 -> 17 | B26: FLORES MANTILLA MARIANA | C26: 39142 | D26: 41821 | E26: =+D26 -> 41821 | G26: =$G$8-E26 -> 2313 | H26: 2 | I26: =H26*30 -> 60 | J26: 0 | K26: 30 | L26: 30 | M26: 30 | N26: 30 | O26: =+G26+I26+J26++K26+L26+M26+N26 -> 2493 | P26: =(O26/365)*30 -> 204.90411 | Q26: =+'Control de dias gozados 2019'!#REF! -> #REF! | R26: =P26-Q26 -> #REF! | S26: =$W$10-I26-J26 -> 77
A27: =+A26+1 -> 18 | B27: GOYAS ABRAMONTE, JAVIER ENRIQUE | C27: 39142 | D27: 43556 | E27: =+D27 -> 43556 | G27: =$G$8-E27 -> 578 | H27: 2.1 | I27: =H27*30 -> 63 | J27: 30 | K27: 30 | L27: 30 | M27: 30 | N27: 30 | O27: =+G27+I27+J27++K27+L27+M27+N27 -> 791 | P27: =(O27/365)*30 -> 65.013699 | Q27: =+'Control de dias gozados 2019'!#REF! -> #REF! | R27: =P27-Q27 -> #REF! | S27: =$W$10-I27-J27 -> 44
A28: =+A27+1 -> 19 | B28: GRANDE ALCANTARA GERMAN NICOLAS | D28: 39173 | E28: 40634 | G28: =$G$8-E28 -> 3500 | H28: 2.2 | I28: =H28*30 -> 66 | J28: 30 | K28: 30 | L28: 30 | M28: 30 | N28: 30 | O28: =+G28+I28+J28++K28+L28+M28+N28 -> 3716 | P28: =(O28/365)*30 -> 305.42466 | Q28: =+'Control de dias gozados 2019'!#REF! -> #REF! | R28: =P28-Q28 -> #REF! | S28: =$W$10-I28-J28 -> 41
A29: =+A28+1 -> 20 | B29: GRANDE ALCANTARA MILAGROS M. | D29: 39630 | E29: 40725 | G29: =$G$8-E29 -> 3409 | H29: 2.2 | I29: =H29*30 -> 66 | J29: 15 | K29: 30 | L29: 30 | M29: 30 | N29: 30 | O29: =+G29+I29+J29++K29+L29+M29+N29 -> 3610 | P29: =(O29/365)*30 -> 296.71233 | Q29: =+'Control de dias gozados 2019'!#REF! -> #REF! | R29: =P29-Q29 -> #REF! | S29: =$W$10-I29-J29 -> 56
A30: =+A29+1 -> 21 | B30: GRANDE ALCANTARA PAUL | D30: 40909 | E30: =+D30 -> 40909 | G30: =$G$8-E30 -> 3225 | H30: 2 | I30: =H30*30 -> 60 | J30: 30 | K30: 30 | L30: 30 | M30: 30 | N30: 30 | O30: =+G30+I30+J30++K30+L30+M30+N30 -> 3435 | P30: =(O30/365)*30 -> 282.32877 | Q30: =+'Control de dias gozados 2019'!#REF! -> #REF! | R30: =P30-Q30 -> #REF! | S30: =$W$10-I30-J30 -> 47
A31: =+A30+1 -> 22 | B31: GRANDE ALCANTRA, RAUL NEVADA | D31: 39173 | E31: =+D31 -> 39173 | H31: 2.2 | K31: 30 | O31: =+G31+I31+J31++K31+L31+M31+N31 -> 30 | S31: =$W$10-I31-J31 -> 137
A32: =+A31+1 -> 23 | B32: GRANDE PECEROS DAVID | D32: 43374 | E32: =+D32 -> 43374 | G32: =$G$8-E32 -> 760 | H32: 2 | I32: =H32*30 -> 60 | J32: 30 | K32: 30 | L32: 30 | M32: 30 | N32: 30 | O32: =+G32+I32+J32++K32+L32+M32+N32 -> 970 | P32: =(O32/365)*30 -> 79.726027 | Q32: =+'Control de dias gozados 2019'!#REF! -> #REF! | R32: =P32-Q32 -> #REF! | S32: =$W$10-I32-J32 -> 47
A33: =+A32+1 -> 24 | B33: JUAN PEDRO CRUZ, GIOVANNA PAULA | C33: 39661 | D33: 40969 | E33: =+D33 -> 40969 | G33: =$G$8-E33 -> 3165 | H33: 2.2 | I33: =H33*30 -> 66 | J33: 15 | K33: 30 | L33: 30 | M33: 30 | N33: 30 | O33: =+G33+I33+J33++K33+L33+M33+N33 -> 3366 | P33: =(O33/365)*30 -> 276.65753 | Q33: =+'Control de dias gozados 2019'!#REF! -> #REF! | R33: =P33-Q33 -> #REF! | S33: =$W$10-I33-J33 -> 56
A34: =+A33+1 -> 25 | B34: MENDOZA GARCÍA, ZINCIA | D34: 43466 | E34: =+D34 -> 43466 | G34: =$G$8-E34 -> 668 | H34: 0.5 | I34: =H34*30 -> 15 | J34: 0 | K34: 30 | L34: 2 | M34: 9 | N34: 30 | O34: =+G34+I34+J34++K34+L34+M34+N34 -> 754 | P34: =(O34/365)*30 -> 61.972603 | Q34: =+'Control de dias gozados 2019'!#REF! -> #REF! | R34: =P34-Q34 -> #REF! | S34: =$W$10-I34-J34 -> 122
A35: =+A34+1 -> 26 | B35: OCHOA GUTIERREZ ERICKSON | D35: 43678 | E35: =+D35 -> 43678 | G35: =$G$8-E35 -> 456 | H35: 2.1 | I35: =H35*30 -> 63 | J35: 30 | K35: 30 | L35: 30 | M35: 30 | N35: 30 | O35: =+G35+I35+J35++K35+L35+M35+N35 -> 669 | P35: =(O35/365)*30 -> 54.986301 | Q35: =+'Control de dias gozados 2019'!#REF! -> #REF! | R35: =P35-Q35 -> #REF! | S35: =$W$10-I35-J35 -> 44
A36: =+A35+1 -> 27 | B36: OSCCO GUILLEN EDWIN RAFAEL | D36: 43678 | E36: =+D36 -> 43678 | G36: =$G$8-E36 -> 456 | H36: 2.25 | I36: =H36*30 -> 67.5 | J36: 30 | K36: 30 | L36: 30 | M36: 30 | N36: 30 | O36: =+G36+I36+J36++K36+L36+M36+N36 -> 673.5 | P36: =(O36/365)*30 -> 55.356164 | Q36: =+'Control de dias gozados 2019'!#REF! -> #REF! | R36: =P36-Q36 -> #REF! | S36: =$W$10-I36-J36 -> 39.5
A37: =+A36+1 -> 28 | B37: OSCCO GUILLEN ZORAIDA | C37: 39661 | D37: 41283 | E37: =+D37 -> 41283 | G37: =$G$8-E37 -> 2851 | H37: 3.5 | I37: =H37*30 -> 105 | J37: 30 | K37: 30 | L37: 30 | M37: 30 | N37: 30 | O37: =+G37+I37+J37++K37+L37+M37+N37 -> 3106 | P37: =(O37/365)*30 -> 255.28767 | Q37: =+'Control de dias gozados 2019'!#REF! -> #REF! | R37: =P37-Q37 -> #REF! | S37: =$W$10-I37-J37 -> 2
A38: =+A37+1 -> 29 | B38: PEÑA HERNANDEZ, FERNANDO FAVIAN | D38: 42856 | E38: =+D38 -> 42856 | G38: =$G$8-E38 -> 1278 | H38: 1 | I38: =H38*30 -> 30 | J38: 15 | K38: 30 | L38: 30 | M38: 30 | N38: 30 | O38: =+G38+I38+J38++K38+L38+M38+N38 -> 1443 | P38: =(O38/365)*30 -> 118.60274 | Q38: =+'Control de dias gozados 2019'!#REF! -> #REF! | R38: =P38-Q38 -> #REF! | S38: =$W$10-I38-J38 -> 92
A39: =+A38+1 -> 30 | B39: RAMIREZ ROMAN MARCELO | C39: 39295 | D39: 39630 | E39: 40725 | G39: =$G$8-E39 -> 3409 | H39: 1.6 | I39: =H39*30 -> 48 | J39: 30 | K39: 30 | L39: 30 | M39: 30 | N39: 30 | O39: =+G39+I39+J39++K39+L39+M39+N39 -> 3607 | P39: =(O39/365)*30 -> 296.46575 | Q39: =+'Control de dias gozados 2019'!#REF! -> #REF! | R39: =P39-Q39 -> #REF! | S39: =$W$10-I39-J39 -> 59
A40: =+A39+1 -> 31 | B40: REYNA COSTA CLARA | D40: 43070 | E40: =+D40 -> 43070 | G40: =$G$8-E40 -> 1064 | H40: 1.85 | I40: =H40*30 -> 55.5 | J40: 30 | K40: 30 | L40: 30 | M40: 14 | N40: 30 | O40: =+G40+I40+J40++K40+L40+M40+N40 -> 1253.5 | P40: =(O40/365)*30 -> 103.0274 | Q40: =+'Control de dias gozados 2019'!#REF! -> #REF! | R40: =P40-Q40 -> #REF! | S40: =$W$10-I40-J40 -> 51.5
A41: =+A40+1 -> 32 | B41: TERRONES BECERRA MARISSA | D41: 39630 | E41: 40725 | G41: =$G$8-E41 -> 3409 | H41: 2.2 | I41: =H41*30 -> 66 | J41: 30 | K41: 30 | L41: 30 | M41: 30 | N41: 30 | O41: =+G41+I41+J41++K41+L41+M41+N41 -> 3625 | P41: =(O41/365)*30 -> 297.94521 | Q41: =+'Control de dias gozados 2019'!#REF! -> #REF! | R41: =P41-Q41 -> #REF! | S41: =$W$10-I41-J41 -> 41
A42: =+A41+1 -> 33 | B42: TOMAYLLA TERRONES KATHERINE | D42: 41671 | E42: =+D42 -> 41671 | G42: =$G$8-E42 -> 2463 | H42: 1.5 | I42: =H42*30 -> 45 | J42: 30 | K42: 30 | L42: 30 | M42: 30 | N42: 30 | O42: =+G42+I42+J42++K42+L42+M42+N42 -> 2658 | P42: =(O42/365)*30 -> 218.46575 | Q42: =+'Control de dias gozados 2019'!#REF! -> #REF! | R42: =P42-Q42 -> #REF! | S42: =$W$10-I42-J42 -> 62
A43: =+A42+1 -> 34 | B43: VENEGAS MARCHAND, FRANCISCO MARTIN | D43: 43466 | E43: =+D43 -> 43466 | G43: =$G$8-E43 -> 668 | H43: 1.5 | I43: =H43*30 -> 45 | J43: 30 | K43: 30 | L43: 30 | M43: 30 | N43: 30 | O43: =+G43+I43+J43++K43+L43+M43+N43 -> 863 | P43: =(O43/365)*30 -> 70.931507 | Q43: =+'Control de dias gozados 2019'!#REF! -> #REF! | R43: =P43-Q43 -> #REF! | S43: =$W$10-I43-J43 -> 62
A44: =+A43+1 -> 35 | B44: YNCIO JIMENEZ SILVIA | D44: 43101 | E44: =+D44 -> 43101 | G44: =$G$8-E44 -> 1033 | H44: 2 | I44: =H44*30 -> 60 | J44: 30 | K44: 30 | L44: 30 | M44: 30 | N44: 30 | O44: =+G44+I44+J44++K44+L44+M44+N44 -> 1243 | P44: =(O44/365)*30 -> 102.16438 | Q44: =+'Control de dias gozados 2019'!#REF! -> #REF! | R44: =P44-Q44 -> #REF! | S44: =$W$10-I44-J44 -> 47
A45: =+A44+1 -> 36 | B45: YON UTRILLA LUIS | D45: 43313 | E45: =+D45 -> 43313 | G45: =$G$8-E45 -> 821 | H45: 1.5 | I45: =H45*30 -> 45 | J45: 15 | K45: 30 | L45: 3 | M45: 30 | N45: 30 | O45: =+G45+I45+J45++K45+L45+M45+N45 -> 974 | P45: =(O45/365)*30 -> 80.054795 | Q45: =+'Control de dias gozados 2019'!#REF! -> #REF! | R45: =P45-Q45 -> #REF! | S45: =$W$10-I45-J45 -> 77
A46: =+A45+1 -> 37 | B46: ZURITA PEÑA JOANY | D46: 41913 | E46: =+D46 -> 41913 | G46: =$G$8-E46 -> 2221 | H46: 3.5 | I46: =H46*30 -> 105 | J46: 30 | K46: 30 | L46: 30 | M46: 30 | N46: 30 | O46: =+G46+I46+J46++K46+L46+M46+N46 -> 2476 | P46: =(O46/365)*30 -> 203.50685 | Q46: =+'Control de dias gozados 2019'!#REF! -> #REF! | R46: =P46-Q46 -> #REF! | S46: =$W$10-I46-J46 -> 2
B47: TOTAL | P47: =SUM(P10:P46) -> 5923.3356 | Q47: =SUM(Q10:Q46) -> #REF! | R47: =SUM(R10:R46) -> #REF!

Sheet Licencia sin goce de haber
A7: N° | B7: EMPLEADOS | C7: LICENCIA SIN GOCE DE HABER | D7: PERIODO SIN GOCE DE HABER | G7: OBSERVACIONES
D8: INICIO | E8: FINAL | F8: DIAS
A9: 1 | B9: ARROYO FALLA, VANESSA ALICIA | C9: 01/09/2020 hasta 01/10/2020 - FIRMADO | D9: 44075 | E9: 44105 | F9: =+E9-D9 -> 30 | G9: SE REINCORPORO EL DIA 01/10/20
A10: 2 | B10: DAMBROSIO RIVERO LIZETH STEFANNY | C10: 03/09/2020 hasta 30/11/2020 - FIRMADO | D10: 44077 | E10: 44165 | F10: =+E10-D10 -> 88 | G10: SE REINCORPORO EL DIA 01/12/20
A11: 3 | B11: FLORES GUARDIA CLAUDIA | C11: 19/09/2020 hasta 31/12/2020 - FIRMADO | D11: 44093 | E11: 44130 | F11: =+E11-D11 -> 37 | G11: SE REINCORPORO EL DIA 26/10/20
A12: 4 | B12: MENDOZA GARCÍA, ZINCIA | C12: 03/09/2020 hasta 31/10/2020 - FIRMADO | D12: 44077 | E12: 44127 | F12: =+E12-D12 -> 50 | G12: SE REINCORPORO EL DIA 23/10/20
A13: 5 | B13: REYNA COSTA CLARA | C13: 15/10/2020 hasta 31/12/2020 - FIRMADO | D13: 44119 | E13: 44196 | F13: =+E13-D13 -> 77 | G13: SE REINCORPORO EL DIA 01/02/21
A14: 6 | B14: YON UTRILLA LUIS | C14: 03/09/2020 hasta 31/10/2020 - FIRMADO | D14: 44077 | E14: 44104 | F14: =+E14-D14 -> 27 | G14: SE REINCORPORO EL DIA 30/09/20
A15: 7 | B15: ALHUAY AYESTA, RAMIRO | C15: 22/11/2020 hasta 31/12/2020 - FIRMADO | D15: 44157 | E15: 44196 | F15: =+E15-D15 -> 39 | G15: VACACIONES DESDE 01/10/2020
A16: 8 | B16: GRANDE ALCANTARA MILAGROS M. | C16: 23/03/2021 hasta 14/04/2021 | D16: 44278 | E16: 44300 | F16: =+E16-D16 -> 22 | G16: VACACIONES DESDE EL 12/10/2020 hasta 22/03/2021
A17: 9 | B17: GRANDE ALCANTARA PAUL | C17: 01/03/2021 hasta 14/04/2021 | D17: 44256 | E17: 44300 | F17: =+E17-D17 -> 44 | G17: VACACIONES DESDE EL 01/09/2020 HASTA EL 28/02/2021
A18: 10 | B18: OSCCO GUILLEN EDWIN RAFAEL
A19: 11 | B19: YNCIO JIMENEZ SILVIA
A20: 12 | B20: ALARCON PEREZ LUIS
A21: 13 | B21: ALEJOS TORIBIO, SULELMA MELISA
A22: 14 | B22: ALTAMIRANO SULCA MANUEL
A23: 15 | B23: ASPILCUETA GUTIERREZ KAREN
A24: 16 | B24: BACA WIESSE JOSE ALBERTO
A25: 17 | B25: BALLENA CASTILLO ITALA ADRIANA
A26: 18 | B26: BAUTISTA AYESTA HEBER
A27: 19 | B27: BAUTISTA AYESTA WALTER
A28: 20 | B28: BRIONES RIVERA, RICHARD
A29: 21 | B29: COLETO PASTOR LUIS ENRIQUE
... A42: 34 | B42: ZURITA PEÑA JOANY
B43: TOTAL

Sheet PARA DECLARAR EN SUNAT
A1: ROL DE VACACIONES PARA EL PDT - PLAME 2020
A2: COD. | B2: APELLIDOS Y NOMBRES | C2: FECHA DE INGRESO A RUAG | D2: INGRESO A PLANILLA | E2: VACACIONES PENDIENTES (DÍAS) | F2: AÑO DE VACACIONES PARA EL PLAME | G2: DIAS DE VACACIONES | H2: 2020
H3: ENE | I3: FEB | J3: MAR | K3: ABR | L3: MAY | M3: JUN | N3: JUL | O3: AGO | P3: SEP | Q3: OCT | R3: NOV | S3: DIC
A4: 1 | B4: ACEVEDO LOPEZ, FLOR MARÍA | D4: 43753 | F4: 2019 | G4: 30
A5: 2 | B5: ALARCON PEREZ, LUIS ALBERTO | D5: 42767 | E5: 49 | F5: 2019 | G5: 30
A6: 3 | B6: ALEJOS TORIBIO, SULELMA MELISA | D6: 42979 | E6: 11 | F6: 2019 | G6: 30
A7: 4 | B7: ALHUAY AYESTA, RAMIRO | D7: 41883 | E7: 26 | F7: 2019 | G7: 30
A8: 5 | B8: ALTAMIRANO SULCA, JOSE MANUEL | D8: 43313 | E8: 16 | F8: 2019 | G8: 30
A9: 6 | B9: ANYOSA GOMEZ, JUAN CARLOS | D9: 43760 | F9: 2019 | G9: 30
A10: 7 | B10: ARROYO FALLA, VANESSA ALICIA | C10: 41030 | D10: 43556 | E10: 30 | F10: 2019 | G10: 30
A11: 8 | B11: ASPILCUETA GUTIERREZ KAREN CRISTINA | C11: 41365 | D11: 41365 | E11: 72 | F11: 2019 | G11: 30
A12: 9 | B12: BACA WIESSE, JOSE ALBERTO | C12: 38504 | D12: 40545 | E12: 122 | F12: 2019 | G12: 30
A13: 10 | B13: BALLENA CASTILLO, ITALA ADRIANA | C13: 40210 | D13: 40603 | E13: 61 | F13: 2019 | G13: 30
A14: 11 | B14: BAUTISTA AYESTA, HEBERT | C14: 38565 | D14: 39630 | E14: 175 | F14: 2019 | G14: 30
A15: 12 | B15: BAUTISTA AYESTA, WALTER | C15: 38353 | D15: 39203 | E15: 234 | F15: 2019 | G15: 30
A16: 13 | B16: COLETO PASTOR, LUIS ENRIQUE | C16: 40422 | D16: 40452 | E16: 40 | F16: 2019 | G16: 30
A17: 14 | B17: DAMBROSIO RIVERO , LIZETH STEFANNY | D17: 43466 | E17: 23 | F17: 2019 | G17: 30
A18: 15 | B18: ESPEJO PACHECO URSULA EMELIA | C18: 40238 | D18: 40238 | F18: 2019 | G18: 30
A19: 16 | B19: FLORES GUARDIA, CLAUDIA ALEJANDRA | D19: 43789 | F19: 2019 | G19: 30
A20: 17 | B20: FLORES MANTILLA, MARIANA LORENA | D20: 41821 | E20: 42 | F20: 2019 | G20: 30
A21: 18 | B21: FLORES ORE, DANTE | D21: 43773 | F21: 2019 | G21: 30
A22: 19 | B22: GOYAS ABRAMONTE JAVIER ENRRIQUE | D22: 43556 | F22: 2019 | G22: 30
A23: 20 | B23: GRANDE ALCANTARA, GERMAN NICOLAS | C23: 38473 | D23: 39173 | E23: 240 | F23: 2019 | G23: 30
A24: 21 | B24: GRANDE ALCANTARA, MILAGROS MARGARITA | C24: 39448 | D24: 39630 | E24: 163 | F24: 2019 | G24: 30
A25: 22 | B25: GRANDE ALCANTARA, PAUL JOSEPH | C25: 38961 | D25: 40909 | E25: 152 | F25: 2019 | G25: 30
A26: 23 | B26: GRANDE ALCANTARA, RAUL NEVADA | D26: 39173 | F26: 2019 | G26: 30
A27: 24 | B27: GRANDES PECEROS DAVID | D27: 43374 | E27: 10 | F27: 2019 | G27: 30
A28: 25 | B28: GUZMAN MANTARI, INGRID ISABEL | D28: 43832 | F28: 2019 | G28: 30
A29: 26 | B29: JIMENEZ KAMEL FERNANDO ELIAS | D29: 43374 | F29: 2019 | G29: 30
A30: 27 | B30: JUAN-PEDRO CRUZ,GIOVANNA PAULA | C30: 40483 | D30: 40969 | E30: 45 | F30: 2019 | G30: 30
A31: 28 | B31: LOZANO SOTO, ROY | D31: 43717 | F31: 2019 | G31: 30
A32: 29 | B32: MENDOZA GARCÍA, ZINCIA ISAURA | D32: 43466 | E32: 25 | F32: 2019 | G32: 30
A33: 30 | B33: OCHOA GUTIERREZ, ERICKSON | D33: 43678 | F33: 2019 | G33: 30
A34: 31 | B34: OSCCO GUILEN, EDWIN RAFAEL | D34: 43405 | F34: 2019 | G34: 30
A35: 32 | B35: 0SCCO GUILLEN, ORMINDA ZORAIDA | D35: 41306 | E35: 85 | F35: 2019 | G35: 30
A36: 33 | B36: PEÑA HERNANDEZ, FERNANDO FABIAN | D36: 42856 | E36: 44 | F36: 2019 | G36: 30
A37: 34 | B37: RAMIREZ ROMAN, JOSE MARCELO | C37: 39295 | D37: 39630 | E37: 127 | F37: 2019 | G37: 30
A38: 35 | B38: REYNA ACOSTA, CLARA PATRICIA VICTORIA | D38: 43435 | E38: 34 | F38: 2019 | G38: 30
A39: 36 | B39: ROCA URBANO, INES | D39: 43753 | F39: 2019 | G39: 30
A40: 37 | B40: SAPAICO PICHARD, JOSEPH JESÚS | D40: 43587 | F40: 2019 | G40: 30
A41: 38 | B41: SOTO MAYOR, DIANA | D41: 43832 | F41: 2019 | G41: 30
A42: 39 | B42: TERRONES BECERRA, MARISSA ESTHER | C42: 38899 | D42: 39630 | E42: 106 | F42: 2019 | G42: 30
A43: 40 | B43: TOMAYLLA TERRONES KATHERINE | D43: 41671 | E43: 150 | F43: 2019 | G43: 30
A44: 41 | B44: VELASQUEZ VENTURA, SONIA PILAR | C44: 40210 | D44: 40909 | E44: 88 | F44: 2019 | G44: 30
A45: 42 | B45: VENEGAS MARCHAND FRANCISCO MARTIN | D45: 43466 | E45: 30 | F45: 2019 | G45: 30
A46: 43 | B46: VERA AGUILAR, FIORELLA DIANINY | D46: 43070 | E46: 24 | F46: 2019 | G46: 30
A47: 44 | B47: YNCIO JIMENEZ, SILVIA JANNET | D47: 43101 | E47: 0 | F47: 2019 | G47: 30
A48: 45 | B48: YON UTRILLA, LUIS CARLOS | D48: 43313 | E48: 15 | F48: 2019 | G48: 30
A49: 46 | B49: ZURITA PEÑA, JOANY | C49: 40210 | D49: 41913 | E49: 53 | F49: 2019 | G49: 30

Sheet PARA DECLARAR EN SUNAT (2)
A1: ROL DE VACACIONES PARA EL PDT - PLAME 2020
A2: COD. | B2: ÁREA | C2: APELLIDOS Y NOMBRES | D2: FECHA DE INGRESO A RUAG | E2: INGRESO A PLANILLA | F2: VACACIONES PENDIENTES (DÍAS) | G2: AÑO DE VACACIONES PARA EL PLAME | H2: DIAS DE VACACIONES | I2: 2020
I3: ENE | J3: FEB | K3: MAR | L3: ABR | M3: MAY | N3: JUN | O3: JUL | P3: AGO | Q3: SEP | R3: OCT | S3: NOV | T3: DIC
A4: OPERATIVA
A5: 1 | B5: OPERATIVA | C5: YON UTRILLA, LUIS CARLOS | E5: 43313 | F5: 15 | G5: 2019 | H5: 30
A6: 2 | B6: OPERATIVA | C6: ALTAMIRANO SULCA, JOSE MANUEL | E6: 43313 | F6: 16 | G6: 2019 | H6: 30
A7: 3 | B7: OPERATIVA | C7: DAMBROSIO RIVERO , LIZETH STEFANNY | E7: 43466 | F7: 23 | G7: 2019 | H7: 30
A8: 4 | B8: OPERATIVA | C8: VERA AGUILAR, FIORELLA DIANINY | E8: 43070 | F8: 24 | G8: 2019 | H8: 30
A9: 5 | B9: OPERATIVA | C9: MENDOZA GARCÍA, ZINCIA ISAURA | E9: 43466 | F9: 25 | G9: 2019 | H9: 30
A10: 6 | B10: OPERATIVA | C10: ARROYO FALLA, VANESSA ALICIA | D10: 41030 | E10: 43556 | F10: 30 | G10: 2019 | H10: 30
A11: 7 | B11: OPERATIVA | C11: VENEGAS MARCHAND FRANCISCO MARTIN | E11: 43466 | F11: 30 | G11: 2019 | H11: 30
A12: 8 | B12: OPERATIVA | C12: REYNA ACOSTA, CLARA PATRICIA VICTORIA | E12: 43435 | F12: 34 | G12: 2019 | H12: 30
A13: 9 | B13: OPERATIVA | C13: COLETO PASTOR, LUIS ENRIQUE | D13: 40422 | E13: 40452 | F13: 40 | G13: 2019 | H13: 30
A14: 10 | B14: OPERATIVA | C14: FLORES MANTILLA, MARIANA LORENA | E14: 41821 | F14: 42 | G14: 2019 | H14: 30
A15: 11 | B15: OPERATIVA | C15: ALARCON PEREZ, LUIS ALBERTO | E15: 42767 | F15: 49 | G15: 2019 | H15: 30
A16: 12 | B16: OPERATIVA | C16: BALLENA CASTILLO, ITALA ADRIANA | D16: 40210 | E16: 40603 | F16: 61 | G16: 2019 | H16: 30
A17: 13 | B17: OPERATIVA | C17: RAMIREZ ROMAN, JOSE MARCELO | D17: 39295 | E17: 39630 | F17: 127 | G17: 2019 | H17: 30
A18: 14 | B18: OPERATIVA | C18: GRANDE ALCANTARA, MILAGROS MARGARITA | D18: 39448 | E18: 39630 | F18: 163 | G18: 2019 | H18: 30
A19: 15 | B19: OPERATIVA | C19: ACEVEDO LOPEZ, FLOR MARÍA | E19: 43753 | G19: 2019 | H19: 30
A20: 16 | B20: OPERATIVA | C20: ANYOSA GOMEZ, JUAN CARLOS | E20: 43760 | G20: 2019 | H20: 30
A21: 17 | B21: OPERATIVA | C21: FLORES GUARDIA, CLAUDIA ALEJANDRA | E21: 43789 | G21: 2019 | H21: 30
A22: 18 | B22: OPERATIVA | C22: FLORES ORE, DANTE | E22: 43773 | G22: 2019 | H22: 30
A23: 19 | B23: OPERATIVA | C23: GOYAS ABRAMONTE JAVIER ENRRIQUE | E23: 43556 | G23: 2019 | H23: 30
A24: 20 | B24: OPERATIVA | C24: GRANDE ALCANTARA, RAUL NEVADA | E24: 39173 | G24: 2019 | H24: 30
A25: 21 | B25: OPERATIVA | C25: JIMENEZ KAMEL FERNANDO ELIAS | E25: 43374 | G25: 2019 | H25: 30
A26: 22 | B26: OPERATIVA | C26: LOZANO SOTO, ROY | E26: 43717 | G26: 2019 | H26: 30
A27: 23 | B27: OPERATIVA | C27: OCHOA GUTIERREZ, ERICKSON | E27: 43678 | G27: 2019 | H27: 30
A28: 24 | B28: OPERATIVA | C28: OSCCO GUILEN, EDWIN RAFAEL | E28: 43405 | G28: 2019 | H28: 30
A29: 25 | B29: OPERATIVA | C29: ROCA URBANO, INES | E29: 43753 | G29: 2019 | H29: 30
A30: 26 | B30: OPERATIVA | C30: SAPAICO PICHARD, JOSEPH JESÚS | E30: 43587 | G30: 2019 | H30: 30
A31: OFICINA
A32: ADMINISTRATIVO
A33: 27 | B33: ADMINISTRATIVO | C33: YNCIO JIMENEZ, SILVIA JANNET | E33: 43101 | F33: 0 | G33: 2019 | H33: 30
A34: 28 | B34: ADMINISTRATIVO | C34: GRANDES PECEROS DAVID | E34: 43374 | F34: 10 | G34: 2019 | H34: 30
A35: 29 | B35: ADMINISTRATIVO | C35: BAUTISTA AYESTA, WALTER | D35: 38353 | E35: 39203 | F35: 234 | G35: 2019 | H35: 30
A36: 30 | B36: ADMINISTRATIVO | C36: ESPEJO PACHECO URSULA EMELIA | D36: 40238 | E36: 40238 | G36: 2019 | H36: 30
A37: FINANZAS
A38: 31 | B38: FINANZAS | C38: JUAN-PEDRO CRUZ,GIOVANNA PAULA | D38: 40483 | E38: 40969 | F38: 45 | G38: 2019 | H38: 30
A39: 32 | B39: FINANZAS | C39: GRANDE ALCANTARA, GERMAN NICOLAS | D39: 38473 | E39: 39173 | F39: 240 | G39: 2019 | H39: 30
A40: ASISTENTE DE GERENCIA
A41: 33 | B41: ASISTENTE GERENCIA | C41: ASPILCUETA GUTIERREZ KAREN CRISTINA | D41: 41365 | E41: 41365 | F41: 72 | G41: 2019 | H41: 30
A42: CONTABILIDAD
A43: 34 | B43: CONTABILIDAD | C43: VELASQUEZ VENTURA, SONIA PILAR | D43: 40210 | E43: 40909 | F43: 88 | G43: 2019 | H43: 30
A44: 35 | B44: CONTABILIDAD | C44: BACA WIESSE, JOSE ALBERTO | D44: 38504 | E44: 40545 | F44: 122 | G44: 2019 | H44: 30
A45: 36 | B45: CONTABILIDAD | C45: GUZMAN MANTARI, INGRID ISABEL | E45: 43832 | G45: 2019 | H45: 30
A46: LIMPIEZA
A47: 37 | B47: LIMPIEZA | C47: SOTO MAYOR, DIANA | E47: 43832 | G47: 2019 | H47: 30
A48: LOGISTICA
A49: 38 | B49: LOGÍSTICA | C49: ALHUAY AYESTA, RAMIRO | E49: 41883 | F49: 26 | G49: 2019 | H49: 30
A50: 39 | B50: LOGÍSTICA | C50: GRANDE ALCANTARA, PAUL JOSEPH | D50: 38961 | E50: 40909 | F50: 152 | G50: 2019 | H50: 30
A51: 40 | B51: LOGÍSTICA | C51: BAUTISTA AYESTA, HEBERT | D51: 38565 | E51: 39630 | F51: 175 | G51: 2019 | H51: 30
A52: RECEPCIÓN
A53: 41 | B53: RECEPCION | C53: ALEJOS TPRIBIO, SULELMA MELISA | E53: 42979 | F53: 11 | G53: 2019 | H53: 30
A54: RR.HH.
A55: 42 | B55: RRHH | C55: TERRONES BECERRA, MARISSA ESTHER | D55: 38899 | E55: 39630 | F55: 106 | G55: 2019 | H55: 30
A56: 43 | B56: RRHH | C56: TOMAYLLA TERRONES KATHERINE | E56: 41671 | F56: 150 | G56: 2019 | H56: 30
A57: SEGURIDAD
A58: 44 | B58: SEGURIDAD | C58: ZURITA PEÑA, JOANY | D58: 40210 | E58: 41913 | F58: 53 | G58: 2019 | H58: 30
A59: 45 | B59: SEGURIDAD | C59: 0SCCO GUILLEN, ORMINDA ZORAIDA | E59: 41306 | F59: 85 | G59: 2019 | H59: 30
A60: VENTAS
A61: 46 | B61: VENTAS | C61: PEÑA HERNANDEZ, FERNANDO FABIAN | E61: 42856 | F61: 44 | G61: 2019 | H61: 30

Sheet solicitud de vacaciones
C1: SOLICITUD DE VACACIONES
D4: Fecha de solicitud:
B6: Yo,
B8: Solicito a usted autorización para gozar | F8: días de vacaciones
B10: A partir del: | D10: hasta
E11: .
B12: Correspondiente al período
B14: Jefe Inmediato:
B20: …………………………..………… | D20: …………………………. | F20: ………………………….
B21: Ing. Raúl Grande Alcántara | D21: Jefe Inmediato. | F21: D.N.I.
B22: Gerente General | F22: Colaborador
